Workbook

Sheet Sumario
M3: USD to EU | R3: FALSE
M4: =IFERROR(__xludf.DUMMYFUNCTION("ARRAYFORMULA({NOW(), GOOGLEFINANCE(""CURRENCY:USDEUR"")})"),46288.715450601856) -> 46288.715 | N4: =IFERROR(__xludf.DUMMYFUNCTION("""COMPUTED_VALUE"""),0.87762) -> 0.87762 | R4: FALSE
R5: FALSE
C6: Mês | D6: - | E6: Total EURO | F6: Total USD | G6: Total USD to EUR | H6: Total EUR | I6: Dividendos EU | J6: Dividendos US | K6: TOTAL | R6: FALSE
C7: 1 | D7: janeiro | E7: =JAN!L3 -> 0 | F7: =JAN!M3 -> 62.98 | G7: =F7*$N$4 -> 55.272508 | H7: =E7+G7 -> 55.272508 | I7: =0.04+0.26+0.04+2.53+0.01+0.02+0.23+0.48+0.24+2.53 -> 6.38 | J7: =0.06+0.07+0.06+0.06+0.02+0.03 -> 0.3 | K7: =H7+I7+(J7*$N$4) -> 61.915794 | R7: FALSE
C8: 2 | D8: fevereiro | E8: =FEV!L3 -> 0 | F8: =FEV!M3 -> 65.8 | G8: =F8*$N$4 -> 57.747396 | H8: =E8+G8 -> 57.747396 | I8: =1.87+0.05+0.01 -> 1.93 | J8: =0.11+0.1+0.08+0.12+0.17+0.11+0.15+0.29+0.08+0.08+0.02+0.02 -> 1.33 | K8: =H8+I8+(J8*$N$4) -> 60.844631 | R8: FALSE
C9: 3 | D9: março | E9: =MAR!L3 -> 0 | F9: =MAR!M3 -> 297.24 | G9: =F9*$N$4 -> 260.86377 | H9: =E9+G9 -> 260.86377 | I9: =0.01+0.04+0.01+0.03+0.04+3 -> 3.13 | J9: =0.14+0.2+0.08+0.13+0.02 -> 0.57 | K9: =H9+I9+(J9*$N$4) -> 264.49401 | R9: FALSE
C10: 4 | D10: abril | E10: =ABR!L3 -> 11.31 | F10: =ABR!M3 -> 388.56 | G10: =F10*$N$4 -> 341.00803 | H10: =E10+G10 -> 352.31803 | I10: =0.02+0.07+0.06+0.04+0.05+0.05+0.29+0.02+0.01+0.05+0.78+0.09+0.08+0.03+0.7+12.88+0.61+0.27+0.04+0.64+2.55+0.15+0.14+0.39 -> 20.01 | J10: =0.23+0.2+0.17+0.18+0.17+0.05+0.06+0.25+0.1+0.17+0.17+0.27+0.37+0.03+0.09+0.01 -> 2.52 | K10: =H10+I10+(J10*$N$4) -> 374.53963 | R10: FALSE
C11: 5 | D11: maio | E11: =MAI!L3 -> 0 | F11: =MAI!M3 -> 606.31 | G11: =F11*$N$4 -> 532.10978 | H11: =E11+G11 -> 532.10978 | I11: =0.29+0.01+0.14+0.14+0.15+0.15+0.13+0.15+0.16+3.68+2.38+0.66+0.13+0.31+0.18+0.14+0.02+0.28+0.13+0.13 -> 9.36 | J11: =0.06+0.03+0.18+0.18+0.18+0.14 -> 0.77 | K11: =H11+I11+(J11*$N$4) -> 542.14555 | N11: =J12*N4 -> 0.2018526 | R11: FALSE
C12: 6 | D12: junho | E12: =JUN!L3 -> 0 | F12: =JUN!M3 -> 127.55 | G12: =F12*$N$4 -> 111.94043 | H12: =E12+G12 -> 111.94043 | I12: =0.22+0.06+0.17+0.09+0.17+3.51+0.91+0.15+0.08+0.74 -> 6.1 | J12: =0.19+0.04 -> 0.23 | K12: =H12+I12+(J12*$N$4) -> 118.24228 | R12: FALSE
C13: 7 | D13: julho | E13: =JUL!L3 -> 0 | F13: =JUL!M3 -> -429.78 | G13: =F13*$N$4 -> -377.18352 | H13: =E13+G13 -> -377.18352 | I13: =28.41+0.07+0.07+0.16+0.07+0.07+0.28+0.09+0.04+0.07+0.04+0.15+0.02+0.36+0.06+0.02 -> 29.98 | J13: =0.01+3.05+0.18 -> 3.24 | K13: =H13+I13+(J13*$N$4) -> -344.36003 | R13: FALSE
C14: 8 | D14: agosto | E14: =AGO!L3 -> 76.77 | F14: =AGO!M3 -> -1446.55 | G14: =F14*$N$4 -> -1269.5212 | H14: =E14+G14 -> -1192.7512 | I14: =0.15+0.12+0.14+0.01+0.14+0.18+0.16 -> 0.9 | J14: =0.12+0.11+0.12+0.12+0.11+0.16+0.63+0.57+0.55+0.4+0.41+0.49+0.53+0.54+0.64 -> 5.5 | K14: =H14+I14+(J14*$N$4) -> -1187.0243 | R14: FALSE
C15: 9 | D15: setembro | E15: =SET!L3 -> 0 | F15: =SET!M3 -> -675.07 | G15: =F15*$N$4 -> -592.45493 | H15: =E15+G15 -> -592.45493 | I15: =1.18 -> 1.18 | J15: =18.05 -> 18.05 | K15: =H15+I15+(J15*$N$4) -> -575.43389 | R15: FALSE
C16: 10 | D16: outubro | E16: =OUT!L3 -> 0 | F16: =OUT!M3 -> 0 | G16: =F16*$N$4 -> 0 | H16: =E16+G16 -> 0 | K16: =H16+I16+(J16*$N$4) -> 0 | R16: FALSE
C17: 11 | D17: novembro | E17: =NOV!L3 -> 0 | F17: =NOV!M3 -> 0 | G17: =F17*$N$4 -> 0 | H17: =E17+G17 -> 0 | K17: =H17+I17+(J17*$N$4) -> 0 | R17: FALSE
C18: 12 | D18: dezembro | E18: =DEZ!L3 -> 0 | F18: =DEZ!M3 -> 0 | G18: =F18*$N$4 -> 0 | H18: =E18+G18 -> 0 | K18: =H18+I18+(J18*$N$4) -> 0 | N18: NET | O18: TAX | R18: FALSE
D19: total | E19: =sum(E7:E18) -> 88.08 | F19: =sum(F7:F18) -> -1002.96 | G19: =sum(G7:G18) -> -880.21776 | H19: =E19+G19 -> -792.13776 | I19: =SUM(I7:I18) -> 78.97 | J19: =SUM(J7:J18) -> 32.51 | K19: =SUM(K7:K18) -> -684.63633 | N19: =K19-(K19*28%) -> -492.93816 | O19: =K19*28% -> -191.69817 | R19: FALSE
N20: =N19/12 -> -41.07818 | R20: FALSE
N21: =K19/12 -> -57.053027 | R21: FALSE
R22: FALSE
R23: FALSE
R24: FALSE
R25: FALSE
R26: FALSE
R27: FALSE
R28: FALSE
R29: FALSE
R30: FALSE
R31: FALSE
R32: FALSE
R33: FALSE
... R1001: FALSE

Sheet JAN
K2: Valor Conta | L2: EUR | M2: USD | N2: USD em EU
K3: Total | L3: =sum(E7:E37) -> 0 | M3: =sum(F7:F37) -> 62.98 | N3: =M3*Sumario!N4 -> 55.272508 | O3: =Sumario!N4 -> 0.87762
B4: JAN
B5: Posicao | C5: Data | D5: Preço Abertura | E5: Lucro EU | F5: Lucro USD | G5: Total EUR
H6: Goal
C7: Day 1 | G7: =E7+(F7*$O$3) -> 0 | H7: =G7/$O$9 -> 0 | I7: =315+G7 -> 315
C8: Day 2 | F8: =11.61 -> 11.61 | G8: =E8+(F8*$O$3) -> 10.189168 | H8: =G8/$O$9 -> 0.085589013 | I8: =315+G8 -> 325.18917 | N8: Goal | O8: 2500 | P8: =O8-Sumario!K7 -> 2438.0842
C9: Day 3 | G9: =E9+(F9*$O$3) -> 0 | H9: =G9/$O$9 -> 0 | I9: =315+G9 -> 315 | L9: 7245 | N9: Goal Day | O9: =O8/21 -> 119.04762 | P9: =P8/O8 -> 0.97523368
C10: Day 4 | G10: =E10+(F10*$O$3) -> 0 | H10: =G10/$O$9 -> 0 | I10: =315+G10 -> 315 | L10: =L9+Sumario!K16 -> 7245
C11: Day 5 | F11: =6.15+7.5 -> 13.65 | G11: =E11+(F11*$O$3) -> 11.979513 | H11: =G11/$O$9 -> 0.10062791 | I11: =315+G11 -> 326.97951
C12: Day 6 | F12: =1.65+1.13+2.12+6.45+9.2+9.2 -> 29.75 | G12: =E12+(F12*$O$3) -> 26.109195 | H12: =G12/$O$9 -> 0.21931724 | I12: =315+G12 -> 341.10919
C13: Day 7 | G13: =E13+(F13*$O$3) -> 0 | H13: =G13/$O$9 -> 0 | I13: =315+G13 -> 315
C14: Day 8 | G14: =E14+(F14*$O$3) -> 0 | H14: =G14/$O$9 -> 0 | I14: =315+G14 -> 315
C15: Day 9 | F15: =3.3 -> 3.3 | G15: =E15+(F15*$O$3) -> 2.896146 | H15: =G15/$O$9 -> 0.024327626 | I15: =315+G15 -> 317.89615
C16: Day 10 | G16: =E16+(F16*$O$3) -> 0 | H16: =G16/$O$9 -> 0 | I16: =315+G16 -> 315
C17: Day 11 | G17: =E17+(F17*$O$3) -> 0 | H17: =G17/$O$9 -> 0 | I17: =315+G17 -> 315
C18: Day 12 | G18: =E18+(F18*$O$3) -> 0 | H18: =G18/$O$9 -> 0 | I18: =315+G18 -> 315
C19: Day 13 | G19: =E19+(F19*$O$3) -> 0 | H19: =G19/$O$9 -> 0 | I19: =315+G19 -> 315
C20: Day 14 | G20: =E20+(F20*$O$3) -> 0 | H20: =G20/$O$9 -> 0 | I20: =315+G20 -> 315
C21: Day 15 | G21: =E21+(F21*$O$3) -> 0 | H21: =G21/$O$9 -> 0 | I21: =315+G21 -> 315
C22: Day 16 | F22: =1.43+1.22+2.02 -> 4.67 | G22: =E22+(F22*$O$3) -> 4.0984854 | H22: =G22/$O$9 -> 0.034427277 | I22: =315+G22 -> 319.09849
C23: Day 17 | G23: =E23+(F23*$O$3) -> 0 | H23: =G23/$O$9 -> 0 | I23: =315+G23 -> 315
C24: Day 18 | G24: =E24+(F24*$O$3) -> 0 | H24: =G24/$O$9 -> 0 | I24: =315+G24 -> 315
C25: Day 19 | G25: =E25+(F25*$O$3) -> 0 | H25: =G25/$O$9 -> 0 | I25: =315+G25 -> 315
C26: Day 20 | G26: =E26+(F26*$O$3) -> 0 | H26: =G26/$O$9 -> 0 | I26: =315+G26 -> 315
C27: Day 21 | G27: =E27+(F27*$O$3) -> 0 | H27: =G27/$O$9 -> 0 | I27: =315+G27 -> 315
C28: Day 22 | G28: =E28+(F28*$O$3) -> 0 | H28: =G28/$O$9 -> 0 | I28: =315+G28 -> 315
C29: Day 23 | G29: =E29+(F29*$O$3) -> 0 | H29: =G29/$O$9 -> 0 | I29: =315+G29 -> 315
C30: Day 24 | G30: =E30+(F30*$O$3) -> 0 | H30: =G30/$O$9 -> 0 | I30: =315+G30 -> 315
C31: Day 25 | G31: =E31+(F31*$O$3) -> 0 | H31: =G31/$O$9 -> 0 | I31: =315+G31 -> 315
C32: Day 26 | G32: =E32+(F32*$O$3) -> 0 | H32: =G32/$O$9 -> 0 | I32: =315+G32 -> 315
C33: Day 27 | G33: =E33+(F33*$O$3) -> 0 | H33: =G33/$O$9 -> 0 | I33: =315+G33 -> 315
C34: Day 28 | G34: =E34+(F34*$O$3) -> 0 | H34: =G34/$O$9 -> 0 | I34: =315+G34 -> 315
... C37: Day 31 | G37: =E37+(F37*$O$3) -> 0 | H37: =G37/$O$9 -> 0 | I37: =315+G37 -> 315

Sheet FEV
K2: Valor Conta | L2: EUR | M2: USD | N2: USD em EU
K3: Total | L3: =sum(E7:E37) -> 0 | M3: =sum(F7:F37) -> 65.8 | N3: =M3*Sumario!N4 -> 57.747396 | O3: =Sumario!N4 -> 0.87762
B4: FEV
B5: Posicao | C5: Data | D5: Preço Abertura | E5: Lucro EU | F5: Lucro USD | G5: Total EUR
H6: Goal
C7: Day 1 | G7: =E7+(F7*$O$3) -> 0 | H7: =G7/$O$9 -> 0 | I7: =315+G7 -> 315
C8: Day 2 | G8: =E8+(F8*$O$3) -> 0 | H8: =G8/$O$9 -> 0 | I8: =315+G8 -> 315 | N8: Goal | O8: 2500 | P8: =O8-Sumario!K8 -> 2439.1554
C9: Day 3 | F9: =4.06 -> 4.06 | G9: =E9+(F9*$O$3) -> 3.5631372 | H9: =G9/$O$9 -> 0.029930352 | I9: =315+G9 -> 318.56314 | L9: 6300 | N9: Goal Day | O9: =O8/21 -> 119.04762 | P9: =P8/O8 -> 0.97566215
C10: Day 4 | G10: =E10+(F10*$O$3) -> 0 | H10: =G10/$O$9 -> 0 | I10: =315+G10 -> 315 | L10: =L9+Sumario!K8 -> 6360.8446
C11: Day 5 | G11: =E11+(F11*$O$3) -> 0 | H11: =G11/$O$9 -> 0 | I11: =315+G11 -> 315
C12: Day 6 | F12: =0.91+0.33+1.52+0.57+0.63+1.39 -> 5.35 | G12: =E12+(F12*$O$3) -> 4.695267 | H12: =G12/$O$9 -> 0.039440243 | I12: =315+G12 -> 319.69527
C13: Day 7 | G13: =E13+(F13*$O$3) -> 0 | H13: =G13/$O$9 -> 0 | I13: =315+G13 -> 315
C14: Day 8 | G14: =E14+(F14*$O$3) -> 0 | H14: =G14/$O$9 -> 0 | I14: =315+G14 -> 315
C15: Day 9 | G15: =E15+(F15*$O$3) -> 0 | H15: =G15/$O$9 -> 0 | I15: =315+G15 -> 315
C16: Day 10 | F16: =4+5.48 -> 9.48 | G16: =E16+(F16*$O$3) -> 8.3198376 | H16: =G16/$O$9 -> 0.069886636 | I16: =315+G16 -> 323.31984
C17: Day 11 | G17: =E17+(F17*$O$3) -> 0 | H17: =G17/$O$9 -> 0 | I17: =315+G17 -> 315
C18: Day 12 | G18: =E18+(F18*$O$3) -> 0 | H18: =G18/$O$9 -> 0 | I18: =315+G18 -> 315
C19: Day 13 | G19: =E19+(F19*$O$3) -> 0 | H19: =G19/$O$9 -> 0 | I19: =315+G19 -> 315
C20: Day 14 | G20: =E20+(F20*$O$3) -> 0 | H20: =G20/$O$9 -> 0 | I20: =315+G20 -> 315
C21: Day 15 | G21: =E21+(F21*$O$3) -> 0 | H21: =G21/$O$9 -> 0 | I21: =315+G21 -> 315
C22: Day 16 | G22: =E22+(F22*$O$3) -> 0 | H22: =G22/$O$9 -> 0 | I22: =315+G22 -> 315
C23: Day 17 | G23: =E23+(F23*$O$3) -> 0 | H23: =G23/$O$9 -> 0 | I23: =315+G23 -> 315
C24: Day 18 | G24: =E24+(F24*$O$3) -> 0 | H24: =G24/$O$9 -> 0 | I24: =315+G24 -> 315
C25: Day 19 | F25: =3.36+1.72 -> 5.08 | G25: =E25+(F25*$O$3) -> 4.4583096 | H25: =G25/$O$9 -> 0.037449801 | I25: =315+G25 -> 319.45831
C26: Day 20 | G26: =E26+(F26*$O$3) -> 0 | H26: =G26/$O$9 -> 0 | I26: =315+G26 -> 315
C27: Day 21 | G27: =E27+(F27*$O$3) -> 0 | H27: =G27/$O$9 -> 0 | I27: =315+G27 -> 315
C28: Day 22 | G28: =E28+(F28*$O$3) -> 0 | H28: =G28/$O$9 -> 0 | I28: =315+G28 -> 315
C29: Day 23 | G29: =E29+(F29*$O$3) -> 0 | H29: =G29/$O$9 -> 0 | I29: =315+G29 -> 315
C30: Day 24 | G30: =E30+(F30*$O$3) -> 0 | H30: =G30/$O$9 -> 0 | I30: =315+G30 -> 315
C31: Day 25 | G31: =E31+(F31*$O$3) -> 0 | H31: =G31/$O$9 -> 0 | I31: =315+G31 -> 315
C32: Day 26 | F32: =16.07+14.62+11.14 -> 41.83 | G32: =E32+(F32*$O$3) -> 36.710845 | H32: =G32/$O$9 -> 0.30837109 | I32: =315+G32 -> 351.71084
C33: Day 27 | G33: =E33+(F33*$O$3) -> 0 | H33: =G33/$O$9 -> 0 | I33: =315+G33 -> 315
C34: Day 28 | G34: =E34+(F34*$O$3) -> 0 | H34: =G34/$O$9 -> 0 | I34: =315+G34 -> 315
C35: Day 29 | G35: =E35+(F35*$O$3) -> 0 | H35: =G35/$O$9 -> 0 | I35: =315+G35 -> 315
C36: Day 30 | G36: =E36+(F36*$O$3) -> 0 | H36: =G36/$O$9 -> 0 | I36: =315+G36 -> 315
C37: Day 31 | G37: =E37+(F37*$O$3) -> 0 | H37: =G37/$O$9 -> 0 | I37: =315+G37 -> 315

Sheet MAR
K2: Valor Conta | L2: EUR | M2: USD | N2: USD em EU
K3: Total | L3: =sum(E7:E37) -> 0 | M3: =sum(F7:F37) -> 297.24 | N3: =M3*Sumario!N4 -> 260.86377 | O3: =Sumario!N4 -> 0.87762
B4: MAR
B5: Posicao | C5: Data | D5: Preço Abertura | E5: Lucro EU | F5: Lucro USD | G5: Total EUR
H6: Goal
C7: Day 1 | G7: =E7+(F7*$O$3) -> 0 | H7: =G7/$O$9 -> 0 | I7: =315+G7 -> 315
C8: Day 2 | F8: =20.55+1.25 -> 21.8 | G8: =E8+(F8*$O$3) -> 19.132116 | H8: =G8/$O$9 -> 0.16070977 | I8: =315+G8 -> 334.13212 | N8: Goal | O8: 2500 | P8: =O8-Sumario!K9 -> 2235.506
C9: Day 3 | F9: =7.44+1.37 -> 8.81 | G9: =E9+(F9*$O$3) -> 7.7318322 | H9: =G9/$O$9 -> 0.06494739 | I9: =315+G9 -> 322.73183 | L9: 6930 | N9: Goal Day | O9: =O8/21 -> 119.04762 | P9: =P8/O8 -> 0.8942024
C10: Day 4 | F10: =5.96+5.23+6.43 -> 17.62 | G10: =E10+(F10*$O$3) -> 15.463664 | H10: =G10/$O$9 -> 0.12989478 | I10: =315+G10 -> 330.46366 | L10: =L9+Sumario!K9 -> 7194.494
C11: Day 5 | F11: =7.5 -> 7.5 | G11: =E11+(F11*$O$3) -> 6.58215 | H11: =G11/$O$9 -> 0.05529006 | I11: =315+G11 -> 321.58215
C12: Day 6 | F12: =21.87+18.23 -> 40.1 | G12: =E12+(F12*$O$3) -> 35.192562 | H12: =G12/$O$9 -> 0.29561752 | I12: =315+G12 -> 350.19256
C13: Day 7 | G13: =E13+(F13*$O$3) -> 0 | H13: =G13/$O$9 -> 0 | I13: =315+G13 -> 315
C14: Day 8 | G14: =E14+(F14*$O$3) -> 0 | H14: =G14/$O$9 -> 0 | I14: =315+G14 -> 315
C15: Day 9 | G15: =E15+(F15*$O$3) -> 0 | H15: =G15/$O$9 -> 0 | I15: =315+G15 -> 315
C16: Day 10 | F16: =25.88+19.05+4.77+13.03 -> 62.73 | G16: =E16+(F16*$O$3) -> 55.053103 | H16: =G16/$O$9 -> 0.46244606 | I16: =315+G16 -> 370.0531
C17: Day 11 | G17: =E17+(F17*$O$3) -> 0 | H17: =G17/$O$9 -> 0 | I17: =315+G17 -> 315
C18: Day 12 | G18: =E18+(F18*$O$3) -> 0 | H18: =G18/$O$9 -> 0 | I18: =315+G18 -> 315
C19: Day 13 | F19: =9.1+0.97+9.12+0.96+4.42+5.04 -> 29.61 | G19: =E19+(F19*$O$3) -> 25.986328 | H19: =G19/$O$9 -> 0.21828516 | I19: =315+G19 -> 340.98633
C20: Day 14 | G20: =E20+(F20*$O$3) -> 0 | H20: =G20/$O$9 -> 0 | I20: =315+G20 -> 315
C21: Day 15 | G21: =E21+(F21*$O$3) -> 0 | H21: =G21/$O$9 -> 0 | I21: =315+G21 -> 315
C22: Day 16 | F22: =3.11 -> 3.11 | G22: =E22+(F22*$O$3) -> 2.7293982 | H22: =G22/$O$9 -> 0.022926945 | I22: =315+G22 -> 317.7294
C23: Day 17 | F23: =7.49+2.49 -> 9.98 | G23: =E23+(F23*$O$3) -> 8.7586476 | H23: =G23/$O$9 -> 0.07357264 | I23: =315+G23 -> 323.75865
C24: Day 18 | F24: =4.66+2.22 -> 6.88 | G24: =E24+(F24*$O$3) -> 6.0380256 | H24: =G24/$O$9 -> 0.050719415 | I24: =315+G24 -> 321.03803
C25: Day 19 | G25: =E25+(F25*$O$3) -> 0 | H25: =G25/$O$9 -> 0 | I25: =315+G25 -> 315
C26: Day 20 | G26: =E26+(F26*$O$3) -> 0 | H26: =G26/$O$9 -> 0 | I26: =315+G26 -> 315
C27: Day 21 | G27: =E27+(F27*$O$3) -> 0 | H27: =G27/$O$9 -> 0 | I27: =315+G27 -> 315
C28: Day 22 | G28: =E28+(F28*$O$3) -> 0 | H28: =G28/$O$9 -> 0 | I28: =315+G28 -> 315
C29: Day 23 | G29: =E29+(F29*$O$3) -> 0 | H29: =G29/$O$9 -> 0 | I29: =315+G29 -> 315
C30: Day 24 | F30: =35.7 -> 35.7 | G30: =E30+(F30*$O$3) -> 31.331034 | H30: =G30/$O$9 -> 0.26318069 | I30: =315+G30 -> 346.33103
C31: Day 25 | G31: =E31+(F31*$O$3) -> 0 | H31: =G31/$O$9 -> 0 | I31: =315+G31 -> 315
C32: Day 26 | G32: =E32+(F32*$O$3) -> 0 | H32: =G32/$O$9 -> 0 | I32: =315+G32 -> 315
C33: Day 27 | G33: =E33+(F33*$O$3) -> 0 | H33: =G33/$O$9 -> 0 | I33: =315+G33 -> 315
C34: Day 28 | G34: =E34+(F34*$O$3) -> 0 | H34: =G34/$O$9 -> 0 | I34: =315+G34 -> 315
C35: Day 29 | G35: =E35+(F35*$O$3) -> 0 | H35: =G35/$O$9 -> 0 | I35: =315+G35 -> 315
C36: Day 30 | G36: =E36+(F36*$O$3) -> 0 | H36: =G36/$O$9 -> 0 | I36: =315+G36 -> 315
C37: Day 31 | F37: =38.55+8.11+6.74 -> 53.4 | G37: =E37+(F37*$O$3) -> 46.864908 | H37: =G37/$O$9 -> 0.39366523 | I37: =315+G37 -> 361.86491

Sheet ABR
K2: Valor Conta | L2: EUR | M2: USD | N2: USD em EU
K3: Total | L3: =sum(E7:E37) -> 11.31 | M3: =sum(F7:F37) -> 388.56 | N3: =M3*Sumario!N4 -> 341.00803 | O3: =Sumario!N4 -> 0.87762
B4: ABR
B5: Posicao | C5: Data | D5: Preço Abertura | E5: Lucro EU | F5: Lucro USD | G5: Total EUR
H6: Goal
C7: Day 1 | F7: =13.05+2.54 -> 15.59 | G7: =E7+(F7*$O$3) -> 13.682096 | H7: =G7/$O$9 -> 0.1149296 | I7: =315+G7 -> 328.6821
C8: Day 2 | F8: =5.72+3.96+9.37+1.37+3.16 -> 23.58 | G8: =E8+(F8*$O$3) -> 20.69428 | H8: =G8/$O$9 -> 0.17383195 | I8: =315+G8 -> 335.69428 | N8: Goal | O8: 2500 | P8: =O8-Sumario!K10 -> 2125.4604
C9: Day 3 | G9: =E9+(F9*$O$3) -> 0 | H9: =G9/$O$9 -> 0 | I9: =315+G9 -> 315 | L9: 6615 | N9: Goal Day | O9: =O8/21 -> 119.04762 | P9: =P8/O8 -> 0.85018415
C10: Day 4 | G10: =E10+(F10*$O$3) -> 0 | H10: =G10/$O$9 -> 0 | I10: =315+G10 -> 315 | L10: =L9+Sumario!K10 -> 6989.5396
C11: Day 5 | G11: =E11+(F11*$O$3) -> 0 | H11: =G11/$O$9 -> 0 | I11: =315+G11 -> 315
C12: Day 6 | F12: =0.6+6.82+1.43+3.06+2.69+2.18+12.21+1.31+1.44+4.05+0.57+0.87+2.4 -> 39.63 | G12: =E12+(F12*$O$3) -> 34.780081 | H12: =G12/$O$9 -> 0.29215268 | I12: =315+G12 -> 349.78008
C13: Day 7 | F13: =3.94+1.5+0.74+6.7+2+1.5+2.46+2.25+1.36 -> 22.45 | G13: =E13+(F13*$O$3) -> 19.702569 | H13: =G13/$O$9 -> 0.16550158 | I13: =315+G13 -> 334.70257
C14: Day 8 | E14: =2.15 -> 2.15 | F14: =1.51+6.28+8.74+3.85+0.96+3.34+3.7+0.13+3.72+0.11+2.59+0.03+4.78+3.65+3.28 -> 46.67 | G14: =E14+(F14*$O$3) -> 43.108525 | H14: =G14/$O$9 -> 0.36211161 | I14: =315+G14 -> 358.10853
C15: Day 9 | F15: =5.1+3.9+11.35+4.63+0.58+0.05+0.62 -> 26.23 | G15: =E15+(F15*$O$3) -> 23.019973 | H15: =G15/$O$9 -> 0.19336777 | I15: =315+G15 -> 338.01997
C16: Day 10 | F16: =1.98+2.4 -> 4.38 | G16: =E16+(F16*$O$3) -> 3.8439756 | H16: =G16/$O$9 -> 0.032289395 | I16: =315+G16 -> 318.84398
C17: Day 11 | G17: =E17+(F17*$O$3) -> 0 | H17: =G17/$O$9 -> 0 | I17: =315+G17 -> 315
C18: Day 12 | G18: =E18+(F18*$O$3) -> 0 | H18: =G18/$O$9 -> 0 | I18: =315+G18 -> 315
C19: Day 13 | F19: =2.46+2.1+3.1+12.32+1.3+7.05+6.59+3.78 -> 38.7 | G19: =E19+(F19*$O$3) -> 33.963894 | H19: =G19/$O$9 -> 0.28529671 | I19: =315+G19 -> 348.96389
C20: Day 14 | F20: =2.41+2.8+14.43 -> 19.64 | G20: =E20+(F20*$O$3) -> 17.236457 | H20: =G20/$O$9 -> 0.14478624 | I20: =315+G20 -> 332.23646
C21: Day 15 | F21: =8.73+5.49+12.21+8.21 -> 34.64 | G21: =E21+(F21*$O$3) -> 30.400757 | H21: =G21/$O$9 -> 0.25536636 | I21: =315+G21 -> 345.40076
C22: Day 16 | F22: =5+34.8+9.82+12.38 -> 62 | G22: =E22+(F22*$O$3) -> 54.41244 | H22: =G22/$O$9 -> 0.4570645 | I22: =315+G22 -> 369.41244
C23: Day 17 | F23: =3.84+5.1+2.64 -> 11.58 | G23: =E23+(F23*$O$3) -> 10.16284 | H23: =G23/$O$9 -> 0.085367853 | I23: =315+G23 -> 325.16284
C24: Day 18 | G24: =E24+(F24*$O$3) -> 0 | H24: =G24/$O$9 -> 0 | I24: =315+G24 -> 315
C25: Day 19 | G25: =E25+(F25*$O$3) -> 0 | H25: =G25/$O$9 -> 0 | I25: =315+G25 -> 315
C26: Day 20 | F26: =9.1+0.48+0.5+0.5+1.18 -> 11.76 | G26: =E26+(F26*$O$3) -> 10.320811 | H26: =G26/$O$9 -> 0.086694814 | I26: =315+G26 -> 325.32081
C27: Day 21 | F27: =0.82+0.2+8.6+8.6+2.35 -> 20.57 | G27: =E27+(F27*$O$3) -> 18.052643 | H27: =G27/$O$9 -> 0.1516422 | I27: =315+G27 -> 333.05264
C28: Day 22 | F28: =4.22 -> 4.22 | G28: =E28+(F28*$O$3) -> 3.7035564 | H28: =G28/$O$9 -> 0.031109874 | I28: =315+G28 -> 318.70356
C29: Day 23 | G29: =E29+(F29*$O$3) -> 0 | H29: =G29/$O$9 -> 0 | I29: =315+G29 -> 315
C30: Day 24 | G30: =E30+(F30*$O$3) -> 0 | H30: =G30/$O$9 -> 0 | I30: =315+G30 -> 315
C31: Day 25 | G31: =E31+(F31*$O$3) -> 0 | H31: =G31/$O$9 -> 0 | I31: =315+G31 -> 315
C32: Day 26 | G32: =E32+(F32*$O$3) -> 0 | H32: =G32/$O$9 -> 0 | I32: =315+G32 -> 315
C33: Day 27 | E33: =0.22+0.76+6.09 -> 7.07 | G33: =E33+(F33*$O$3) -> 7.07 | H33: =G33/$O$9 -> 0.059388 | I33: =315+G33 -> 322.07
C34: Day 28 | G34: =E34+(F34*$O$3) -> 0 | H34: =G34/$O$9 -> 0 | I34: =315+G34 -> 315
C35: Day 29 | G35: =E35+(F35*$O$3) -> 0 | H35: =G35/$O$9 -> 0 | I35: =315+G35 -> 315
C36: Day 30 | E36: =2.09 -> 2.09 | F36: =5.26+1.66 -> 6.92 | G36: =E36+(F36*$O$3) -> 8.1631304 | H36: =G36/$O$9 -> 0.068570295 | I36: =315+G36 -> 323.16313
C37: Day 31 | G37: =E37+(F37*$O$3) -> 0 | H37: =G37/$O$9 -> 0 | I37: =315+G37 -> 315

Sheet MAI
K2: Valor Conta | L2: EUR | M2: USD | N2: USD em EU
K3: Total | L3: =sum(E7:E37) -> 0 | M3: =sum(F7:F37) -> 606.31 | N3: =M3*Sumario!N4 -> 532.10978 | O3: =Sumario!N4 -> 0.87762
B4: MAI
B5: Posicao | C5: Data | D5: Preço Abertura | E5: Lucro EU | F5: Lucro USD | G5: Total EUR
H6: Goal
C7: Day 1 | F7: =2.61+2.68+4.62 -> 9.91 | G7: =E7+(F7*$O$3) -> 8.6972142 | H7: =G7/$O$9 -> 0.073056599 | I7: =315+G7 -> 323.69721
C8: Day 2 | G8: =E8+(F8*$O$3) -> 0 | H8: =G8/$O$9 -> 0 | I8: =315+G8 -> 315 | N8: Goal | O8: 2500 | P8: =O8-Sumario!K11 -> 1957.8545
C9: Day 3 | G9: =E9+(F9*$O$3) -> 0 | H9: =G9/$O$9 -> 0 | I9: =315+G9 -> 315 | L9: 6300 | N9: Goal Day | O9: =O8/21 -> 119.04762 | P9: =P8/O8 -> 0.78314178
C10: Day 4 | F10: =4.17+19.3+9.6 -> 33.07 | G10: =E10+(F10*$O$3) -> 29.022893 | H10: =G10/$O$9 -> 0.2437923 | I10: =315+G10 -> 344.02289 | L10: =L9+Sumario!K11 -> 6842.1456
C11: Day 5 | G11: =E11+(F11*$O$3) -> 0 | H11: =G11/$O$9 -> 0 | I11: =315+G11 -> 315
C12: Day 6 | F12: =18.98+3.03+5.1 -> 27.11 | G12: =E12+(F12*$O$3) -> 23.792278 | H12: =G12/$O$9 -> 0.19985514 | I12: =315+G12 -> 338.79228
C13: Day 7 | F13: =7.6+8.87+7.74+9.36+4.68+8.11+4.52+4.86 -> 55.74 | G13: =E13+(F13*$O$3) -> 48.918539 | H13: =G13/$O$9 -> 0.41091573 | I13: =315+G13 -> 363.91854
C14: Day 8 | F14: =27.52 -> 27.52 | G14: =E14+(F14*$O$3) -> 24.152102 | H14: =G14/$O$9 -> 0.20287766 | I14: =315+G14 -> 339.1521
C15: Day 9 | G15: =E15+(F15*$O$3) -> 0 | H15: =G15/$O$9 -> 0 | I15: =315+G15 -> 315
C16: Day 10 | G16: =E16+(F16*$O$3) -> 0 | H16: =G16/$O$9 -> 0 | I16: =315+G16 -> 315
C17: Day 11 | F17: =111.5+8.89+22.35 -> 142.74 | G17: =E17+(F17*$O$3) -> 125.27148 | H17: =G17/$O$9 -> 1.0522804 | I17: =315+G17 -> 440.27148
C18: Day 12 | F18: =6+4.79+1.07+1.16+10.25+7.67+2.11 -> 33.05 | G18: =E18+(F18*$O$3) -> 29.005341 | H18: =G18/$O$9 -> 0.24364486 | I18: =315+G18 -> 344.00534
C19: Day 13 | F19: =0.44+1.16+7.99+16.2 -> 25.79 | G19: =E19+(F19*$O$3) -> 22.63382 | H19: =G19/$O$9 -> 0.19012409 | I19: =315+G19 -> 337.63382
C20: Day 14 | F20: =4.42+7.84+6.07+11.4 -> 29.73 | G20: =E20+(F20*$O$3) -> 26.091643 | H20: =G20/$O$9 -> 0.2191698 | I20: =315+G20 -> 341.09164
C21: Day 15 | F21: =12.1+13.45+1.1+2.52+0.48 -> 29.65 | G21: =E21+(F21*$O$3) -> 26.021433 | H21: =G21/$O$9 -> 0.21858004 | I21: =315+G21 -> 341.02143
C22: Day 16 | G22: =E22+(F22*$O$3) -> 0 | H22: =G22/$O$9 -> 0 | I22: =315+G22 -> 315
C23: Day 17 | G23: =E23+(F23*$O$3) -> 0 | H23: =G23/$O$9 -> 0 | I23: =315+G23 -> 315
C24: Day 18 | F24: =9.19 -> 9.19 | G24: =E24+(F24*$O$3) -> 8.0653278 | H24: =G24/$O$9 -> 0.067748754 | I24: =315+G24 -> 323.06533
C25: Day 19 | G25: =E25+(F25*$O$3) -> 0 | H25: =G25/$O$9 -> 0 | I25: =315+G25 -> 315
C26: Day 20 | G26: =E26+(F26*$O$3) -> 0 | H26: =G26/$O$9 -> 0 | I26: =315+G26 -> 315
C27: Day 21 | F27: =52.14 -> 52.14 | G27: =E27+(F27*$O$3) -> 45.759107 | H27: =G27/$O$9 -> 0.3843765 | I27: =315+G27 -> 360.75911
C28: Day 22 | F28: =7.93+15.81 -> 23.74 | G28: =E28+(F28*$O$3) -> 20.834699 | H28: =G28/$O$9 -> 0.17501147 | I28: =315+G28 -> 335.8347
C29: Day 23 | G29: =E29+(F29*$O$3) -> 0 | H29: =G29/$O$9 -> 0 | I29: =315+G29 -> 315
C30: Day 24 | G30: =E30+(F30*$O$3) -> 0 | H30: =G30/$O$9 -> 0 | I30: =315+G30 -> 315
C31: Day 25 | G31: =E31+(F31*$O$3) -> 0 | H31: =G31/$O$9 -> 0 | I31: =315+G31 -> 315
C32: Day 26 | F32: =18.68 -> 18.68 | G32: =E32+(F32*$O$3) -> 16.393942 | H32: =G32/$O$9 -> 0.13770911 | I32: =315+G32 -> 331.39394
C33: Day 27 | G33: =E33+(F33*$O$3) -> 0 | H33: =G33/$O$9 -> 0 | I33: =315+G33 -> 315
C34: Day 28 | F34: =8.34+7.76+6.34+7.2+12.57+7.06+14.54 -> 63.81 | G34: =E34+(F34*$O$3) -> 56.000932 | H34: =G34/$O$9 -> 0.47040783 | I34: =315+G34 -> 371.00093
C35: Day 29 | F35: =2.16+3.05+2.22+1.41+8.32+1.94+5.34 -> 24.44 | G35: =E35+(F35*$O$3) -> 21.449033 | H35: =G35/$O$9 -> 0.18017188 | I35: =315+G35 -> 336.44903
C36: Day 30 | G36: =E36+(F36*$O$3) -> 0 | H36: =G36/$O$9 -> 0 | I36: =315+G36 -> 315
C37: Day 31 | G37: =E37+(F37*$O$3) -> 0 | H37: =G37/$O$9 -> 0 | I37: =315+G37 -> 315

Sheet JUN
K2: Valor Conta | L2: EUR | M2: USD | N2: USD em EU
K3: Total | L3: =sum(E7:E37) -> 0 | M3: =sum(F7:F37) -> 127.55 | N3: =M3*Sumario!N4 -> 111.94043 | O3: =Sumario!N4 -> 0.87762
B4: JUN
B5: Posicao | C5: Data | D5: Preço Abertura | E5: Lucro EU | F5: Lucro USD | G5: Total EUR
H6: Goal
C7: Day 1 | F7: =6.02+14.31+8.88+1.5 -> 30.71 | G7: =E7+(F7*$O$3) -> 26.95171 | H7: =G7/$O$9 -> 0.22639437 | I7: =315+G7 -> 341.95171
C8: Day 2 | G8: =E8+(F8*$O$3) -> 0 | H8: =G8/$O$9 -> 0 | I8: =315+G8 -> 315 | N8: Goal | O8: 2500 | P8: =O8-Sumario!K12 -> 2381.7577
C9: Day 3 | G9: =E9+(F9*$O$3) -> 0 | H9: =G9/$O$9 -> 0 | I9: =315+G9 -> 315 | L9: 7245 | N9: Goal Day | O9: =O8/21 -> 119.04762 | P9: =P8/O8 -> 0.95270309
C10: Day 4 | G10: =E10+(F10*$O$3) -> 0 | H10: =G10/$O$9 -> 0 | I10: =315+G10 -> 315 | L10: =L9+Sumario!K12 -> 7363.2423
C11: Day 5 | G11: =E11+(F11*$O$3) -> 0 | H11: =G11/$O$9 -> 0 | I11: =315+G11 -> 315
C12: Day 6 | G12: =E12+(F12*$O$3) -> 0 | H12: =G12/$O$9 -> 0 | I12: =315+G12 -> 315
C13: Day 7 | G13: =E13+(F13*$O$3) -> 0 | H13: =G13/$O$9 -> 0 | I13: =315+G13 -> 315
C14: Day 8 | G14: =E14+(F14*$O$3) -> 0 | H14: =G14/$O$9 -> 0 | I14: =315+G14 -> 315
C15: Day 9 | F15: =11.4 -> 11.4 | G15: =E15+(F15*$O$3) -> 10.004868 | H15: =G15/$O$9 -> 0.084040891 | I15: =315+G15 -> 325.00487
C16: Day 10 | F16: =28.49 -> 28.49 | G16: =E16+(F16*$O$3) -> 25.003394 | H16: =G16/$O$9 -> 0.21002851 | I16: =315+G16 -> 340.00339
C17: Day 11 | G17: =E17+(F17*$O$3) -> 0 | H17: =G17/$O$9 -> 0 | I17: =315+G17 -> 315
C18: Day 12 | F18: =9.78+1.97 -> 11.75 | G18: =E18+(F18*$O$3) -> 10.312035 | H18: =G18/$O$9 -> 0.086621094 | I18: =315+G18 -> 325.31203
C19: Day 13 | G19: =E19+(F19*$O$3) -> 0 | H19: =G19/$O$9 -> 0 | I19: =315+G19 -> 315
C20: Day 14 | G20: =E20+(F20*$O$3) -> 0 | H20: =G20/$O$9 -> 0 | I20: =315+G20 -> 315
C21: Day 15 | F21: =3.3+7.01 -> 10.31 | G21: =E21+(F21*$O$3) -> 9.0482622 | H21: =G21/$O$9 -> 0.076005402 | I21: =315+G21 -> 324.04826
C22: Day 16 | G22: =E22+(F22*$O$3) -> 0 | H22: =G22/$O$9 -> 0 | I22: =315+G22 -> 315
C23: Day 17 | F23: =7.42+20.45+3.9+0.76+2.36 -> 34.89 | G23: =E23+(F23*$O$3) -> 30.620162 | H23: =G23/$O$9 -> 0.25720936 | I23: =315+G23 -> 345.62016
C24: Day 18 | G24: =E24+(F24*$O$3) -> 0 | H24: =G24/$O$9 -> 0 | I24: =315+G24 -> 315
C25: Day 19 | G25: =E25+(F25*$O$3) -> 0 | H25: =G25/$O$9 -> 0 | I25: =315+G25 -> 315
C26: Day 20 | G26: =E26+(F26*$O$3) -> 0 | H26: =G26/$O$9 -> 0 | I26: =315+G26 -> 315
C27: Day 21 | G27: =E27+(F27*$O$3) -> 0 | H27: =G27/$O$9 -> 0 | I27: =315+G27 -> 315
C28: Day 22 | G28: =E28+(F28*$O$3) -> 0 | H28: =G28/$O$9 -> 0 | I28: =315+G28 -> 315
C29: Day 23 | G29: =E29+(F29*$O$3) -> 0 | H29: =G29/$O$9 -> 0 | I29: =315+G29 -> 315
C30: Day 24 | G30: =E30+(F30*$O$3) -> 0 | H30: =G30/$O$9 -> 0 | I30: =315+G30 -> 315
C31: Day 25 | G31: =E31+(F31*$O$3) -> 0 | H31: =G31/$O$9 -> 0 | I31: =315+G31 -> 315
C32: Day 26 | G32: =E32+(F32*$O$3) -> 0 | H32: =G32/$O$9 -> 0 | I32: =315+G32 -> 315
C33: Day 27 | G33: =E33+(F33*$O$3) -> 0 | H33: =G33/$O$9 -> 0 | I33: =315+G33 -> 315
C34: Day 28 | G34: =E34+(F34*$O$3) -> 0 | H34: =G34/$O$9 -> 0 | I34: =315+G34 -> 315
C35: Day 29 | G35: =E35+(F35*$O$3) -> 0 | H35: =G35/$O$9 -> 0 | I35: =315+G35 -> 315
... C37: Day 31 | G37: =E37+(F37*$O$3) -> 0 | H37: =G37/$O$9 -> 0 | I37: =315+G37 -> 315

Sheet JUL
K2: Valor Conta | L2: EUR | M2: USD | N2: USD em EU
K3: Total | L3: =sum(E7:E37) -> 0 | M3: =sum(F7:F37) -> -429.78 | N3: =M3*Sumario!N4 -> -377.18352 | O3: =Sumario!N4 -> 0.87762
B4: JUL
B5: Posicao | C5: Data | D5: Preço Abertura | E5: Lucro EU | F5: Lucro USD | G5: Total EUR
H6: Goal
C7: Day 1 | G7: =E7+(F7*$O$3) -> 0 | H7: =G7/$O$9 -> 0 | I7: =315+G7 -> 315
C8: Day 2 | G8: =E8+(F8*$O$3) -> 0 | H8: =G8/$O$9 -> 0 | I8: =315+G8 -> 315 | N8: Goal | O8: 2500 | P8: =O8-Sumario!K13 -> 2844.36
C9: Day 3 | G9: =E9+(F9*$O$3) -> 0 | H9: =G9/$O$9 -> 0 | I9: =315+G9 -> 315 | L9: 7245 | N9: Goal Day | O9: =O8/21 -> 119.04762 | P9: =P8/O8 -> 1.137744
C10: Day 4 | G10: =E10+(F10*$O$3) -> 0 | H10: =G10/$O$9 -> 0 | I10: =315+G10 -> 315 | L10: =L9+Sumario!K13 -> 6900.64
C11: Day 5 | G11: =E11+(F11*$O$3) -> 0 | H11: =G11/$O$9 -> 0 | I11: =315+G11 -> 315
C12: Day 6 | F12: =31.39+10.97 -> 42.36 | G12: =E12+(F12*$O$3) -> 37.175983 | H12: =G12/$O$9 -> 0.31227826 | I12: =315+G12 -> 352.17598
C13: Day 7 | G13: =E13+(F13*$O$3) -> 0 | H13: =G13/$O$9 -> 0 | I13: =315+G13 -> 315
C14: Day 8 | G14: =E14+(F14*$O$3) -> 0 | H14: =G14/$O$9 -> 0 | I14: =315+G14 -> 315
C15: Day 9 | G15: =E15+(F15*$O$3) -> 0 | H15: =G15/$O$9 -> 0 | I15: =315+G15 -> 315
C16: Day 10 | G16: =E16+(F16*$O$3) -> 0 | H16: =G16/$O$9 -> 0 | I16: =315+G16 -> 315
C17: Day 11 | G17: =E17+(F17*$O$3) -> 0 | H17: =G17/$O$9 -> 0 | I17: =315+G17 -> 315
C18: Day 12 | G18: =E18+(F18*$O$3) -> 0 | H18: =G18/$O$9 -> 0 | I18: =315+G18 -> 315
C19: Day 13 | G19: =E19+(F19*$O$3) -> 0 | H19: =G19/$O$9 -> 0 | I19: =315+G19 -> 315
C20: Day 14 | G20: =E20+(F20*$O$3) -> 0 | H20: =G20/$O$9 -> 0 | I20: =315+G20 -> 315
C21: Day 15 | G21: =E21+(F21*$O$3) -> 0 | H21: =G21/$O$9 -> 0 | I21: =315+G21 -> 315
C22: Day 16 | F22: =3.95-37.98 -> -34.03 | G22: =E22+(F22*$O$3) -> -29.865409 | H22: =G22/$O$9 -> -0.25086943 | I22: =315+G22 -> 285.13459
C23: Day 17 | F23: =20.83+10.13+4.26-336.26 -> -301.04 | G23: =E23+(F23*$O$3) -> -264.19872 | H23: =G23/$O$9 -> -2.2192693 | I23: =315+G23 -> 50.801275
C24: Day 18 | G24: =E24+(F24*$O$3) -> 0 | H24: =G24/$O$9 -> 0 | I24: =315+G24 -> 315
C25: Day 19 | G25: =E25+(F25*$O$3) -> 0 | H25: =G25/$O$9 -> 0 | I25: =315+G25 -> 315
C26: Day 20 | G26: =E26+(F26*$O$3) -> 0 | H26: =G26/$O$9 -> 0 | I26: =315+G26 -> 315
C27: Day 21 | F27: =-31.29-41.74-42.07 -> -115.1 | G27: =E27+(F27*$O$3) -> -101.01406 | H27: =G27/$O$9 -> -0.84851812 | I27: =315+G27 -> 213.98594
C28: Day 22 | F28: =-20.04-53.81-0.67 -> -74.52 | G28: =E28+(F28*$O$3) -> -65.400242 | H28: =G28/$O$9 -> -0.54936204 | I28: =315+G28 -> 249.59976
C29: Day 23 | G29: =E29+(F29*$O$3) -> 0 | H29: =G29/$O$9 -> 0 | I29: =315+G29 -> 315
C30: Day 24 | F30: =2.73 -> 2.73 | G30: =E30+(F30*$O$3) -> 2.3959026 | H30: =G30/$O$9 -> 0.020125582 | I30: =315+G30 -> 317.3959
C31: Day 25 | G31: =E31+(F31*$O$3) -> 0 | H31: =G31/$O$9 -> 0 | I31: =315+G31 -> 315
C32: Day 26 | G32: =E32+(F32*$O$3) -> 0 | H32: =G32/$O$9 -> 0 | I32: =315+G32 -> 315
C33: Day 27 | G33: =E33+(F33*$O$3) -> 0 | H33: =G33/$O$9 -> 0 | I33: =315+G33 -> 315
C34: Day 28 | F34: =-48.16-24.64 -> -72.8 | G34: =E34+(F34*$O$3) -> -63.890736 | H34: =G34/$O$9 -> -0.53668218 | I34: =315+G34 -> 251.10926
C35: Day 29 | F35: =-45.15+79.7 -> 34.55 | G35: =E35+(F35*$O$3) -> 30.321771 | H35: =G35/$O$9 -> 0.25470288 | I35: =315+G35 -> 345.32177
C36: Day 30 | G36: =E36+(F36*$O$3) -> 0 | H36: =G36/$O$9 -> 0 | I36: =315+G36 -> 315
C37: Day 31 | F37: =88.07 -> 88.07 | G37: =E37+(F37*$O$3) -> 77.291993 | H37: =G37/$O$9 -> 0.64925274 | I37: =315+G37 -> 392.29199

Sheet AGO
K2: Valor Conta | L2: EUR | M2: USD | N2: USD em EU
K3: Total | L3: =sum(E7:E37) -> 76.77 | M3: =sum(F7:F37) -> -1446.55 | N3: =M3*Sumario!N4 -> -1269.5212 | O3: =Sumario!N4 -> 0.87762
B4: AGO
B5: Posicao | C5: Data | D5: Preço Abertura | E5: Lucro EU | F5: Lucro USD | G5: Total EUR
H6: Goal
C7: Day 1 | G7: =E7+(F7*$O$3) -> 0 | H7: =G7/$O$9 -> 0 | I7: =315+G7 -> 315
C8: Day 2 | G8: =E8+(F8*$O$3) -> 0 | H8: =G8/$O$9 -> 0 | I8: =315+G8 -> 315 | N8: Goal | O8: 1000 | P8: =O8-Sumario!K14 -> 2187.0243
C9: Day 3 | G9: =E9+(F9*$O$3) -> 0 | H9: =G9/$O$9 -> 0 | I9: =315+G9 -> 315 | L9: 6615 | N9: Goal Day | O9: =O8/21 -> 47.619048 | P9: =P8/O8 -> 2.1870243
C10: Day 4 | F10: =9.43+0.27+6.82+0.08+0.06+185.87 -> 202.53 | G10: =E10+(F10*$O$3) -> 177.74438 | H10: =G10/$O$9 -> 3.732632 | I10: =315+G10 -> 492.74438 | L10: =L9+Sumario!K14 -> 5427.9757
C11: Day 5 | F11: =-20.95-16.82-3.44 -> -41.21 | G11: =E11+(F11*$O$3) -> -36.16672 | H11: =G11/$O$9 -> -0.75950112 | I11: =315+G11 -> 278.83328
C12: Day 6 | F12: =-10.15-637.02+2.69+3.74+3.74+3.74+3.91+24.73 -> -604.62 | G12: =E12+(F12*$O$3) -> -530.6266 | H12: =G12/$O$9 -> -11.143159 | I12: =315+G12 -> -215.6266
C13: Day 7 | G13: =E13+(F13*$O$3) -> 0 | H13: =G13/$O$9 -> 0 | I13: =315+G13 -> 315
C14: Day 8 | G14: =E14+(F14*$O$3) -> 0 | H14: =G14/$O$9 -> 0 | I14: =315+G14 -> 315
C15: Day 9 | G15: =E15+(F15*$O$3) -> 0 | H15: =G15/$O$9 -> 0 | I15: =315+G15 -> 315
C16: Day 10 | F16: =15.46+54.92-31.81 -> 38.57 | G16: =E16+(F16*$O$3) -> 33.849803 | H16: =G16/$O$9 -> 0.71084587 | I16: =315+G16 -> 348.8498
C17: Day 11 | F17: =-246.04-11.35 -> -257.39 | G17: =E17+(F17*$O$3) -> -225.89061 | H17: =G17/$O$9 -> -4.7437028 | I17: =315+G17 -> 89.109388 | K17: 4200
C18: Day 12 | F18: =-90.15 -> -90.15 | G18: =E18+(F18*$O$3) -> -79.117443 | H18: =G18/$O$9 -> -1.6614663 | I18: =315+G18 -> 235.88256
C19: Day 13 | G19: =E19+(F19*$O$3) -> 0 | H19: =G19/$O$9 -> 0 | I19: =315+G19 -> 315 | K19: 3292 | L19: Euros
C20: Day 14 | G20: =E20+(F20*$O$3) -> 0 | H20: =G20/$O$9 -> 0 | I20: =315+G20 -> 315
C21: Day 15 | G21: =E21+(F21*$O$3) -> 0 | H21: =G21/$O$9 -> 0 | I21: =315+G21 -> 315
C22: Day 16 | G22: =E22+(F22*$O$3) -> 0 | H22: =G22/$O$9 -> 0 | I22: =315+G22 -> 315
C23: Day 17 | E23: =76.77 -> 76.77 | F23: =-20.91+8.25-126 -> -138.66 | G23: =E23+(F23*$O$3) -> -44.920789 | H23: =G23/$O$9 -> -0.94333657 | I23: =315+G23 -> 270.07921
C24: Day 18 | F24: =-617.57-7.21 -> -624.78 | G24: =E24+(F24*$O$3) -> -548.31942 | H24: =G24/$O$9 -> -11.514708 | I24: =315+G24 -> -233.31942
C25: Day 19 | G25: =E25+(F25*$O$3) -> 0 | H25: =G25/$O$9 -> 0 | I25: =315+G25 -> 315
C26: Day 20 | F26: =155.7+16.33 -> 172.03 | G26: =E26+(F26*$O$3) -> 150.97697 | H26: =G26/$O$9 -> 3.1705163 | I26: =315+G26 -> 465.97697
C27: Day 21 | F27: =-163.12 -> -163.12 | G27: =E27+(F27*$O$3) -> -143.15737 | H27: =G27/$O$9 -> -3.0063049 | I27: =315+G27 -> 171.84263
C28: Day 22 | G28: =E28+(F28*$O$3) -> 0 | H28: =G28/$O$9 -> 0 | I28: =315+G28 -> 315
C29: Day 23 | G29: =E29+(F29*$O$3) -> 0 | H29: =G29/$O$9 -> 0 | I29: =315+G29 -> 315
C30: Day 24 | G30: =E30+(F30*$O$3) -> 0 | H30: =G30/$O$9 -> 0 | I30: =315+G30 -> 315
C31: Day 25 | F31: =27.13+179.31 -> 206.44 | G31: =E31+(F31*$O$3) -> 181.17587 | H31: =G31/$O$9 -> 3.8046933 | I31: =315+G31 -> 496.17587
C32: Day 26 | G32: =E32+(F32*$O$3) -> 0 | H32: =G32/$O$9 -> 0 | I32: =315+G32 -> 315
C33: Day 27 | F33: =-98.78-0.05 -> -98.83 | G33: =E33+(F33*$O$3) -> -86.735185 | H33: =G33/$O$9 -> -1.8214389 | I33: =315+G33 -> 228.26482
C34: Day 28 | G34: =E34+(F34*$O$3) -> 0 | H34: =G34/$O$9 -> 0 | I34: =315+G34 -> 315
C35: Day 29 | G35: =E35+(F35*$O$3) -> 0 | H35: =G35/$O$9 -> 0 | I35: =315+G35 -> 315
C36: Day 30 | G36: =E36+(F36*$O$3) -> 0 | H36: =G36/$O$9 -> 0 | I36: =315+G36 -> 315
C37: Day 31 | F37: =-47.36 -> -47.36 | G37: =E37+(F37*$O$3) -> -41.564083 | H37: =G37/$O$9 -> -0.87284575 | I37: =315+G37 -> 273.43592

Sheet SET
K2: Valor Conta | L2: EUR | M2: USD | N2: USD em EU
K3: Total | L3: =sum(E7:E37) -> 0 | M3: =sum(F7:F36) -> -675.07 | N3: =M3*Sumario!N4 -> -592.45493 | O3: =Sumario!N4 -> 0.87762
B4: SET
B5: Posicao | C5: Data | D5: Preço Abertura | E5: Lucro EU | F5: Lucro USD | G5: Total EUR
H6: Goal
C7: Day 1 | F7: =-52.82-45.27-44.16-49.7 -> -191.95 | G7: =E7+(F7*$O$3) -> -168.45916 | H7: =G7/$O$9 -> -1.4150569 | I7: =315+G7 -> 146.54084 | K7: =-321-501 -> -822
C8: Day 2 | F8: =-49.97 -> -49.97 | G8: =E8+(F8*$O$3) -> -43.854671 | H8: =G8/$O$9 -> -0.36837924 | I8: =315+G8 -> 271.14533 | N8: Goal | O8: 2500 | P8: =O8-Sumario!K15 -> 3075.4339
C9: Day 3 | F9: =-85.9 -> -85.9 | G9: =E9+(F9*$O$3) -> -75.387558 | H9: =G9/$O$9 -> -0.63325549 | I9: =315+G9 -> 239.61244 | L9: 6930 | N9: Goal Day | O9: =O8/21 -> 119.04762 | P9: =P8/O8 -> 1.2301736
C10: Day 4 | F10: =-46.48-94.04 -> -140.52 | G10: =E10+(F10*$O$3) -> -123.32316 | H10: =G10/$O$9 -> -1.0359146 | I10: =315+G10 -> 191.67684 | L10: =L9+Sumario!K15 -> 6354.5661
C11: Day 5 | G11: =E11+(F11*$O$3) -> 0 | H11: =G11/$O$9 -> 0 | I11: =315+G11 -> 315
C12: Day 6 | G12: =E12+(F12*$O$3) -> 0 | H12: =G12/$O$9 -> 0 | I12: =315+G12 -> 315
C13: Day 7 | G13: =E13+(F13*$O$3) -> 0 | H13: =G13/$O$9 -> 0 | I13: =315+G13 -> 315
C14: Day 8 | F14: =-58.29 -> -58.29 | G14: =E14+(F14*$O$3) -> -51.15647 | H14: =G14/$O$9 -> -0.42971435 | I14: =315+G14 -> 263.84353
C15: Day 9 | G15: =E15+(F15*$O$3) -> 0 | H15: =G15/$O$9 -> 0 | I15: =315+G15 -> 315
C16: Day 10 | G16: =E16+(F16*$O$3) -> 0 | H16: =G16/$O$9 -> 0 | I16: =315+G16 -> 315
C17: Day 11 | G17: =E17+(F17*$O$3) -> 0 | H17: =G17/$O$9 -> 0 | I17: =315+G17 -> 315
C18: Day 12 | G18: =E18+(F18*$O$3) -> 0 | H18: =G18/$O$9 -> 0 | I18: =315+G18 -> 315
C19: Day 13 | G19: =E19+(F19*$O$3) -> 0 | H19: =G19/$O$9 -> 0 | I19: =315+G19 -> 315
C20: Day 14 | G20: =E20+(F20*$O$3) -> 0 | H20: =G20/$O$9 -> 0 | I20: =315+G20 -> 315
C21: Day 15 | G21: =E21+(F21*$O$3) -> 0 | H21: =G21/$O$9 -> 0 | I21: =315+G21 -> 315
C22: Day 16 | G22: =E22+(F22*$O$3) -> 0 | H22: =G22/$O$9 -> 0 | I22: =315+G22 -> 315
C23: Day 17 | F23: =-44.91 -> -44.91 | G23: =E23+(F23*$O$3) -> -39.413914 | H23: =G23/$O$9 -> -0.33107688 | I23: =315+G23 -> 275.58609
C24: Day 18 | F24: =-0.75+68.64 -> 67.89 | G24: =E24+(F24*$O$3) -> 59.581622 | H24: =G24/$O$9 -> 0.50048562 | I24: =315+G24 -> 374.58162
C25: Day 19 | G25: =E25+(F25*$O$3) -> 0 | H25: =G25/$O$9 -> 0 | I25: =315+G25 -> 315
C26: Day 20 | G26: =E26+(F26*$O$3) -> 0 | H26: =G26/$O$9 -> 0 | I26: =315+G26 -> 315
C27: Day 21 | F27: =-48.29-48.97 -> -97.26 | G27: =E27+(F27*$O$3) -> -85.357321 | H27: =G27/$O$9 -> -0.7170015 | I27: =315+G27 -> 229.64268
C28: Day 22 | F28: =0.96+1.12+1.14 -> 3.22 | G28: =E28+(F28*$O$3) -> 2.8259364 | H28: =G28/$O$9 -> 0.023737866 | I28: =315+G28 -> 317.82594
C29: Day 23 | F29: =-27.59-49.79 -> -77.38 | G29: =E29+(F29*$O$3) -> -67.910236 | H29: =G29/$O$9 -> -0.57044598 | I29: =315+G29 -> 247.08976
C30: Day 24 | G30: =E30+(F30*$O$3) -> 0 | H30: =G30/$O$9 -> 0 | I30: =315+G30 -> 315
C31: Day 25 | G31: =E31+(F31*$O$3) -> 0 | H31: =G31/$O$9 -> 0 | I31: =315+G31 -> 315
C32: Day 26 | G32: =E32+(F32*$O$3) -> 0 | H32: =G32/$O$9 -> 0 | I32: =315+G32 -> 315
C33: Day 27 | G33: =E33+(F33*$O$3) -> 0 | H33: =G33/$O$9 -> 0 | I33: =315+G33 -> 315
C34: Day 28 | G34: =E34+(F34*$O$3) -> 0 | H34: =G34/$O$9 -> 0 | I34: =315+G34 -> 315
C35: Day 29 | G35: =E35+(F35*$O$3) -> 0 | H35: =G35/$O$9 -> 0 | I35: =315+G35 -> 315
C36: Day 30 | G36: =E36+(F36*$O$3) -> 0 | H36: =G36/$O$9 -> 0 | I36: =315+G36 -> 315
C37: Day 31 | G37: =E37+(F37*$O$3) -> 0 | H37: =G37/$O$9 -> 0 | I37: =315+G37 -> 315

Sheet OUT
K2: Valor Conta | L2: EUR | M2: USD | N2: USD em EU
K3: Total | L3: =sum(E7:E37) -> 0 | M3: =sum(F7:F37) -> 0 | N3: =M3*Sumario!N4 -> 0 | O3: =Sumario!N4 -> 0.87762
B4: OUT
B5: Posicao | C5: Data | D5: Preço Abertura | E5: Lucro EU | F5: Lucro USD | G5: Total EUR
H6: Goal
C7: Day 1 | G7: =E7+(F7*$O$3) -> 0 | H7: =G7/$O$9 -> 0 | I7: =315+G7 -> 315
C8: Day 2 | G8: =E8+(F8*$O$3) -> 0 | H8: =G8/$O$9 -> 0 | I8: =315+G8 -> 315 | N8: Goal | O8: 2500 | P8: =O8-Sumario!K16 -> 2500
C9: Day 3 | G9: =E9+(F9*$O$3) -> 0 | H9: =G9/$O$9 -> 0 | I9: =315+G9 -> 315 | L9: 7245 | N9: Goal Day | O9: =O8/21 -> 119.04762 | P9: =P8/O8 -> 1
C10: Day 4 | G10: =E10+(F10*$O$3) -> 0 | H10: =G10/$O$9 -> 0 | I10: =315+G10 -> 315 | L10: =L9+Sumario!K16 -> 7245
C11: Day 5 | G11: =E11+(F11*$O$3) -> 0 | H11: =G11/$O$9 -> 0 | I11: =315+G11 -> 315
C12: Day 6 | G12: =E12+(F12*$O$3) -> 0 | H12: =G12/$O$9 -> 0 | I12: =315+G12 -> 315
C13: Day 7 | G13: =E13+(F13*$O$3) -> 0 | H13: =G13/$O$9 -> 0 | I13: =315+G13 -> 315
C14: Day 8 | G14: =E14+(F14*$O$3) -> 0 | H14: =G14/$O$9 -> 0 | I14: =315+G14 -> 315
C15: Day 9 | G15: =E15+(F15*$O$3) -> 0 | H15: =G15/$O$9 -> 0 | I15: =315+G15 -> 315
C16: Day 10 | G16: =E16+(F16*$O$3) -> 0 | H16: =G16/$O$9 -> 0 | I16: =315+G16 -> 315
C17: Day 11 | G17: =E17+(F17*$O$3) -> 0 | H17: =G17/$O$9 -> 0 | I17: =315+G17 -> 315
C18: Day 12 | G18: =E18+(F18*$O$3) -> 0 | H18: =G18/$O$9 -> 0 | I18: =315+G18 -> 315
C19: Day 13 | G19: =E19+(F19*$O$3) -> 0 | H19: =G19/$O$9 -> 0 | I19: =315+G19 -> 315
C20: Day 14 | G20: =E20+(F20*$O$3) -> 0 | H20: =G20/$O$9 -> 0 | I20: =315+G20 -> 315
C21: Day 15 | G21: =E21+(F21*$O$3) -> 0 | H21: =G21/$O$9 -> 0 | I21: =315+G21 -> 315
C22: Day 16 | G22: =E22+(F22*$O$3) -> 0 | H22: =G22/$O$9 -> 0 | I22: =315+G22 -> 315
... C37: Day 31 | G37: =E37+(F37*$O$3) -> 0 | H37: =G37/$O$9 -> 0 | I37: =315+G37 -> 315

Sheet NOV
K2: Valor Conta | L2: EUR | M2: USD | N2: USD em EU
K3: Total | L3: =sum(E7:E37) -> 0 | M3: =sum(F7:F37) -> 0 | N3: =M3*Sumario!N4 -> 0 | O3: =Sumario!N4 -> 0.87762
B4: NOV
B5: Posicao | C5: Data | D5: Preço Abertura | E5: Lucro EU | F5: Lucro USD | G5: Total EUR
H6: Goal
C7: Day 1 | G7: =E7+(F7*$O$3) -> 0 | H7: =G7/$O$9 -> 0 | I7: =315+G7 -> 315
C8: Day 2 | G8: =E8+(F8*$O$3) -> 0 | H8: =G8/$O$9 -> 0 | I8: =315+G8 -> 315 | N8: Goal | O8: 2500 | P8: =O8-Sumario!K17 -> 2500
C9: Day 3 | G9: =E9+(F9*$O$3) -> 0 | H9: =G9/$O$9 -> 0 | I9: =315+G9 -> 315 | L9: 7245 | N9: Goal Day | O9: =O8/21 -> 119.04762 | P9: =P8/O8 -> 1
C10: Day 4 | G10: =E10+(F10*$O$3) -> 0 | H10: =G10/$O$9 -> 0 | I10: =315+G10 -> 315 | L10: =L9+Sumario!K16 -> 7245
C11: Day 5 | G11: =E11+(F11*$O$3) -> 0 | H11: =G11/$O$9 -> 0 | I11: =315+G11 -> 315
C12: Day 6 | G12: =E12+(F12*$O$3) -> 0 | H12: =G12/$O$9 -> 0 | I12: =315+G12 -> 315
C13: Day 7 | G13: =E13+(F13*$O$3) -> 0 | H13: =G13/$O$9 -> 0 | I13: =315+G13 -> 315
C14: Day 8 | G14: =E14+(F14*$O$3) -> 0 | H14: =G14/$O$9 -> 0 | I14: =315+G14 -> 315
C15: Day 9 | G15: =E15+(F15*$O$3) -> 0 | H15: =G15/$O$9 -> 0 | I15: =315+G15 -> 315
C16: Day 10 | G16: =E16+(F16*$O$3) -> 0 | H16: =G16/$O$9 -> 0 | I16: =315+G16 -> 315
C17: Day 11 | G17: =E17+(F17*$O$3) -> 0 | H17: =G17/$O$9 -> 0 | I17: =315+G17 -> 315
C18: Day 12 | G18: =E18+(F18*$O$3) -> 0 | H18: =G18/$O$9 -> 0 | I18: =315+G18 -> 315
C19: Day 13 | G19: =E19+(F19*$O$3) -> 0 | H19: =G19/$O$9 -> 0 | I19: =315+G19 -> 315
C20: Day 14 | G20: =E20+(F20*$O$3) -> 0 | H20: =G20/$O$9 -> 0 | I20: =315+G20 -> 315
C21: Day 15 | G21: =E21+(F21*$O$3) -> 0 | H21: =G21/$O$9 -> 0 | I21: =315+G21 -> 315
C22: Day 16 | G22: =E22+(F22*$O$3) -> 0 | H22: =G22/$O$9 -> 0 | I22: =315+G22 -> 315
... C37: Day 31 | G37: =E37+(F37*$O$3) -> 0 | H37: =G37/$O$9 -> 0 | I37: =315+G37 -> 315

Sheet DEZ
K2: Valor Conta | L2: EUR | M2: USD | N2: USD em EU
K3: Total | L3: =sum(E7:E37) -> 0 | M3: =sum(F7:F37) -> 0 | N3: =M3*Sumario!N4 -> 0 | O3: =Sumario!N4 -> 0.87762
B4: DEZ
B5: Posicao | C5: Data | D5: Preço Abertura | E5: Lucro EU | F5: Lucro USD | G5: Total EUR
H6: Goal
C7: Day 1 | G7: =E7+(F7*$O$3) -> 0 | H7: =G7/$O$9 -> 0 | I7: =315+G7 -> 315
C8: Day 2 | G8: =E8+(F8*$O$3) -> 0 | H8: =G8/$O$9 -> 0 | I8: =315+G8 -> 315 | N8: Goal | O8: 2500 | P8: =O8-Sumario!K18 -> 2500
C9: Day 3 | G9: =E9+(F9*$O$3) -> 0 | H9: =G9/$O$9 -> 0 | I9: =315+G9 -> 315 | L9: 7245 | N9: Goal Day | O9: =O8/21 -> 119.04762 | P9: =P8/O8 -> 1
C10: Day 4 | G10: =E10+(F10*$O$3) -> 0 | H10: =G10/$O$9 -> 0 | I10: =315+G10 -> 315 | L10: =L9+Sumario!K16 -> 7245
C11: Day 5 | G11: =E11+(F11*$O$3) -> 0 | H11: =G11/$O$9 -> 0 | I11: =315+G11 -> 315
C12: Day 6 | G12: =E12+(F12*$O$3) -> 0 | H12: =G12/$O$9 -> 0 | I12: =315+G12 -> 315
C13: Day 7 | G13: =E13+(F13*$O$3) -> 0 | H13: =G13/$O$9 -> 0 | I13: =315+G13 -> 315
C14: Day 8 | G14: =E14+(F14*$O$3) -> 0 | H14: =G14/$O$9 -> 0 | I14: =315+G14 -> 315
C15: Day 9 | G15: =E15+(F15*$O$3) -> 0 | H15: =G15/$O$9 -> 0 | I15: =315+G15 -> 315
C16: Day 10 | G16: =E16+(F16*$O$3) -> 0 | H16: =G16/$O$9 -> 0 | I16: =315+G16 -> 315
C17: Day 11 | G17: =E17+(F17*$O$3) -> 0 | H17: =G17/$O$9 -> 0 | I17: =315+G17 -> 315
C18: Day 12 | G18: =E18+(F18*$O$3) -> 0 | H18: =G18/$O$9 -> 0 | I18: =315+G18 -> 315
C19: Day 13 | G19: =E19+(F19*$O$3) -> 0 | H19: =G19/$O$9 -> 0 | I19: =315+G19 -> 315
C20: Day 14 | G20: =E20+(F20*$O$3) -> 0 | H20: =G20/$O$9 -> 0 | I20: =315+G20 -> 315
C21: Day 15 | G21: =E21+(F21*$O$3) -> 0 | H21: =G21/$O$9 -> 0 | I21: =315+G21 -> 315
C22: Day 16 | G22: =E22+(F22*$O$3) -> 0 | H22: =G22/$O$9 -> 0 | I22: =315+G22 -> 315
... C37: Day 31 | G37: =E37+(F37*$O$3) -> 0 | H37: =G37/$O$9 -> 0 | I37: =315+G37 -> 315

Sheet Configs
A1: Configs
A2: processarLoteItems | B2: FALSE | C2: A função processarLoteItems é um motor de execução em lotes resiliente, desenhado para processar chamadas de API (como o envio de ordens de trading) diretamente a partir do Google Sheets, garantindo que os limites de tempo do Google e os limites de taxa da API não são excedidos.
A3: processarTudo | B3: FALSE
A4: processarLoteItems_Short | B4: FALSE
A5: enviarRelatorioIA | B5: FALSE
A6: riscoMaximoDolares | B6: 25
A7: racioTakeProfit | C7: Colocar o valor temporáriamente. Por defeito assume os valores standard 1.5 e 2.0.
A8: multiplicadorTrailing | B8: 2 | C8: 1.5 (Stop Apertado / Conservador): É o valor por defeito. É excelente para mercados muito voláteis, ou quando a ação já subiu muito e tu queres trancar o máximo de lucro possível ao primeiro sinal de fraqueza. A desvantagem? Podes ser "expulso" da posição num dia de queda normal, antes da ação voltar a subir. 2.0 (O Padrão de Ouro / Moderado): É o valor clássico do famoso indicador Chandelier Exit. Dá espaço suficiente para a ação sofrer o seu "ruído" normal do dia-a-dia (quedas normais numa tendência de alta) sem te fechar a posição prematuramente. É o ideal para deixar os lucros correrem. 2.5 a 3.0 (Stop Largo / Seguidor de Tendência): Usado apenas se quiseres segurar a ação durante meses (como a VISA, que é uma ação muito estável a longo prazo). Dá imenso espaço para a ação corrigir, mas significa que devolves uma parte maior do lucro ao mercado se a tendência reverter. | D8: 0
A9: analiseTecnica | B9: FALSE
A10: listaAtivosPermitidos | B10: NOW,AMZN, WMT, PG, PEP,TSLA,BRK.B, VISA, MA,LLY, UNH,AAPL, MSFT, GOOGL, NVDA, AVGO, ASML,ADBE, CRM, SAP, ORCL, AMD, INTC, DELL, PANW, PLTR, NET, CSCO, MRVL, MCHP, QLYS, IBM, TYL, VRSK,NKE, BABA, PDD, SHOP, EBAY, EL, BOSS, UBER, DASH, OR, HEIA, NFLX,BMW, MBG, VOW3, P911, BYDDY, SIE, LMT, RHM, GRMN, SWK, TKA,PFE, ABT, NOVN, MRNA, HUM,UPST,ANF,ASTS,QLYS,NET,NFLX,ADP,BBAI,META | C10: Short List para processamento | D10: =IFERROR(__xludf.DUMMYFUNCTION("IF(B10="""", 0, COUNTA(SPLIT(B10, "","")))"),71.0) -> 71
A11: listaAllStocks | B11: ANF, ACN, ADS, ADBE, ADYEN, AHL, A, BABA, ALV, GOOGL, AMZ, AMZN, AMD, AS, AMPL, APCA, AAPL, APP, ANET, ASML, ASTS, TEAM, BAYN, BRK.B, BBAI, BMW, BABA, BOSS, AVGO, BYDDY, AI, CAP, CELH, CNA, CSCO, CLSK, NET, CNXC, COND, TG, DBX, BROS, EBAY, LLY, ENVX, EL, GALP, GRMN, HEIA, HEN3, HSBA, HSBC, IDR, IFX, INL, INTC, IONQ, LMT, OR, MRVL, M4I, MA, MBG, META, MSFT, MRNA, MNDY, NFC, NFLX, NKE, NKE, NOVN, NOVN, VONV, D, NVDA, ORC, ORCL, PTX, PLTR, PANW, 2PP, PDD, PEP, PHIA, P911, PRG, PG, PG, QLYS, QUBT, QSR, L, RHM, RGTI, HOOD, RKLB, RGLD, FOO, CRM, SAP, LAE, SNOW, SHAK, SIE, SWK, SG, LE, SOON, SOUN, STR, SMCI, TALK, TEM, TSLA, TL0, TKA, TTD, UT8, UNH, U, UPST, VISA, VOW3, WMT, WMT, DELL, SHELL, SHOP, PFE, RDDT, RBLX, FITB, RCAT, MCHP, ARES, BMI, UBER, FIG, HUM, TZOO, VRSK, TYL, DDOG, ABT, IBM, DASH | C11: All Stocks | D11: =IFERROR(__xludf.DUMMYFUNCTION("IF(B11="""", 0, COUNTA(SPLIT(B11, "","")))"),147.0) -> 147
A12: listaLightStocks | B12: NOW,AMZN, WMT, PG, PEP,TSLA,BRK.B, VISA, MA,LLY, UNH,AAPL, MSFT, GOOGL, NVDA, AVGO, ASML,ADBE, CRM, SAP, ORCL, AMD, INTC, DELL, PANW, PLTR, NET, CSCO, MRVL, MCHP, QLYS, IBM, TYL, VRSK,NKE, BABA, PDD, SHOP, EBAY, EL, BOSS, UBER, DASH, OR, HEIA, NFLX,BMW, MBG, VOW3, P911, BYDDY, SIE, LMT, RHM, GRMN, SWK, TKA,PFE, ABT, NOVN, MRNA, HUM | C12: Light Stocks | D12: =IFERROR(__xludf.DUMMYFUNCTION("IF(B12="""", 0, COUNTA(SPLIT(B12, "","")))"),62.0) -> 62
E16: Estados usados no Diario de Bordo
E17: PENDENTE | F17: A ordem Buy Limit está colocada na corretora. O setup é válido e aguarda que o preço recue até à Drop Zone.
E18: ATIVA | F18: A ordem Limit foi acionada. O capital está no mercado e o Hard Stop de proteção está obrigatoriamente colocado na corretora.
E19: WIN | F19: A ação seguiu a tendência e atingiu o teu alvo quantitativo.
E20: LOSS | F20: O mercado invalidou a tese. O Hard Stop cortou o risco ao nível predefinido (~$50).
E21: FUGIU | F21: O ativo arrancou sem acionar a ordem. A janela de oportunidade fechou e a ordem foi cancelada para proteger a margem e evitar "facas a cair".
E22: INVALIDADO | F22: A ordem limite estava pendente, mas os filtros técnicos que a justificavam (como o RVOL a cair abaixo de 1.0 ou o ADX a perder força) deterioraram-se antes de o preço chegar à Drop Zone.
E23: BREAKEVEN

Sheet Analise Compra
E2: Stock | F2: Description | G2: Market Price | H2: L | I2: H | J2: Result | K2: Momentum | L2: RSI | M2: ADX | N2: ATR | O2: Pivot | P2: Price | Q2: Time | R2: true | S2: ERRO: Cannot read properties of undefined (reading '0') | T2: 0 | U2: Ticker | V2: Ticker Price | W2: distMM20 | X2: Momentum 2 | Y2: RSI 2 | Z2: ADX 2 | AA2: ATR 2 | AB2: VOL | AC2: Column 1 | AD2: Drop Zone | AE2: Column 2 | AF2: Column 3 | AG2: Column 4 | AH2: Column 5
E3: AAPL | F3: Apple US | G3: =IFERROR(__xludf.DUMMYFUNCTION("GOOGLEFINANCE(E3, ""price"")"),336.89) -> 336.89 | H3: =IFERROR(__xludf.DUMMYFUNCTION("GOOGLEFINANCE(E3, ""low"")"),335.91) -> 335.91 | I3: =IFERROR(__xludf.DUMMYFUNCTION("GOOGLEFINANCE(E3, ""high"")"),341.8) -> 341.8 | K3: 11.27 | L3: 59.69 | M3: 19.99 | N3: 5.47 | O3: P Down | P3: 205.2 | Q3: 45761.644 | R3: TRUE | S3: AAPL,Preço: 339.75,Dist MM20: 4.35%,Momentum: 14.62,RSI: 66.88,ADX: 18.67,ATR: 6.97,RVOL: 0.94,Estado: Aguardar Recuo,Entrada: 336.96,Stop: 329.99,Take-Profit: 345.32,Break-Even: 341.14,Qtd: 3.59,Trailing: 329.99,Data: 23/09/2026 02:04:29 | T3: 0 | U3: AAPL | V3: Preço: 333.43 | W3: Dist MM20: 2.80% | X3: Momentum: 18.11 | Y3: RSI: 61.66 | Z3: ADX: 29.46 | AA3: ATR: 7.30 | AB3: RVOL: 1.11 | AC3: Data: 31/07/2026 02:06:15 | AD3: 46030.371 | AE3: AAPL,Preço: 333.43,Dist MM20: 2.80%,Momentum: 18.11,RSI: 61.66,ADX: 29.46,ATR: 7.30,RVOL: 1.11,Estado: Observar,Entrada: N/A,Stop: N/A,Take-Profit: N/A,Break-Even: N/A,Qtd: N/A,Data: 31/07/2026 02:06:15
B4: Time Now | C4: =now() -> 46288.715 | E4: ABNB | F4: Airbnb | G4: =IFERROR(__xludf.DUMMYFUNCTION("GOOGLEFINANCE(E4, ""price"")"),152.37) -> 152.37 | R4: TRUE | S4: ABNB,Preço: 161.81,Dist MM20: -8.01%,Momentum: -20.73,RSI: 35.83,ADX: 23.28,ATR: 4.55,RVOL: 1.11,Estado: Observar,Entrada: N/A,Stop: N/A,Take-Profit: N/A,Break-Even: N/A,Qtd: N/A,Trailing: 152.71,Data: 23/09/2026 06:43:09 | T4: 0 | U4: ABNB | V4: Preço: 152.08 | W4: Dist MM20: 3.75% | X4: Momentum: 3.46 | Y4: RSI: 60.76 | Z4: ADX: 16.86 | AA4: ATR: 3.81 | AB4: RVOL: 0.90 | AC4: Data: 31/07/2026 04:52:48 | AD4: 46030.371 | AE4: ABNB,Preço: 152.08,Dist MM20: 3.75%,Momentum: 3.46,RSI: 60.76,ADX: 16.86,ATR: 3.81,RVOL: 0.90,Estado: Observar,Entrada: N/A,Stop: N/A,Take-Profit: N/A,Break-Even: N/A,Qtd: N/A,Data: 31/07/2026 04:52:48
E5: ABT | F5: Abbot Laboratories | G5: =IFERROR(__xludf.DUMMYFUNCTION("GOOGLEFINANCE(E5, ""price"")"),104.05) -> 104.05 | H5: =IFERROR(__xludf.DUMMYFUNCTION("GOOGLEFINANCE(E5, ""low"")"),102.85) -> 102.85 | I5: =IFERROR(__xludf.DUMMYFUNCTION("GOOGLEFINANCE(E5, ""high"")"),104.29) -> 104.29 | K5: 7.93 | L5: 0 | M5: 21.44 | N5: 3.13 | R5: TRUE | S5: ABT,Preço: 103.69,Dist MM20: -2.92%,Momentum: -5.24,RSI: 42.27,ADX: 25.38,ATR: 2.31,RVOL: 0.96,Estado: Observar,Entrada: N/A,Stop: N/A,Take-Profit: N/A,Break-Even: N/A,Qtd: N/A,Trailing: 99.07,Data: 23/09/2026 02:04:47 | T5: 0 | U5: ABT | V5: Preço: 105.61 | W5: Dist MM20: 7.15% | X5: Momentum: 11.68 | Y5: RSI: 66.64 | Z5: ADX: 31.05 | AA5: ATR: 2.71 | AB5: RVOL: 0.50 | AC5: Data: 31/07/2026 02:37:35 | AD5: 46030.371 | AE5: ABT,Preço: 105.61,Dist MM20: 7.15%,Momentum: 11.68,RSI: 66.64,ADX: 31.05,ATR: 2.71,RVOL: 0.50,Estado: Observar,Entrada: N/A,Stop: N/A,Take-Profit: N/A,Break-Even: N/A,Qtd: N/A,Data: 31/07/2026 02:37:35
E6: ACN | F6: Accenture | G6: =IFERROR(__xludf.DUMMYFUNCTION("GOOGLEFINANCE(E6, ""price"")"),185.3) -> 185.3 | H6: =IFERROR(__xludf.DUMMYFUNCTION("GOOGLEFINANCE(E6, ""low"")"),182.56) -> 182.56 | I6: =IFERROR(__xludf.DUMMYFUNCTION("GOOGLEFINANCE(E6, ""high"")"),188.28) -> 188.28 | K6: -4.31 | L6: 47.14 | M6: 13.93 | N6: 5.42 | O6: S1 Up | P6: 311.07 | Q6: 45828.334 | R6: TRUE | S6: ACN,Preço: 183.72,Dist MM20: -1.40%,Momentum: -4.37,RSI: 51.15,ADX: 18.44,ATR: 6.24,RVOL: 0.80,Estado: Observar,Entrada: N/A,Stop: N/A,Take-Profit: N/A,Break-Even: N/A,Qtd: N/A,Trailing: 171.24,Data: 23/09/2026 06:44:26 | T6: 0 | U6: ACN | V6: Preço: 163.29 | W6: Dist MM20: 12.89% | X6: Momentum: 28.06 | Y6: RSI: 60.57 | Z6: ADX: 21.73 | AA6: ATR: 6.90 | AB6: RVOL: 1.02 | AC6: Data: 31/07/2026 03:50:33 | AD6: 46030.371 | AE6: ACN,Preço: 163.29,Dist MM20: 12.89%,Momentum: 28.06,RSI: 60.57,ADX: 21.73,ATR: 6.90,RVOL: 1.02,Estado: Observar,Entrada: N/A,Stop: N/A,Take-Profit: N/A,Break-Even: N/A,Qtd: N/A,Data: 31/07/2026 03:50:33
E7: ADBE | F7: Adobe Inc US | G7: =IFERROR(__xludf.DUMMYFUNCTION("GOOGLEFINANCE(E7, ""price"")"),240.71) -> 240.71 | H7: =IFERROR(__xludf.DUMMYFUNCTION("GOOGLEFINANCE(E7, ""low"")"),237.51) -> 237.51 | I7: =IFERROR(__xludf.DUMMYFUNCTION("GOOGLEFINANCE(E7, ""high"")"),241.69) -> 241.69 | R7: TRUE | S7: ADBE,Preço: 238.25,Dist MM20: -10.35%,Momentum: -47.83,RSI: 37.39,ADX: 21.84,ATR: 8.84,RVOL: 1.28,Estado: Observar,Entrada: N/A,Stop: N/A,Take-Profit: N/A,Break-Even: N/A,Qtd: N/A,Trailing: 220.57,Data: 23/09/2026 02:05:04 | T7: 0 | U7: ADBE | V7: Preço: 247.90 | W7: Dist MM20: 8.00% | X7: Momentum: 24.26 | Y7: RSI: 58.84 | Z7: ADX: 17.19 | AA7: ATR: 10.79 | AB7: RVOL: 1.18 | AC7: Data: 31/07/2026 02:04:27 | AD7: 46030.371 | AE7: ADBE,Preço: 247.90,Dist MM20: 8.00%,Momentum: 24.26,RSI: 58.84,ADX: 17.19,ATR: 10.79,RVOL: 1.18,Estado: Observar,Entrada: N/A,Stop: N/A,Take-Profit: N/A,Break-Even: N/A,Qtd: N/A,Data: 31/07/2026 02:04:27
E8: ADP | F8: Automatic Data Processing | G8: =IFERROR(__xludf.DUMMYFUNCTION("GOOGLEFINANCE(E8, ""price"")"),267.39) -> 267.39 | R8: TRUE | S8: ADP,Preço: 269.64,Dist MM20: -2.42%,Momentum: -13.85,RSI: 46.09,ADX: 19.79,ATR: 4.78,RVOL: 0.86,Estado: Observar,Entrada: N/A,Stop: N/A,Take-Profit: N/A,Break-Even: N/A,Qtd: N/A,Trailing: 260.08,Data: 23/09/2026 02:05:22 | T8: 0 | U8: ADP | V8: Preço: 270.62 | W8: Dist MM20: 6.50% | X8: Momentum: 23.15 | Y8: RSI: 67.16 | Z8: ADX: 36.53 | AA8: ATR: 8.27 | AB8: RVOL: 1.03 | AC8: Trailing: 259.05 | AD8: 46150.444 | AE8: ADP,Preço: 270.62,Dist MM20: 6.50%,Momentum: 23.15,RSI: 67.16,ADX: 36.53,ATR: 8.27,RVOL: 1.03,Estado: Forca Consolidada,Entrada: 268.97,Stop: 259.05,Take-Profit: 283.86,Break-Even: 276.42,Qtd: 5.04,Trailing: 259.05,Data: 05/08/2026 10:33:05
E9: ADSK | F9: AutoDesk | G9: =IFERROR(__xludf.DUMMYFUNCTION("GOOGLEFINANCE(E9, ""price"")"),219.03) -> 219.03 | H9: =IFERROR(__xludf.DUMMYFUNCTION("GOOGLEFINANCE(F9, ""price"")"),"#N/A") -> #N/A | I9: =IFERROR(__xludf.DUMMYFUNCTION("GOOGLEFINANCE(G9, ""price"")"),"#N/A") -> #N/A | R9: TRUE | S9: ADSK,Preço: 219.62,Dist MM20: -5.20%,Momentum: -28.07,RSI: 42.82,ADX: 20.86,ATR: 8.05,RVOL: 0.69,Estado: Observar,Entrada: N/A,Stop: N/A,Take-Profit: N/A,Break-Even: N/A,Qtd: N/A,Trailing: 203.52,Data: 23/09/2026 06:44:26 | T9: 0 | U9: ADSK | V9: Preço: 234.97 | W9: Dist MM20: 9.19% | X9: Momentum: 26.52 | Y9: RSI: 61.81 | Z9: ADX: 17.19 | AA9: ATR: 8.60 | AB9: RVOL: 1.06 | AC9: Data: 31/07/2026 04:53:43 | AD9: 46030.371 | AE9: ADSK,Preço: 234.97,Dist MM20: 9.19%,Momentum: 26.52,RSI: 61.81,ADX: 17.19,ATR: 8.60,RVOL: 1.06,Estado: Observar,Entrada: N/A,Stop: N/A,Take-Profit: N/A,Break-Even: N/A,Qtd: N/A,Data: 31/07/2026 04:53:43
E10: ADYEN | F10: Adyen | G10: =IFERROR(__xludf.DUMMYFUNCTION("GOOGLEFINANCE(E10, ""price"")"),860.1) -> 860.1 | H10: =IFERROR(__xludf.DUMMYFUNCTION("GOOGLEFINANCE(E10, ""low"")"),856.0) -> 856 | I10: =IFERROR(__xludf.DUMMYFUNCTION("GOOGLEFINANCE(E10, ""high"")"),899.6) -> 899.6 | K10: 246.4 | L10: 80.15 | M10: 24.54 | N10: 51.6 | O10: R3 Down | P10: 1835.8 | Q10: 45707.814 | R10: TRUE | S10: ADYEN,Preço: 903.00,Dist MM20: -7.75%,Momentum: -135.60,RSI: 38.93,ADX: 29.54,ATR: 25.59,RVOL: 1.06,Estado: Observar,Entrada: N/A,Stop: N/A,Take-Profit: N/A,Break-Even: N/A,Qtd: N/A,Trailing: 851.82,Data: 23/09/2026 06:44:29 | T10: 0 | U10: ADYEN | V10: Preço: 885.20 | W10: Dist MM20: 4.85% | X10: Momentum: 38.60 | Y10: RSI: 57.69 | Z10: ADX: 14.69 | AA10: ATR: 31.76 | AB10: RVOL: 0.85 | AC10: Data: 31/07/2026 03:51:07 | AD10: 46030.371 | AE10: ADYEN,Preço: 885.20,Dist MM20: 4.85%,Momentum: 38.60,RSI: 57.69,ADX: 14.69,ATR: 31.76,RVOL: 0.85,Estado: Aguardar Recuo,Entrada: 872.50,Stop: 840.74,Take-Profit: 936.02,Break-Even: 904.26,Qtd: 1.57,Data: 31/07/2026 03:51:07
E11: AEP | F11: American Electric Power | G11: =IFERROR(__xludf.DUMMYFUNCTION("GOOGLEFINANCE(E11, ""price"")"),118.06) -> 118.06 | R11: TRUE | S11: AEP,Preço: 120.27,Dist MM20: -1.89%,Momentum: -2.69,RSI: 35.97,ADX: 21.24,ATR: 1.89,RVOL: 1.31,Estado: Observar,Entrada: N/A,Stop: N/A,Take-Profit: N/A,Break-Even: N/A,Qtd: N/A,Trailing: 116.49,Data: 23/09/2026 06:44:27 | T11: 0 | U11: AEP | V11: Preço: 127.78 | W11: Dist MM20: -4.44% | X11: Momentum: -7.65 | Y11: RSI: 37.84 | Z11: ADX: 12.60 | AA11: ATR: 2.66 | AB11: RVOL: 1.35 | AC11: Data: 31/07/2026 04:53:26 | AD11: 46030.371 | AE11: AEP,Preço: 127.78,Dist MM20: -4.44%,Momentum: -7.65,RSI: 37.84,ADX: 12.60,ATR: 2.66,RVOL: 1.35,Estado: Observar,Entrada: N/A,Stop: N/A,Take-Profit: N/A,Break-Even: N/A,Qtd: N/A,Data: 31/07/2026 04:53:26
E12: AGNC | F12: AGNC Investments | G12: =IFERROR(__xludf.DUMMYFUNCTION("GOOGLEFINANCE(E12, ""price"")"),9.95) -> 9.95 | R12: TRUE | S12: AGNC,Preço: 10.09,Dist MM20: -3.04%,Momentum: -0.51,RSI: 37.10,ADX: 26.49,ATR: 0.20,RVOL: 0.84,Estado: Observar,Entrada: N/A,Stop: N/A,Take-Profit: N/A,Break-Even: N/A,Qtd: N/A,Trailing: 9.69,Data: 23/09/2026 06:44:27 | T12: 0 | U12: AGNC | V12: Preço: 10.64 | W12: Dist MM20: -2.53% | X12: Momentum: -0.68 | Y12: RSI: 45.08 | Z12: ADX: 16.75 | AA12: ATR: 0.23 | AB12: RVOL: 1.27 | AC12: Trailing: 10.18 | AD12: 46150.444 | AE12: AGNC,Preço: 10.64,Dist MM20: -2.53%,Momentum: -0.68,RSI: 45.08,ADX: 16.75,ATR: 0.23,RVOL: 1.27,Estado: Observar,Entrada: N/A,Stop: N/A,Take-Profit: N/A,Break-Even: N/A,Qtd: N/A,Trailing: 10.18,Data: 05/08/2026 10:28:13
E13: AI | F13: C3.ai | G13: =IFERROR(__xludf.DUMMYFUNCTION("GOOGLEFINANCE(E13, ""price"")"),10.89) -> 10.89 | K13: 2.45 | L13: 58 | M13: 27.5 | N13: 1.61 | O13: S1 Up | P13: 25.85 | Q13: 45812.512 | R13: TRUE | S13: AI,Preço: 10.85,Dist MM20: 2.96%,Momentum: 0.51,RSI: 56.45,ADX: 24.07,ATR: 0.50,RVOL: 0.72,Estado: Observar,Entrada: N/A,Stop: N/A,Take-Profit: N/A,Break-Even: N/A,Qtd: N/A,Trailing: 9.85,Data: 23/09/2026 06:49:38 | T13: 0 | U13: AI | V13: Preço: 9.07 | W13: Dist MM20: 2.72% | X13: Momentum: 0.12 | Y13: RSI: 51.28 | Z13: ADX: 16.64 | AA13: ATR: 0.45 | AB13: RVOL: 0.72 | AC13: Data: 31/07/2026 03:53:52 | AD13: 46030.371 | AE13: AI,Preço: 9.07,Dist MM20: 2.72%,Momentum: 0.12,RSI: 51.28,ADX: 16.64,ATR: 0.45,RVOL: 0.72,Estado: Aguardar Recuo,Entrada: 8.89,Stop: 8.44,Take-Profit: 9.79,Break-Even: 9.34,Qtd: 111.11,Data: 31/07/2026 03:53:52
E14: ALTG | F14: Alta Equipment | G14: =IFERROR(__xludf.DUMMYFUNCTION("GOOGLEFINANCE(E14, ""price"")"),6.19) -> 6.19 | R14: TRUE | S14: ALTG,Preço: 6.28,Dist MM20: 5.04%,Momentum: 0.56,RSI: 52.49,ADX: 18.57,ATR: 0.32,RVOL: 1.19,Estado: Aguardar Recuo,Entrada: 6.15,Stop: 5.83,Take-Profit: 6.53,Break-Even: 6.34,Qtd: 78.12,Trailing: 5.83,Data: 23/09/2026 06:49:55 | T14: 0 | U14: ALTG | V14: Preço: 6.07 | W14: Dist MM20: -4.54% | X14: Momentum: -0.55 | Y14: RSI: 42.11 | Z14: ADX: 9.80 | AA14: ATR: 0.39 | AB14: RVOL: 0.57 | AC14: Data: 31/07/2026 04:50:03 | AD14: 46030.371 | AE14: ALTG,Preço: 6.07,Dist MM20: -4.54%,Momentum: -0.55,RSI: 42.11,ADX: 9.80,ATR: 0.39,RVOL: 0.57,Estado: Aguardar Recuo,Entrada: 5.91,Stop: 5.52,Take-Profit: 6.69,Break-Even: 6.30,Qtd: 128.21,Data: 31/07/2026 04:50:03
B15: Time Now | C15: =now() -> 46288.715 | E15: AMD | F15: AMD US | G15: =IFERROR(__xludf.DUMMYFUNCTION("GOOGLEFINANCE(E15, ""price"")"),612.95) -> 612.95 | H15: =IFERROR(__xludf.DUMMYFUNCTION("GOOGLEFINANCE(E15, ""low"")"),608.08) -> 608.08 | I15: =IFERROR(__xludf.DUMMYFUNCTION("GOOGLEFINANCE(E15, ""high"")"),624.69) -> 624.69 | R15: TRUE | S15: AMD,Preço: 623.77,Dist MM20: 23.22%,Momentum: 164.16,RSI: 73.88,ADX: 19.74,ATR: 19.97,RVOL: 1.33,Estado: Aguardar Recuo,Entrada: 615.78,Stop: 595.81,Take-Profit: 639.74,Break-Even: 627.76,Qtd: 1.25,Trailing: 595.81,Data: 23/09/2026 02:05:39 | T15: 0 | U15: AMD | V15: Preço: 485.39 | W15: Dist MM20: -6.14% | X15: Momentum: -72.50 | Y15: RSI: 46.51 | Z15: ADX: 15.51 | AA15: ATR: 33.75 | AB15: RVOL: 1.26 | AC15: Data: 31/07/2026 02:05:58 | AD15: 46030.371 | AE15: AMD,Preço: 485.39,Dist MM20: -6.14%,Momentum: -72.50,RSI: 46.51,ADX: 15.51,ATR: 33.75,RVOL: 1.26,Estado: Aguardar Recuo,Entrada: 471.89,Stop: 438.14,Take-Profit: 539.39,Break-Even: 505.64,Qtd: 1.48,Data: 31/07/2026 02:05:58
E16: AMPL | F16: Amplitude | G16: =IFERROR(__xludf.DUMMYFUNCTION("GOOGLEFINANCE(E16, ""price"")"),13.68) -> 13.68 | H16: =IFERROR(__xludf.DUMMYFUNCTION("GOOGLEFINANCE(E16, ""low"")"),12.84) -> 12.84 | I16: =IFERROR(__xludf.DUMMYFUNCTION("GOOGLEFINANCE(E16, ""high"")"),13.71) -> 13.71 | R16: TRUE | S16: AMPL,Preço: 13.14,Dist MM20: -1.38%,Momentum: -0.69,RSI: 53.59,ADX: 24.56,ATR: 0.65,RVOL: 0.98,Estado: Alerta Iminente,Entrada: 13.01,Stop: 12.23,Take-Profit: 13.95,Break-Even: 13.48,Qtd: 32.05,Trailing: 12.23,Data: 23/09/2026 06:50:13 | T16: 0 | U16: AMPL | V16: Preço: 8.61 | W16: Dist MM20: -5.09% | X16: Momentum: -0.57 | Y16: RSI: 50.66 | Z16: ADX: 23.53 | AA16: ATR: 0.62 | AB16: RVOL: 0.80 | AC16: Data: 31/07/2026 03:51:57 | AD16: 46030.371 | AE16: AMPL,Preço: 8.61,Dist MM20: -5.09%,Momentum: -0.57,RSI: 50.66,ADX: 23.53,ATR: 0.62,RVOL: 0.80,Estado: Observar,Entrada: N/A,Stop: N/A,Take-Profit: N/A,Break-Even: N/A,Qtd: N/A,Data: 31/07/2026 03:51:57
E17: AMZN | F17: Amazon US | G17: =IFERROR(__xludf.DUMMYFUNCTION("GOOGLEFINANCE(E17, ""price"")"),250.45) -> 250.45 | H17: =IFERROR(__xludf.DUMMYFUNCTION("GOOGLEFINANCE(E17, ""low"")"),248.19) -> 248.19 | I17: =IFERROR(__xludf.DUMMYFUNCTION("GOOGLEFINANCE(E17, ""high"")"),253.99) -> 253.99 | K17: 1.93 | L17: 58.43 | M17: 18.49 | N17: 5.28 | O17: R1 Up | P17: 206 | Q17: 45812.24 | R17: TRUE | S17: AMZN,Preço: 254.98,Dist MM20: -0.31%,Momentum: 0.06,RSI: 49.22,ADX: 11.57,ATR: 4.42,RVOL: 1.22,Estado: Observar,Entrada: N/A,Stop: N/A,Take-Profit: N/A,Break-Even: N/A,Qtd: N/A,Trailing: 246.14,Data: 23/09/2026 02:05:59 | T17: 0 | U17: AMZN | V17: Preço: 235.50 | W17: Dist MM20: -2.85% | X17: Momentum: -9.84 | Y17: RSI: 44.41 | Z17: ADX: 18.82 | AA17: ATR: 5.91 | AB17: RVOL: 1.95 | AC17: Data: 31/07/2026 02:05:42 | AD17: 46030.371 | AE17: AMZN,Preço: 235.50,Dist MM20: -2.85%,Momentum: -9.84,RSI: 44.41,ADX: 18.82,ATR: 5.91,RVOL: 1.95,Estado: Aguardar Recuo,Entrada: 233.14,Stop: 227.23,Take-Profit: 244.96,Break-Even: 239.05,Qtd: 8.46,Data: 31/07/2026 02:05:42
E18: ANET | F18: Arista Networks | G18: =IFERROR(__xludf.DUMMYFUNCTION("GOOGLEFINANCE(E18, ""price"")"),201.68) -> 201.68 | K18: 19.88 | L18: 75.4 | M18: 28.09 | N18: 4.4 | O18: P Up | P18: 145.81 | Q18: 45918.484 | R18: TRUE | S18: ANET,Preço: 205.19,Dist MM20: 4.95%,Momentum: 15.93,RSI: 59.62,ADX: 16.51,ATR: 6.36,RVOL: 0.89,Estado: Observar,Entrada: N/A,Stop: N/A,Take-Profit: N/A,Break-Even: N/A,Qtd: N/A,Trailing: 192.47,Data: 23/09/2026 06:44:43 | T18: 0 | U18: ANET | V18: Preço: 171.02 | W18: Dist MM20: -1.26% | X18: Momentum: -15.94 | Y18: RSI: 50.85 | Z18: ADX: 13.89 | AA18: ATR: 9.32 | AB18: RVOL: 0.81 | AC18: Data: 31/07/2026 03:52:29 | AD18: 46030.371 | AE18: ANET,Preço: 171.02,Dist MM20: -1.26%,Momentum: -15.94,RSI: 50.85,ADX: 13.89,ATR: 9.32,RVOL: 0.81,Estado: Aguardar Recuo,Entrada: 167.29,Stop: 157.97,Take-Profit: 185.93,Break-Even: 176.61,Qtd: 5.36,Data: 31/07/2026 03:52:29
E19: ANF | F19: Abercrombie & Fitch | G19: =IFERROR(__xludf.DUMMYFUNCTION("GOOGLEFINANCE(E19, ""price"")"),132.25) -> 132.25 | H19: =IFERROR(__xludf.DUMMYFUNCTION("GOOGLEFINANCE(E19, ""low"")"),130.81) -> 130.81 | I19: =IFERROR(__xludf.DUMMYFUNCTION("GOOGLEFINANCE(E19, ""high"")"),141.74) -> 141.74 | P19: 90.18 | Q19: 45805.765 | R19: TRUE | S19: ANF,Preço: 136.21,Dist MM20: -3.37%,Momentum: -4.47,RSI: 53.84,ADX: 27.75,ATR: 5.70,RVOL: 0.51,Estado: Observar,Entrada: N/A,Stop: N/A,Take-Profit: N/A,Break-Even: N/A,Qtd: N/A,Trailing: 124.81,Data: 23/09/2026 02:06:17 | T19: 0 | U19: ANF | V19: Preço: 99.54 | W19: Dist MM20: 5.10% | X19: Momentum: 7.95 | Y19: RSI: 58.98 | Z19: ADX: 21.80 | AA19: ATR: 4.01 | AB19: RVOL: 0.70 | AC19: Data: 01/08/2026 07:08:40 | AD19: 46030.371 | AE19: ANF,Preço: 99.54,Dist MM20: 5.10%,Momentum: 7.95,RSI: 58.98,ADX: 21.80,ATR: 4.01,RVOL: 0.70,Estado: Observar,Entrada: N/A,Stop: N/A,Take-Profit: N/A,Break-Even: N/A,Qtd: N/A,Data: 01/08/2026 07:08:40
E20: APP | F20: Applovin | G20: =IFERROR(__xludf.DUMMYFUNCTION("GOOGLEFINANCE(E20, ""price"")"),312.02) -> 312.02 | H20: =IFERROR(__xludf.DUMMYFUNCTION("GOOGLEFINANCE(E20, ""low"")"),304.77) -> 304.77 | I20: =IFERROR(__xludf.DUMMYFUNCTION("GOOGLEFINANCE(E20, ""high"")"),316.0) -> 316 | R20: TRUE | S20: APP,Preço: 328.73,Dist MM20: 3.34%,Momentum: 16.99,RSI: 49.59,ADX: 17.45,ATR: 16.11,RVOL: 0.70,Estado: Observar,Entrada: N/A,Stop: N/A,Take-Profit: N/A,Break-Even: N/A,Qtd: N/A,Trailing: 296.51,Data: 23/09/2026 06:44:38 | T20: 0 | U20: APP | V20: Preço: 403.87 | W20: Dist MM20: -10.68% | X20: Momentum: -103.11 | Y20: RSI: 37.52 | Z20: ADX: 24.20 | AA20: ATR: 22.62 | AB20: RVOL: 1.31 | AC20: Data: 31/07/2026 03:52:13 | AD20: 46030.371 | AE20: APP,Preço: 403.87,Dist MM20: -10.68%,Momentum: -103.11,RSI: 37.52,ADX: 24.20,ATR: 22.62,RVOL: 1.31,Estado: Aguardar Recuo,Entrada: 394.82,Stop: 372.20,Take-Profit: 440.06,Break-Even: 417.44,Qtd: 2.21,Data: 31/07/2026 03:52:13
E21: ARES | F21: Ares Management | G21: =IFERROR(__xludf.DUMMYFUNCTION("GOOGLEFINANCE(E21, ""price"")"),122.54) -> 122.54 | H21: =IFERROR(__xludf.DUMMYFUNCTION("GOOGLEFINANCE(E21, ""low"")"),121.21) -> 121.21 | I21: =IFERROR(__xludf.DUMMYFUNCTION("GOOGLEFINANCE(E21, ""high"")"),123.96) -> 123.96 | R21: TRUE | S21: ARES,Preço: 124.72,Dist MM20: -7.35%,Momentum: -14.37,RSI: 36.30,ADX: 26.83,ATR: 4.38,RVOL: 1.06,Estado: Observar,Entrada: N/A,Stop: N/A,Take-Profit: N/A,Break-Even: N/A,Qtd: N/A,Trailing: 115.96,Data: 23/09/2026 06:51:14 | T21: 0 | U21: ARES | V21: Preço: 124.12 | W21: Dist MM20: 1.27% | X21: Momentum: 2.31 | Y21: RSI: 52.22 | Z21: ADX: 13.78 | AA21: ATR: 4.32 | AB21: RVOL: 1.30 | AC21: Data: 31/07/2026 04:37:29 | AD21: 46030.371 | AE21: ARES,Preço: 124.12,Dist MM20: 1.27%,Momentum: 2.31,RSI: 52.22,ADX: 13.78,ATR: 4.32,RVOL: 1.30,Estado: Observar,Entrada: N/A,Stop: N/A,Take-Profit: N/A,Break-Even: N/A,Qtd: N/A,Data: 31/07/2026 04:37:29
E22: AS | F22: Amer Sports | G22: =IFERROR(__xludf.DUMMYFUNCTION("GOOGLEFINANCE(E22, ""price"")"),27.17) -> 27.17 | H22: =IFERROR(__xludf.DUMMYFUNCTION("GOOGLEFINANCE(E22, ""low"")"),26.91) -> 26.91 | I22: =IFERROR(__xludf.DUMMYFUNCTION("GOOGLEFINANCE(E22, ""high"")"),27.63) -> 27.63 | K22: 6.06 | L22: 72.57 | M22: 22 | N22: 1.48 | O22: R1 Up | P22: 30.5 | Q22: 45796.329 | R22: TRUE | S22: AS,Preço: 27.65,Dist MM20: -3.35%,Momentum: -1.81,RSI: 39.27,ADX: 38.28,ATR: 0.95,RVOL: 1.01,Estado: Observar,Entrada: N/A,Stop: N/A,Take-Profit: N/A,Break-Even: N/A,Qtd: N/A,Trailing: 25.75,Data: 23/09/2026 06:51:14 | T22: 0 | U22: AS | V22: Preço: 36.10 | W22: Dist MM20: 3.32% | X22: Momentum: 1.30 | Y22: RSI: 56.80 | Z22: ADX: 12.34 | AA22: ATR: 1.28 | AB22: RVOL: 0.93 | AC22: Data: 31/07/2026 03:51:40 | AD22: 46030.371 | AE22: AS,Preço: 36.10,Dist MM20: 3.32%,Momentum: 1.30,RSI: 56.80,ADX: 12.34,ATR: 1.28,RVOL: 0.93,Estado: Aguardar Recuo,Entrada: 35.59,Stop: 34.31,Take-Profit: 38.15,Break-Even: 36.87,Qtd: 39.06,Data: 31/07/2026 03:51:40
B23: Time Now | C23: =now() -> 46288.715 | E23: ASTS | F23: Ast SpaceMobile | G23: =IFERROR(__xludf.DUMMYFUNCTION("GOOGLEFINANCE(E23, ""price"")"),61.7) -> 61.7 | H23: =IFERROR(__xludf.DUMMYFUNCTION("GOOGLEFINANCE(E23, ""low"")"),61.38) -> 61.38 | I23: =IFERROR(__xludf.DUMMYFUNCTION("GOOGLEFINANCE(E23, ""high"")"),63.79) -> 63.79 | K23: -25.79 | L23: 34.66 | M23: 17.28 | N23: 7.47 | O23: R1 Up | P23: 60.53 | Q23: 46219.377 | R23: TRUE | S23: ASTS,Preço: 63.69,Dist MM20: 4.73%,Momentum: 7.89,RSI: 51.86,ADX: 10.72,ATR: 3.74,RVOL: 1.06,Estado: Aguardar Recuo,Entrada: 62.19,Stop: 58.45,Take-Profit: 66.68,Break-Even: 64.44,Qtd: 6.68,Trailing: 58.45,Data: 23/09/2026 02:06:34 | T23: 0 | U23: ASTS | V23: Preço: 58.98 | W23: Dist MM20: -7.55% | X23: Momentum: -8.60 | Y23: RSI: 41.74 | Z23: ADX: 26.86 | AA23: ATR: 4.94 | AB23: RVOL: 0.64 | AC23: Data: 01/08/2026 07:38:36 | AD23: 46030.371 | AE23: ASTS,Preço: 58.98,Dist MM20: -7.55%,Momentum: -8.60,RSI: 41.74,ADX: 26.86,ATR: 4.94,RVOL: 0.64,Estado: Forca Consolidada,Entrada: 57.99,Stop: 52.06,Take-Profit: 66.88,Break-Even: 62.44,Qtd: 8.43,Data: 01/08/2026 07:38:36
E24: AVGO | F24: Broadcom | G24: =IFERROR(__xludf.DUMMYFUNCTION("GOOGLEFINANCE(E24, ""price"")"),356.26) -> 356.26 | H24: =IFERROR(__xludf.DUMMYFUNCTION("GOOGLEFINANCE(E24, ""low"")"),354.8) -> 354.8 | I24: =IFERROR(__xludf.DUMMYFUNCTION("GOOGLEFINANCE(E24, ""high"")"),362.9) -> 362.9 | K24: 26.17 | L24: 81.35 | M24: 35.38 | N24: 7.33 | O24: R1 Up | P24: 248.89 | Q24: 45814.126 | R24: TRUE | S24: AVGO,Preço: 364.54,Dist MM20: 1.45%,Momentum: -5.14,RSI: 49.76,ADX: 23.98,ATR: 8.62,RVOL: 0.75,Estado: Observar,Entrada: N/A,Stop: N/A,Take-Profit: N/A,Break-Even: N/A,Qtd: N/A,Trailing: 347.30,Data: 23/09/2026 02:06:51 | T24: 0 | U24: AVGO | V24: Preço: 387.84 | W24: Dist MM20: 1.19% | X24: Momentum: -12.13 | Y24: RSI: 50.89 | Z24: ADX: 15.44 | AA24: ATR: 13.50 | AB24: RVOL: 1.05 | AC24: Data: 31/07/2026 02:07:04 | AD24: 46030.371 | AE24: AVGO,Preço: 387.84,Dist MM20: 1.19%,Momentum: -12.13,RSI: 50.89,ADX: 15.44,ATR: 13.50,RVOL: 1.05,Estado: Aguardar Recuo,Entrada: 382.44,Stop: 368.94,Take-Profit: 409.44,Break-Even: 395.94,Qtd: 3.70,Data: 31/07/2026 02:07:04
E25: AZN | F25: Astra Zeneca | G25: =IFERROR(__xludf.DUMMYFUNCTION("GOOGLEFINANCE(E25, ""price"")"),164.46) -> 164.46 | R25: TRUE | S25: AZN,Preço: 168.37,Dist MM20: 2.95%,Momentum: 5.90,RSI: 58.50,ADX: 12.80,ATR: 2.94,RVOL: 0.74,Estado: Aguardar Recuo,Entrada: 167.19,Stop: 164.25,Take-Profit: 170.72,Break-Even: 168.95,Qtd: 8.50,Trailing: 164.25,Data: 23/09/2026 06:51:11 | T25: 0 | U25: AZN | V25: Preço: 162.89 | W25: Dist MM20: -0.20% | X25: Momentum: -3.38 | Y25: RSI: 49.54 | Z25: ADX: 13.54 | AA25: ATR: 2.93 | AB25: RVOL: 1.19 | AC25: Trailing: 158.79 | AD25: 17/09/2026 03:54:54 | AE25: AZN,Preço: 162.89,Dist MM20: -0.20%,Momentum: -3.38,RSI: 49.54,ADX: 13.54,ATR: 2.93,RVOL: 1.19,Estado: Aguardar Recuo,Entrada: 161.72,Stop: 158.79,Take-Profit: 167.58,Break-Even: 164.65,Qtd: 17.06,Trailing: 158.79,Data: 17/09/2026 03:51:59
E26: BA | F26: Boeing | G26: =IFERROR(__xludf.DUMMYFUNCTION("GOOGLEFINANCE(E26, ""price"")"),201.51) -> 201.51 | H26: =IFERROR(__xludf.DUMMYFUNCTION("GOOGLEFINANCE(E26, ""low"")"),197.98) -> 197.98 | I26: =IFERROR(__xludf.DUMMYFUNCTION("GOOGLEFINANCE(E26, ""high"")"),204.07) -> 204.07 | L26: 45.52 | M26: 35.64 | N26: 5.79 | O26: P Down | P26: 198.22 | Q26: 45821.674 | R26: TRUE | S26: BA,Preço: 197.72,Dist MM20: -4.40%,Momentum: -7.94,RSI: 35.11,ADX: 28.13,ATR: 5.42,RVOL: 1.31,Estado: Observar,Entrada: N/A,Stop: N/A,Take-Profit: N/A,Break-Even: N/A,Qtd: N/A,Trailing: 186.88,Data: 23/09/2026 06:51:13 | T26: 0 | U26: BA | V26: Preço: 220.90 | W26: Dist MM20: 1.52% | X26: Momentum: -1.38 | Y26: RSI: 53.88 | Z26: ADX: 14.24 | AA26: ATR: 6.58 | AB26: RVOL: 0.73 | AC26: Data: 31/07/2026 03:53:36 | AD26: 46030.371 | AE26: BA,Preço: 220.90,Dist MM20: 1.52%,Momentum: -1.38,RSI: 53.88,ADX: 14.24,ATR: 6.58,RVOL: 0.73,Estado: Aguardar Recuo,Entrada: 218.27,Stop: 211.69,Take-Profit: 231.43,Break-Even: 224.85,Qtd: 7.60,Data: 31/07/2026 03:53:36
E27: BABA | F27: Alibaba US | G27: =IFERROR(__xludf.DUMMYFUNCTION("GOOGLEFINANCE(E27, ""price"")"),110.98) -> 110.98 | H27: =IFERROR(__xludf.DUMMYFUNCTION("GOOGLEFINANCE(E27, ""low"")"),110.87) -> 110.87 | I27: =IFERROR(__xludf.DUMMYFUNCTION("GOOGLEFINANCE(E27, ""high"")"),112.28) -> 112.28 | O27: R3 Down | P27: 117.11 | Q27: 45856.305 | R27: TRUE | S27: BABA,Preço: 116.31,Dist MM20: 3.03%,Momentum: 3.46,RSI: 53.69,ADX: 20.42,ATR: 2.24,RVOL: 1.47,Estado: Alerta Iminente,Entrada: 115.86,Stop: 113.17,Take-Profit: 119.09,Break-Even: 117.47,Qtd: 9.30,Trailing: 113.17,Data: 23/09/2026 02:07:09 | T27: 0 | U27: BABA | V27: Preço: 116.32 | W27: Dist MM20: 3.76% | X27: Momentum: 3.99 | Y27: RSI: 56.06 | Z27: ADX: 24.66 | AA27: ATR: 2.68 | AB27: RVOL: 0.65 | AC27: Data: 31/07/2026 02:04:58 | AD27: 46030.371 | AE27: BABA,Preço: 116.32,Dist MM20: 3.76%,Momentum: 3.99,RSI: 56.06,ADX: 24.66,ATR: 2.68,RVOL: 0.65,Estado: Aguardar Recuo,Entrada: 115.25,Stop: 112.57,Take-Profit: 120.61,Break-Even: 117.93,Qtd: 18.66,Data: 31/07/2026 02:04:58
E28: BBAI | F28: BigBear Ai | G28: =IFERROR(__xludf.DUMMYFUNCTION("GOOGLEFINANCE(E28, ""price"")"),2.89) -> 2.89 | H28: =IFERROR(__xludf.DUMMYFUNCTION("GOOGLEFINANCE(E28, ""low"")"),2.84) -> 2.84 | I28: =IFERROR(__xludf.DUMMYFUNCTION("GOOGLEFINANCE(E28, ""high"")"),2.9) -> 2.9 | K28: -0.46 | L28: 63.98 | M28: 47.18 | N28: 0.71 | O28: P Up | P28: 7.1 | Q28: 45855.329 | R28: TRUE | S28: BBAI,Preço: 2.89,Dist MM20: -1.38%,Momentum: -0.06,RSI: 46.44,ADX: 13.82,ATR: 0.12,RVOL: 0.73,Estado: Observar,Entrada: N/A,Stop: N/A,Take-Profit: N/A,Break-Even: N/A,Qtd: N/A,Trailing: 2.65,Data: 23/09/2026 02:19:30 | T28: 0 | U28: BBAI | V28: Preço: 2.83 | W28: Dist MM20: -6.89% | X28: Momentum: -0.44 | Y28: RSI: 37.96 | Z28: ADX: 32.30 | AA28: ATR: 0.17 | AB28: RVOL: 1.16 | AC28: Data: 31/07/2026 03:53:19 | AD28: 46030.371 | AE28: BBAI,Preço: 2.83,Dist MM20: -6.89%,Momentum: -0.44,RSI: 37.96,ADX: 32.30,ATR: 0.17,RVOL: 1.16,Estado: Forca Consolidada,Entrada: 2.80,Stop: 2.60,Take-Profit: 3.11,Break-Even: 2.96,Qtd: 245.10,Data: 31/07/2026 03:53:19
E29: BLK | F29: BlackRock | G29: =IFERROR(__xludf.DUMMYFUNCTION("GOOGLEFINANCE(E29, ""price"")"),1066.03) -> 1066.03 | R29: TRUE | S29: BLK,Preço: 1066.66,Dist MM20: -3.35%,Momentum: -61.44,RSI: 42.84,ADX: 28.72,ATR: 22.88,RVOL: 0.85,Estado: Observar,Entrada: N/A,Stop: N/A,Take-Profit: N/A,Break-Even: N/A,Qtd: N/A,Trailing: 1020.90,Data: 23/09/2026 06:51:08 | T29: 0 | U29: BLK | V29: Preço: 1131.13 | W29: Dist MM20: 6.29% | X29: Momentum: 37.73 | Y29: RSI: 65.33 | Z29: ADX: 22.82 | AA29: ATR: 28.08 | AB29: RVOL: 0.77 | AC29: Trailing: 1091.82 | AD29: 46150.444 | AE29: BLK,Preço: 1131.13,Dist MM20: 6.29%,Momentum: 37.73,RSI: 65.33,ADX: 22.82,ATR: 28.08,RVOL: 0.77,Estado: Aguardar Recuo,Entrada: 1119.90,Stop: 1091.82,Take-Profit: 1176.06,Break-Even: 1147.98,Qtd: 1.78,Trailing: 1091.82,Data: 05/08/2026 10:31:05
E30: BMI | F30: Badger Meter Inc | G30: =IFERROR(__xludf.DUMMYFUNCTION("GOOGLEFINANCE(E30, ""price"")"),133.4) -> 133.4 | H30: =IFERROR(__xludf.DUMMYFUNCTION("GOOGLEFINANCE(E30, ""low"")"),131.89) -> 131.89 | I30: =IFERROR(__xludf.DUMMYFUNCTION("GOOGLEFINANCE(E30, ""high"")"),134.29) -> 134.29 | K30: 10.75 | L30: 48.28 | M30: 28.46 | N30: 6,72 | O30: P Down | P30: 158.18 | Q30: 46072.143 | R30: TRUE | S30: BMI,Preço: 132.26,Dist MM20: 0.67%,Momentum: -0.01,RSI: 51.87,ADX: 15.63,ATR: 3.94,RVOL: 0.93,Estado: Aguardar Recuo,Entrada: 130.68,Stop: 126.74,Take-Profit: 135.41,Break-Even: 133.05,Qtd: 6.35,Trailing: 126.74,Data: 23/09/2026 06:51:07 | T30: 0 | U30: BMI | V30: Preço: 130.39 | W30: Dist MM20: -6.85% | X30: Momentum: -13.79 | Y30: RSI: 43.47 | Z30: ADX: 18.04 | AA30: ATR: 6.87 | AB30: RVOL: 0.80 | AC30: Data: 31/07/2026 04:37:46 | AD30: 46030.371 | AE30: BMI,Preço: 130.39,Dist MM20: -6.85%,Momentum: -13.79,RSI: 43.47,ADX: 18.04,ATR: 6.87,RVOL: 0.80,Estado: Observar,Entrada: N/A,Stop: N/A,Take-Profit: N/A,Break-Even: N/A,Qtd: N/A,Data: 31/07/2026 04:37:46
E31: BMNR | F31: BitMine Immersion | G31: =IFERROR(__xludf.DUMMYFUNCTION("GOOGLEFINANCE(E31, ""price"")"),27.53) -> 27.53 | R31: TRUE | S31: BMNR,Preço: 28.76,Dist MM20: 15.13%,Momentum: 5.39,RSI: 67.30,ADX: 42.47,ATR: 1.50,RVOL: 0.88,Estado: Observar,Entrada: N/A,Stop: N/A,Take-Profit: N/A,Break-Even: N/A,Qtd: N/A,Trailing: 25.76,Data: 23/09/2026 06:50:55 | T31: 0 | U31: BMNR | V31: Preço: 18.08 | W31: Dist MM20: 5.18% | X31: Momentum: 0.85 | Y31: RSI: 55.65 | Z31: ADX: 22.05 | AA31: ATR: 1.18 | AB31: RVOL: 0.65 | AC31: Trailing: 15.72 | AD31: 46303.944 | AE31: BMNR,Preço: 18.08,Dist MM20: 5.18%,Momentum: 0.85,RSI: 55.65,ADX: 22.05,ATR: 1.18,RVOL: 0.65,Estado: Observar,Entrada: N/A,Stop: N/A,Take-Profit: N/A,Break-Even: N/A,Qtd: N/A,Trailing: 15.72,Data: 10/08/2026 22:31:47
E32: BOLT | F32: Bolt Biotherapeutics | G32: =IFERROR(__xludf.DUMMYFUNCTION("GOOGLEFINANCE(E32, ""price"")"),3.9) -> 3.9 | R32: TRUE | S32: BOLT,Preço: 3.71,Dist MM20: -2.79%,Momentum: -0.36,RSI: 48.68,ADX: 17.32,ATR: 0.38,RVOL: 0.47,Estado: Aguardar Recuo,Entrada: 3.56,Stop: 3.18,Take-Profit: 4.02,Break-Even: 3.79,Qtd: 65.79,Trailing: 3.18,Data: 23/09/2026 06:50:57 | T32: 0 | U32: BOLT | V32: Preço: 3.89 | W32: Dist MM20: -3.38% | X32: Momentum: 0.11 | Y32: RSI: 43.93 | Z32: ADX: 18.48 | AA32: ATR: 0.24 | AB32: RVOL: 0.77 | AC32: Data: 31/07/2026 04:39:45 | AD32: 46030.371 | AE32: BOLT,Preço: 3.89,Dist MM20: -3.38%,Momentum: 0.11,RSI: 43.93,ADX: 18.48,ATR: 0.24,RVOL: 0.77,Estado: Aguardar Recuo,Entrada: 3.79,Stop: 3.55,Take-Profit: 4.27,Break-Even: 4.03,Qtd: 208.33,Data: 31/07/2026 04:39:45
E33: BRK.B | F33: Berkshire Hathaway | G33: =IFERROR(__xludf.DUMMYFUNCTION("GOOGLEFINANCE(E33, ""price"")"),508.51) -> 508.51 | H33: =IFERROR(__xludf.DUMMYFUNCTION("GOOGLEFINANCE(E33, ""low"")"),502.81) -> 502.81 | I33: =IFERROR(__xludf.DUMMYFUNCTION("GOOGLEFINANCE(E33, ""high"")"),509.85) -> 509.85 | K33: 3.53 | L33: 60.7 | M33: 12.67 | N33: 6.13 | P33: 480.42 | Q33: 45709.678 | R33: TRUE | S33: BRK.B,Preço: 503.49,Dist MM20: -0.79%,Momentum: 1.16,RSI: 45.55,ADX: 13.44,ATR: 6.23,RVOL: 1.00,Estado: Aguardar Recuo,Entrada: 501.00,Stop: 494.77,Take-Profit: 508.48,Break-Even: 504.74,Qtd: 4.01,Trailing: 494.77,Data: 23/09/2026 02:19:48 | T33: 0 | U33: BRK.B | V33: Preço: 509.68 | W33: Dist MM20: 2.48% | X33: Momentum: 15.97 | Y33: RSI: 64.62 | Z33: ADX: 20.33 | AA33: ATR: 6.83 | AB33: RVOL: 0.74 | AC33: Data: 31/07/2026 02:06:48 | AD33: 46030.371 | AE33: BRK.B,Preço: 509.68,Dist MM20: 2.48%,Momentum: 15.97,RSI: 64.62,ADX: 20.33,ATR: 6.83,RVOL: 0.74,Estado: Aguardar Recuo,Entrada: 506.95,Stop: 500.12,Take-Profit: 520.61,Break-Even: 513.78,Qtd: 7.32,Data: 31/07/2026 02:06:48
B34: Time Now | C34: =now() -> 46288.715 | E34: BROS | F34: Dutch Bros | G34: =IFERROR(__xludf.DUMMYFUNCTION("GOOGLEFINANCE(E34, ""price"")"),38.6) -> 38.6 | H34: =IFERROR(__xludf.DUMMYFUNCTION("GOOGLEFINANCE(E34, ""low"")"),37.72) -> 37.72 | I34: =IFERROR(__xludf.DUMMYFUNCTION("GOOGLEFINANCE(E34, ""high"")"),38.94) -> 38.94 | K34: 21.88 | L34: 82.05 | M34: 37.66 | N34: 3.53 | O34: R4 Up | P34: 86.5 | Q34: 45707.218 | R34: TRUE | S34: BROS,Preço: 38.76,Dist MM20: -14.13%,Momentum: -7.55,RSI: 21.95,ADX: 42.85,ATR: 1.70,RVOL: 1.37,Estado: Observar,Entrada: N/A,Stop: N/A,Take-Profit: N/A,Break-Even: N/A,Qtd: N/A,Trailing: 35.36,Data: 23/09/2026 06:51:27 | T34: 0 | U34: BROS | V34: Preço: 65.43 | W34: Dist MM20: -0.75% | X34: Momentum: -2.13 | Y34: RSI: 50.57 | Z34: ADX: 14.55 | AA34: ATR: 2.63 | AB34: RVOL: 0.64 | AC34: Data: 31/07/2026 04:05:25 | AD34: 46030.371 | AE34: BROS,Preço: 65.43,Dist MM20: -0.75%,Momentum: -2.13,RSI: 50.57,ADX: 14.55,ATR: 2.63,RVOL: 0.64,Estado: Aguardar Recuo,Entrada: 64.38,Stop: 61.75,Take-Profit: 69.64,Break-Even: 67.01,Qtd: 19.01,Data: 31/07/2026 04:05:25
E35: BYDDY | F35: BYD ADR | G35: =IFERROR(__xludf.DUMMYFUNCTION("GOOGLEFINANCE(E35, ""price"")"),10.14) -> 10.14 | H35: =IFERROR(__xludf.DUMMYFUNCTION("GOOGLEFINANCE(E35, ""low"")"),10.13) -> 10.13 | I35: =IFERROR(__xludf.DUMMYFUNCTION("GOOGLEFINANCE(E35, ""high"")"),10.22) -> 10.22 | P35: 99.11 | Q35: 45769.733 | R35: TRUE | S35: BYDDY,Preço: 10.36,Dist MM20: -3.26%,Momentum: -0.68,RSI: 40.64,ADX: 23.71,ATR: 0.12,RVOL: 0.27,Estado: Observar,Entrada: N/A,Stop: N/A,Take-Profit: N/A,Break-Even: N/A,Qtd: N/A,Trailing: 10.12,Data: 23/09/2026 02:20:07 | T35: 0 | U35: BYDDY | V35: Preço: 11.96 | W35: Dist MM20: 8.04% | X35: Momentum: 1.15 | Y35: RSI: 67.35 | Z35: ADX: 20.62 | AA35: ATR: 0.15 | AB35: RVOL: 0.57 | AC35: Data: 31/07/2026 02:07:22 | AD35: 46030.371 | AE35: BYDDY,Preço: 11.96,Dist MM20: 8.04%,Momentum: 1.15,RSI: 67.35,ADX: 20.62,ATR: 0.15,RVOL: 0.57,Estado: Aguardar Recuo,Entrada: 11.90,Stop: 11.75,Take-Profit: 12.20,Break-Even: 12.05,Qtd: 333.33,Data: 31/07/2026 02:07:22
E36: CAP | F36: Capgemini | G36: =IFERROR(__xludf.DUMMYFUNCTION("GOOGLEFINANCE(E36, ""price"")"),106.1) -> 106.1 | H36: =IFERROR(__xludf.DUMMYFUNCTION("GOOGLEFINANCE(E36, ""low"")"),104.65) -> 104.65 | I36: =IFERROR(__xludf.DUMMYFUNCTION("GOOGLEFINANCE(E36, ""high"")"),107.5) -> 107.5 | P36: 161.7 | R36: TRUE | S36: CAP,Preço: 19.50,Dist MM20: 0.00%,Momentum: 0.00,RSI: 59.04,ADX: 19.41,ATR: 0.00,RVOL: 0.05,Estado: Observar,Entrada: N/A,Stop: N/A,Take-Profit: N/A,Break-Even: N/A,Qtd: N/A,Trailing: 19.50,Data: 23/09/2026 06:51:29 | T36: 0 | U36: CAP | V36: Preço: 19.50 | W36: Dist MM20: 0.00% | X36: Momentum: 0.00 | Y36: RSI: 59.04 | Z36: ADX: 19.41 | AA36: ATR: 0.00 | AB36: RVOL: 0.05 | AC36: Data: 31/07/2026 03:54:09 | AD36: 46030.371 | AE36: CAP,Preço: 19.50,Dist MM20: 0.00%,Momentum: 0.00,RSI: 59.04,ADX: 19.41,ATR: 0.00,RVOL: 0.05,Estado: Observar,Entrada: N/A,Stop: N/A,Take-Profit: N/A,Break-Even: N/A,Qtd: N/A,Data: 31/07/2026 03:54:09
E37: CAR | F37: Avis Budget | G37: =IFERROR(__xludf.DUMMYFUNCTION("GOOGLEFINANCE(E37, ""price"")"),110.15) -> 110.15 | R37: TRUE | S37: CAR,Preço: 107.73,Dist MM20: -17.04%,Momentum: -32.97,RSI: 23.48,ADX: 27.30,ATR: 5.43,RVOL: 1.26,Estado: Observar,Entrada: N/A,Stop: N/A,Take-Profit: N/A,Break-Even: N/A,Qtd: N/A,Trailing: 96.87,Data: 23/09/2026 06:51:30 | T37: 0 | U37: CAR | V37: Preço: 152.00 | W37: Dist MM20: -4.44% | X37: Momentum: -4.19 | Y37: RSI: 41.14 | Z37: ADX: 9.37 | AA37: ATR: 8.17 | AB37: RVOL: 1.59 | AC37: Data: 31/07/2026 04:50:59 | AD37: 46030.371 | AE37: CAR,Preço: 152.00,Dist MM20: -4.44%,Momentum: -4.19,RSI: 41.14,ADX: 9.37,ATR: 8.17,RVOL: 1.59,Estado: Observar,Entrada: N/A,Stop: N/A,Take-Profit: N/A,Break-Even: N/A,Qtd: N/A,Data: 31/07/2026 04:50:59
E38: CB | F38: Chubb | G38: =IFERROR(__xludf.DUMMYFUNCTION("GOOGLEFINANCE(E38, ""price"")"),336.84) -> 336.84 | R38: TRUE | S38: CB,Preço: 335.77,Dist MM20: -1.30%,Momentum: -2.97,RSI: 41.12,ADX: 10.71,ATR: 4.96,RVOL: 0.89,Estado: Observar,Entrada: N/A,Stop: N/A,Take-Profit: N/A,Break-Even: N/A,Qtd: N/A,Trailing: 325.85,Data: 23/09/2026 06:51:30 | T38: 0 | U38: CB | V38: Preço: 348.30 | W38: Dist MM20: -0.91% | X38: Momentum: 10.86 | Y38: RSI: 49.81 | Z38: ADX: 15.39 | AA38: ATR: 7.29 | AB38: RVOL: 0.75 | AC38: Trailing: 338.09 | AD38: 46150.444 | AE38: CB,Preço: 348.30,Dist MM20: -0.91%,Momentum: 10.86,RSI: 49.81,ADX: 15.39,ATR: 7.29,RVOL: 0.75,Estado: Aguardar Recuo,Entrada: 345.38,Stop: 338.09,Take-Profit: 359.96,Break-Even: 352.67,Qtd: 6.86,Trailing: 338.09,Data: 05/08/2026 10:38:08
E39: CELH | F39: Celsius Holdings | G39: =IFERROR(__xludf.DUMMYFUNCTION("GOOGLEFINANCE(E39, ""price"")"),29.05) -> 29.05 | H39: =IFERROR(__xludf.DUMMYFUNCTION("GOOGLEFINANCE(E39, ""low"")"),28.7) -> 28.7 | I39: =IFERROR(__xludf.DUMMYFUNCTION("GOOGLEFINANCE(E39, ""high"")"),29.46) -> 29.46 | O39: P Up | P39: 57.5 | Q39: 45918.478 | R39: TRUE | S39: CELH,Preço: 29.39,Dist MM20: -2.28%,Momentum: -1.33,RSI: 49.71,ADX: 15.39,ATR: 1.03,RVOL: 0.96,Estado: Aguardar Recuo,Entrada: 28.97,Stop: 27.94,Take-Profit: 30.21,Break-Even: 29.59,Qtd: 24.27,Trailing: 27.94,Data: 23/09/2026 06:51:33 | T39: 0 | U39: CELH | V39: Preço: 29.35 | W39: Dist MM20: -1.42% | X39: Momentum: -1.25 | Y39: RSI: 49.50 | Z39: ADX: 12.68 | AA39: ATR: 1.23 | AB39: RVOL: 0.57 | AC39: Data: 31/07/2026 03:54:26 | AD39: 46030.371 | AE39: CELH,Preço: 29.35,Dist MM20: -1.42%,Momentum: -1.25,RSI: 49.50,ADX: 12.68,ATR: 1.23,RVOL: 0.57,Estado: Aguardar Recuo,Entrada: 28.86,Stop: 27.63,Take-Profit: 31.32,Break-Even: 30.09,Qtd: 40.65,Data: 31/07/2026 03:54:26
E40: CLSK | F40: Cleanspark | G40: =IFERROR(__xludf.DUMMYFUNCTION("GOOGLEFINANCE(E40, ""price"")"),14.81) -> 14.81 | H40: =IFERROR(__xludf.DUMMYFUNCTION("GOOGLEFINANCE(E40, ""low"")"),14.7) -> 14.7 | I40: =IFERROR(__xludf.DUMMYFUNCTION("GOOGLEFINANCE(E40, ""high"")"),15.22) -> 15.22 | P40: 9.16 | Q40: 45812.251 | R40: TRUE | S40: CLSK,Preço: 15.14,Dist MM20: 17.16%,Momentum: 4.08,RSI: 63.36,ADX: 16.28,ATR: 0.90,RVOL: 0.96,Estado: Aguardar Recuo,Entrada: 14.78,Stop: 13.88,Take-Profit: 15.86,Break-Even: 15.32,Qtd: 27.78,Trailing: 13.88,Data: 23/09/2026 06:51:24 | T40: 0 | U40: CLSK | V40: Preço: 14.54 | W40: Dist MM20: 6.94% | X40: Momentum: 1.69 | Y40: RSI: 51.36 | Z40: ADX: 14.41 | AA40: ATR: 1.32 | AB40: RVOL: 1.27 | AC40: Data: 31/07/2026 03:54:59 | AD40: 46030.371 | AE40: CLSK,Preço: 14.54,Dist MM20: 6.94%,Momentum: 1.69,RSI: 51.36,ADX: 14.41,ATR: 1.32,RVOL: 1.27,Estado: Aguardar Recuo,Entrada: 14.01,Stop: 12.69,Take-Profit: 16.65,Break-Even: 15.33,Qtd: 37.88,Data: 31/07/2026 03:54:59
B41: Time Now | C41: =now() -> 46288.715 | E41: CNA | F41: Centrica | G41: =IFERROR(__xludf.DUMMYFUNCTION("GOOGLEFINANCE(E41, ""price"")"),148.75) -> 148.75 | H41: =IFERROR(__xludf.DUMMYFUNCTION("GOOGLEFINANCE(E41, ""low"")"),147.95) -> 147.95 | I41: =IFERROR(__xludf.DUMMYFUNCTION("GOOGLEFINANCE(E41, ""high"")"),150.95) -> 150.95 | R41: TRUE | S41: CNA,Preço: 47.47,Dist MM20: -1.78%,Momentum: -1.21,RSI: 37.31,ADX: 28.01,ATR: 0.89,RVOL: 2.12,Estado: Observar,Entrada: N/A,Stop: N/A,Take-Profit: N/A,Break-Even: N/A,Qtd: N/A,Trailing: 45.69,Data: 23/09/2026 06:55:26 | T41: 0 | U41: CNA | V41: Preço: 53.26 | W41: Dist MM20: 1.84% | X41: Momentum: 1.96 | Y41: RSI: 60.21 | Z41: ADX: 35.97 | AA41: ATR: 1.20 | AB41: RVOL: 0.71 | AC41: Data: 31/07/2026 03:54:42 | AD41: 46030.371 | AE41: CNA,Preço: 53.26,Dist MM20: 1.84%,Momentum: 1.96,RSI: 60.21,ADX: 35.97,ATR: 1.20,RVOL: 0.71,Estado: Observar,Entrada: N/A,Stop: N/A,Take-Profit: N/A,Break-Even: N/A,Qtd: N/A,Data: 31/07/2026 03:54:42
E42: CNXC | F42: Concentrix | G42: =IFERROR(__xludf.DUMMYFUNCTION("GOOGLEFINANCE(E42, ""price"")"),30.25) -> 30.25 | H42: =IFERROR(__xludf.DUMMYFUNCTION("GOOGLEFINANCE(E42, ""low"")"),28.84) -> 28.84 | I42: =IFERROR(__xludf.DUMMYFUNCTION("GOOGLEFINANCE(E42, ""high"")"),31.26) -> 31.26 | K42: 4.27 | L42: 56.4 | M42: 14.94 | N42: 2.25 | O42: R1 | P42: 57.43 | Q42: 45841.422 | R42: TRUE | S42: CNXC,Preço: 30.51,Dist MM20: 4.40%,Momentum: -1.77,RSI: 59.65,ADX: 16.22,ATR: 1.82,RVOL: 1.48,Estado: Aguardar Recuo,Entrada: 29.78,Stop: 27.96,Take-Profit: 31.96,Break-Even: 30.87,Qtd: 13.74,Trailing: 27.96,Data: 23/09/2026 06:55:24 | T42: 0 | U42: CNXC | V42: Preço: 24.90 | W42: Dist MM20: 4.77% | X42: Momentum: 2.70 | Y42: RSI: 51.97 | Z42: ADX: 13.70 | AA42: ATR: 1.69 | AB42: RVOL: 0.57 | AC42: Data: 31/07/2026 04:04:34 | AD42: 46030.371 | AE42: CNXC,Preço: 24.90,Dist MM20: 4.77%,Momentum: 2.70,RSI: 51.97,ADX: 13.70,ATR: 1.69,RVOL: 0.57,Estado: Observar,Entrada: N/A,Stop: N/A,Take-Profit: N/A,Break-Even: N/A,Qtd: N/A,Data: 31/07/2026 04:04:34
E43: COP | F43: ConocoPhillips | G43: =IFERROR(__xludf.DUMMYFUNCTION("GOOGLEFINANCE(E43, ""price"")"),128.64) -> 128.64 | R43: TRUE | S43: COP,Preço: 125.27,Dist MM20: -6.25%,Momentum: -10.92,RSI: 39.81,ADX: 22.98,ATR: 3.26,RVOL: 1.29,Estado: Observar,Entrada: N/A,Stop: N/A,Take-Profit: N/A,Break-Even: N/A,Qtd: N/A,Trailing: 118.75,Data: 23/09/2026 06:55:23 | T43: 0 | U43: COP | V43: Preço: 132.54 | W43: Dist MM20: -1.39% | X43: Momentum: 1.93 | Y43: RSI: 51.47 | Z43: ADX: 26.76 | AA43: ATR: 3.17 | AB43: RVOL: 1.38 | AC43: Trailing: 128.11 | AD43: 17/09/2026 03:54:54 | AE43: COP,Preço: 132.54,Dist MM20: -1.39%,Momentum: 1.93,RSI: 51.47,ADX: 26.76,ATR: 3.17,RVOL: 1.38,Estado: Alerta Iminente,Entrada: 131.91,Stop: 128.11,Take-Profit: 137.62,Break-Even: 134.76,Qtd: 13.14,Trailing: 128.11,Data: 17/09/2026 03:47:46
E44: CRM | F44: Salesforce US | G44: =IFERROR(__xludf.DUMMYFUNCTION("GOOGLEFINANCE(E44, ""price"")"),238.9) -> 238.9 | H44: =IFERROR(__xludf.DUMMYFUNCTION("GOOGLEFINANCE(E44, ""low"")"),234.24) -> 234.24 | I44: =IFERROR(__xludf.DUMMYFUNCTION("GOOGLEFINANCE(E44, ""high"")"),239.14) -> 239.14 | R44: TRUE | S44: CRM,Preço: 233.28,Dist MM20: -5.09%,Momentum: -24.83,RSI: 50.04,ADX: 29.02,ATR: 7.98,RVOL: 0.70,Estado: Observar,Entrada: N/A,Stop: N/A,Take-Profit: N/A,Break-Even: N/A,Qtd: N/A,Trailing: 217.32,Data: 23/09/2026 02:20:26 | T44: 0 | U44: CRM | V44: Preço: 180.71 | W44: Dist MM20: 6.47% | X44: Momentum: 17.39 | Y44: RSI: 57.79 | Z44: ADX: 12.18 | AA44: ATR: 7.56 | AB44: RVOL: 0.79 | AC44: Data: 31/07/2026 02:23:24 | AD44: 46030.371 | AE44: CRM,Preço: 180.71,Dist MM20: 6.47%,Momentum: 17.39,RSI: 57.79,ADX: 12.18,ATR: 7.56,RVOL: 0.79,Estado: Observar,Entrada: N/A,Stop: N/A,Take-Profit: N/A,Break-Even: N/A,Qtd: N/A,Data: 31/07/2026 02:23:24
E45: CSCO | F45: Cisco Systems | G45: =IFERROR(__xludf.DUMMYFUNCTION("GOOGLEFINANCE(E45, ""price"")"),106.16) -> 106.16 | H45: =IFERROR(__xludf.DUMMYFUNCTION("GOOGLEFINANCE(E45, ""low"")"),105.95) -> 105.95 | I45: =IFERROR(__xludf.DUMMYFUNCTION("GOOGLEFINANCE(E45, ""high"")"),106.88) -> 106.88 | P45: 57.13 | Q45: 45827.333 | R45: TRUE | S45: CSCO,Preço: 106.44,Dist MM20: -3.09%,Momentum: -3.30,RSI: 40.79,ADX: 26.41,ATR: 2.56,RVOL: 1.97,Estado: Observar,Entrada: N/A,Stop: N/A,Take-Profit: N/A,Break-Even: N/A,Qtd: N/A,Trailing: 101.32,Data: 23/09/2026 02:20:44 | T45: 0 | U45: CSCO | V45: Preço: 113.56 | W45: Dist MM20: -0.38% | X45: Momentum: -7.75 | Y45: RSI: 48.13 | Z45: ADX: 15.56 | AA45: ATR: 3.51 | AB45: RVOL: 1.00 | AC45: Data: 31/07/2026 02:07:39 | AD45: 46030.371 | AE45: CSCO,Preço: 113.56,Dist MM20: -0.38%,Momentum: -7.75,RSI: 48.13,ADX: 15.56,ATR: 3.51,RVOL: 1.00,Estado: Aguardar Recuo,Entrada: 112.16,Stop: 108.65,Take-Profit: 119.18,Break-Even: 115.67,Qtd: 14.25,Data: 31/07/2026 02:07:39
E46: CVX | F46: Chevron | G46: =IFERROR(__xludf.DUMMYFUNCTION("GOOGLEFINANCE(E46, ""price"")"),206.33) -> 206.33 | R46: TRUE | S46: CVX,Preço: 202.41,Dist MM20: -2.91%,Momentum: -8.64,RSI: 44.59,ADX: 27.83,ATR: 4.11,RVOL: 0.93,Estado: Observar,Entrada: N/A,Stop: N/A,Take-Profit: N/A,Break-Even: N/A,Qtd: N/A,Trailing: 194.19,Data: 23/09/2026 06:51:43 | T46: 0 | U46: CVX | V46: Preço: 190.40 | W46: Dist MM20: 1.59% | X46: Momentum: 8.80 | Y46: RSI: 55.59 | Z46: ADX: 23.43 | AA46: ATR: 3.66 | AB46: RVOL: 1.25 | AC46: Trailing: 183.08 | AD46: 46150.444 | AE46: CVX,Preço: 190.40,Dist MM20: 1.59%,Momentum: 8.80,RSI: 55.59,ADX: 23.43,ATR: 3.66,RVOL: 1.25,Estado: Observar,Entrada: N/A,Stop: N/A,Take-Profit: N/A,Break-Even: N/A,Qtd: N/A,Trailing: 183.08,Data: 05/08/2026 10:26:06
E47: DASH | F47: DoorDash | G47: =IFERROR(__xludf.DUMMYFUNCTION("GOOGLEFINANCE(E47, ""price"")"),186.54) -> 186.54 | H47: =IFERROR(__xludf.DUMMYFUNCTION("GOOGLEFINANCE(E47, ""low"")"),184.85) -> 184.85 | I47: =IFERROR(__xludf.DUMMYFUNCTION("GOOGLEFINANCE(E47, ""high"")"),200.59) -> 200.59 | R47: TRUE | S47: DASH,Preço: 192.21,Dist MM20: -9.10%,Momentum: -33.45,RSI: 34.95,ADX: 25.70,ATR: 7.00,RVOL: 1.36,Estado: Observar,Entrada: N/A,Stop: N/A,Take-Profit: N/A,Break-Even: N/A,Qtd: N/A,Trailing: 178.21,Data: 23/09/2026 02:21:03 | T47: 0 | U47: DASH | V47: Preço: 197.53 | W47: Dist MM20: 5.18% | X47: Momentum: 5.71 | Y47: RSI: 61.21 | Z47: ADX: 21.68 | AA47: ATR: 7.96 | AB47: RVOL: 0.89 | AC47: Data: 31/07/2026 02:38:10 | AD47: 46030.371 | AE47: DASH,Preço: 197.53,Dist MM20: 5.18%,Momentum: 5.71,RSI: 61.21,ADX: 21.68,ATR: 7.96,RVOL: 0.89,Estado: Aguardar Recuo,Entrada: 194.35,Stop: 186.39,Take-Profit: 210.27,Break-Even: 202.31,Qtd: 6.28,Data: 31/07/2026 02:38:10
E48: DBX | F48: Dropbox | G48: =IFERROR(__xludf.DUMMYFUNCTION("GOOGLEFINANCE(E48, ""price"")"),34.09) -> 34.09 | H48: =IFERROR(__xludf.DUMMYFUNCTION("GOOGLEFINANCE(E48, ""low"")"),33.3) -> 33.3 | I48: =IFERROR(__xludf.DUMMYFUNCTION("GOOGLEFINANCE(E48, ""high"")"),34.12) -> 34.12 | O48: P Down | P48: 31.77 | Q48: 45708.793 | R48: TRUE | S48: DBX,Preço: 33.90,Dist MM20: -4.69%,Momentum: -0.36,RSI: 43.68,ADX: 25.77,ATR: 1.25,RVOL: 2.31,Estado: Observar,Entrada: N/A,Stop: N/A,Take-Profit: N/A,Break-Even: N/A,Qtd: N/A,Trailing: 31.40,Data: 23/09/2026 06:50:45 | T48: 0 | U48: DBX | V48: Preço: 32.11 | W48: Dist MM20: 7.28% | X48: Momentum: 2.92 | Y48: RSI: 64.46 | Z48: ADX: 17.82 | AA48: ATR: 1.04 | AB48: RVOL: 1.09 | AC48: Data: 31/07/2026 04:05:08 | AD48: 46030.371 | AE48: DBX,Preço: 32.11,Dist MM20: 7.28%,Momentum: 2.92,RSI: 64.46,ADX: 17.82,ATR: 1.04,RVOL: 1.09,Estado: Observar,Entrada: N/A,Stop: N/A,Take-Profit: N/A,Break-Even: N/A,Qtd: N/A,Data: 31/07/2026 04:05:08
E49: DDOG | F49: Datadog | G49: =IFERROR(__xludf.DUMMYFUNCTION("GOOGLEFINANCE(E49, ""price"")"),254.25) -> 254.25 | H49: =IFERROR(__xludf.DUMMYFUNCTION("GOOGLEFINANCE(E49, ""low"")"),247.6) -> 247.6 | I49: =IFERROR(__xludf.DUMMYFUNCTION("GOOGLEFINANCE(E49, ""high"")"),256.71) -> 256.71 | K49: -15 | L49: 39.43 | M49: 19.3 | N49: 7.31 | O49: S1 Up | P49: 107.37 | Q49: 46084.66 | R49: TRUE | S49: DDOG,Preço: 247.48,Dist MM20: 8.63%,Momentum: 23.64,RSI: 58.10,ADX: 13.62,ATR: 10.27,RVOL: 0.77,Estado: Aguardar Recuo,Entrada: 243.37,Stop: 233.10,Take-Profit: 255.69,Break-Even: 249.53,Qtd: 2.43,Trailing: 233.10,Data: 23/09/2026 06:44:50 | T49: 0 | U49: DDOG | V49: Preço: 268.56 | W49: Dist MM20: 3.95% | X49: Momentum: 11.02 | Y49: RSI: 61.88 | Z49: ADX: 18.76 | AA49: ATR: 12.71 | AB49: RVOL: 0.99 | AC49: Data: 31/07/2026 04:38:38 | AD49: 46030.371 | AE49: DDOG,Preço: 268.56,Dist MM20: 3.95%,Momentum: 11.02,RSI: 61.88,ADX: 18.76,ATR: 12.71,RVOL: 0.99,Estado: Aguardar Recuo,Entrada: 263.48,Stop: 250.77,Take-Profit: 288.90,Break-Even: 276.19,Qtd: 3.93,Data: 31/07/2026 04:38:38
E50: DECK | F50: Deckers Outdoor | G50: =IFERROR(__xludf.DUMMYFUNCTION("GOOGLEFINANCE(E50, ""price"")"),79.69) -> 79.69 | R50: TRUE | S50: DECK,Preço: 79.83,Dist MM20: -3.60%,Momentum: -4.75,RSI: 37.70,ADX: 42.98,ATR: 2.36,RVOL: 1.03,Estado: Observar,Entrada: N/A,Stop: N/A,Take-Profit: N/A,Break-Even: N/A,Qtd: N/A,Trailing: 75.11,Data: 23/09/2026 06:55:31 | T50: 0 | U50: DECK | V50: Preço: 99.69 | W50: Dist MM20: -3.79% | X50: Momentum: -6.30 | Y50: RSI: 43.86 | Z50: ADX: 14.33 | AA50: ATR: 3.79 | AB50: RVOL: 0.76 | AC50: Data: 31/07/2026 04:39:28 | AD50: 46030.371 | AE50: DECK,Preço: 99.69,Dist MM20: -3.79%,Momentum: -6.30,RSI: 43.86,ADX: 14.33,ATR: 3.79,RVOL: 0.76,Estado: Observar,Entrada: N/A,Stop: N/A,Take-Profit: N/A,Break-Even: N/A,Qtd: N/A,Data: 31/07/2026 04:39:28
E51: DELL | G51: =IFERROR(__xludf.DUMMYFUNCTION("GOOGLEFINANCE(E51, ""price"")"),552.03) -> 552.03 | H51: =IFERROR(__xludf.DUMMYFUNCTION("GOOGLEFINANCE(E51, ""low"")"),548.55) -> 548.55 | I51: =IFERROR(__xludf.DUMMYFUNCTION("GOOGLEFINANCE(E51, ""high"")"),570.72) -> 570.72 | P51: 120.96 | R51: TRUE | S51: DELL,Preço: 548.92,Dist MM20: 6.36%,Momentum: 123.92,RSI: 56.98,ADX: 21.98,ATR: 32.55,RVOL: 0.91,Estado: Observar,Entrada: N/A,Stop: N/A,Take-Profit: N/A,Break-Even: N/A,Qtd: N/A,Trailing: 483.82,Data: 23/09/2026 02:21:22 | T51: 0 | U51: DELL | V51: Preço: 404.81 | W51: Dist MM20: -2.73% | X51: Momentum: -30.16 | Y51: RSI: 49.65 | Z51: ADX: 18.83 | AA51: ATR: 30.49 | AB51: RVOL: 0.75 | AC51: Data: 31/07/2026 02:35:00 | AD51: 46030.371 | AE51: DELL,Preço: 404.81,Dist MM20: -2.73%,Momentum: -30.16,RSI: 49.65,ADX: 18.83,ATR: 30.49,RVOL: 0.75,Estado: Aguardar Recuo,Entrada: 392.61,Stop: 362.12,Take-Profit: 453.59,Break-Even: 423.10,Qtd: 1.64,Data: 31/07/2026 02:35:00
E52: DPZ | F52: Domino s Pizza | G52: =IFERROR(__xludf.DUMMYFUNCTION("GOOGLEFINANCE(E52, ""price"")"),291.9) -> 291.9 | R52: TRUE | S52: DPZ,Preço: 297.11,Dist MM20: -8.58%,Momentum: -43.26,RSI: 33.93,ADX: 26.46,ATR: 8.99,RVOL: 0.92,Estado: Observar,Entrada: N/A,Stop: N/A,Take-Profit: N/A,Break-Even: N/A,Qtd: N/A,Trailing: 279.13,Data: 23/09/2026 06:55:34 | T52: 0 | U52: DPZ | V52: Preço: 352.25 | W52: Dist MM20: 9.17% | X52: Momentum: 52.79 | Y52: RSI: 65.75 | Z52: ADX: 30.93 | AA52: ATR: 14.18 | AB52: RVOL: 0.78 | AC52: Data: 31/07/2026 03:55:07 | AD52: 46030.371 | AE52: DPZ,Preço: 352.25,Dist MM20: 9.17%,Momentum: 52.79,RSI: 65.75,ADX: 30.93,ATR: 14.18,RVOL: 0.78,Estado: Observar,Entrada: N/A,Stop: N/A,Take-Profit: N/A,Break-Even: N/A,Qtd: N/A,Data: 31/07/2026 03:55:07
E53: DTE | F53: DTE Energy | G53: =IFERROR(__xludf.DUMMYFUNCTION("GOOGLEFINANCE(E53, ""price"")"),123.05) -> 123.05 | R53: TRUE | S53: DTE,Preço: 125.41,Dist MM20: -6.05%,Momentum: -10.65,RSI: 20.19,ADX: 32.71,ATR: 2.10,RVOL: 1.67,Estado: Observar,Entrada: N/A,Stop: N/A,Take-Profit: N/A,Break-Even: N/A,Qtd: N/A,Trailing: 121.21,Data: 23/09/2026 06:55:33 | T53: 0 | U53: DTE | V53: Preço: 130.70 | W53: Dist MM20: -3.45% | X53: Momentum: -7.01 | Y53: RSI: 29.04 | Z53: ADX: 24.23 | AA53: ATR: 2.14 | AB53: RVOL: 1.73 | AC53: Trailing: 126.42 | AD53: 17/09/2026 07:54:56 | AE53: DTE,Preço: 130.70,Dist MM20: -3.45%,Momentum: -7.01,RSI: 29.04,ADX: 24.23,ATR: 2.14,RVOL: 1.73,Estado: Observar,Entrada: N/A,Stop: N/A,Take-Profit: N/A,Break-Even: N/A,Qtd: N/A,Trailing: 126.42,Data: 17/09/2026 07:54:34
E54: EBAY | F54: Ebay | G54: =IFERROR(__xludf.DUMMYFUNCTION("GOOGLEFINANCE(E54, ""price"")"),108.43) -> 108.43 | H54: =IFERROR(__xludf.DUMMYFUNCTION("GOOGLEFINANCE(E54, ""low"")"),106.44) -> 106.44 | I54: =IFERROR(__xludf.DUMMYFUNCTION("GOOGLEFINANCE(E54, ""high"")"),110.52) -> 110.52 | K54: 12.86 | L54: 75.08 | M54: 34.62 | N54: 2.43 | O54: R5 Down | P54: 91 | Q54: 45870.408 | R54: TRUE | S54: EBAY,Preço: 109.28,Dist MM20: 2.51%,Momentum: 4.30,RSI: 53.66,ADX: 11.18,ATR: 3.57,RVOL: 0.85,Estado: Aguardar Recuo,Entrada: 107.85,Stop: 104.28,Take-Profit: 112.13,Break-Even: 109.99,Qtd: 7.00,Trailing: 104.28,Data: 23/09/2026 02:21:42 | T54: 0 | U54: EBAY | V54: Preço: 113.52 | W54: Dist MM20: -0.10% | X54: Momentum: -3.68 | Y54: RSI: 52.29 | Z54: ADX: 13.10 | AA54: ATR: 3.05 | AB54: RVOL: 0.74 | AC54: Data: 31/07/2026 02:08:12 | AD54: 46030.371 | AE54: EBAY,Preço: 113.52,Dist MM20: -0.10%,Momentum: -3.68,RSI: 52.29,ADX: 13.10,ATR: 3.05,RVOL: 0.74,Estado: Observar,Entrada: N/A,Stop: N/A,Take-Profit: N/A,Break-Even: N/A,Qtd: N/A,Data: 31/07/2026 02:08:12
E55: ECL | F55: Ecolab | G55: =IFERROR(__xludf.DUMMYFUNCTION("GOOGLEFINANCE(E55, ""price"")"),275.8) -> 275.8 | R55: TRUE | S55: ECL,Preço: 276.22,Dist MM20: -0.71%,Momentum: -4.03,RSI: 49.13,ADX: 12.57,ATR: 4.96,RVOL: 0.94,Estado: Observar,Entrada: N/A,Stop: N/A,Take-Profit: N/A,Break-Even: N/A,Qtd: N/A,Trailing: 266.30,Data: 23/09/2026 06:55:42 | T55: 0 | U55: ECL | V55: Preço: 285.47 | W55: Dist MM20: 4.14% | X55: Momentum: 9.76 | Y55: RSI: 62.04 | Z55: ADX: 17.67 | AA55: ATR: 6.27 | AB55: RVOL: 0.77 | AC55: Trailing: 276.69 | AD55: 46181.267 | AE55: ECL,Preço: 285.47,Dist MM20: 4.14%,Momentum: 9.76,RSI: 62.04,ADX: 17.67,ATR: 6.27,RVOL: 0.77,Estado: Aguardar Recuo,Entrada: 282.96,Stop: 276.69,Take-Profit: 295.50,Break-Even: 289.23,Qtd: 7.97,Trailing: 276.69,Data: 06/08/2026 06:24:23
B56: Time Now | C56: =now() -> 46288.715 | E56: EL | F56: Essilor | G56: =IFERROR(__xludf.DUMMYFUNCTION("GOOGLEFINANCE(E56, ""price"")"),149.95) -> 149.95 | H56: =IFERROR(__xludf.DUMMYFUNCTION("GOOGLEFINANCE(E56, ""low"")"),144.55) -> 144.55 | I56: =IFERROR(__xludf.DUMMYFUNCTION("GOOGLEFINANCE(E56, ""high"")"),149.95) -> 149.95 | K56: 23.4 | L56: 82.38 | M56: 60.69 | N56: 5.4 | O56: R2 Down | P56: 292 | Q56: 45706.405 | R56: TRUE | S56: EL,Preço: 100.29,Dist MM20: 0.51%,Momentum: 0.29,RSI: 57.88,ADX: 24.95,ATR: 2.89,RVOL: 0.91,Estado: Alerta Iminente,Entrada: 99.71,Stop: 96.24,Take-Profit: 103.87,Break-Even: 101.79,Qtd: 7.21,Trailing: 96.24,Data: 23/09/2026 02:22:00 | T56: 0 | U56: EL | V56: Preço: 84.88 | W56: Dist MM20: 2.60% | X56: Momentum: 2.22 | Y56: RSI: 55.74 | Z56: ADX: 8.71 | AA56: ATR: 2.40 | AB56: RVOL: 0.96 | AC56: Data: 31/07/2026 02:08:45 | AD56: 46030.371 | AE56: EL,Preço: 84.88,Dist MM20: 2.60%,Momentum: 2.22,RSI: 55.74,ADX: 8.71,ATR: 2.40,RVOL: 0.96,Estado: Aguardar Recuo,Entrada: 83.92,Stop: 81.52,Take-Profit: 88.72,Break-Even: 86.32,Qtd: 20.83,Data: 31/07/2026 02:08:45
E57: EMR | F57: Emerson Electric | G57: =IFERROR(__xludf.DUMMYFUNCTION("GOOGLEFINANCE(E57, ""price"")"),155.25) -> 155.25 | R57: TRUE | S57: EMR,Preço: 154.19,Dist MM20: 1.92%,Momentum: 6.56,RSI: 54.70,ADX: 21.04,ATR: 3.15,RVOL: 0.82,Estado: Observar,Entrada: N/A,Stop: N/A,Take-Profit: N/A,Break-Even: N/A,Qtd: N/A,Trailing: 147.89,Data: 23/09/2026 06:50:42 | T57: 0 | U57: EMR | V57: Preço: 158.84 | W57: Dist MM20: 10.81% | X57: Momentum: 22.59 | Y57: RSI: 69.60 | Z57: ADX: 21.48 | AA57: ATR: 4.69 | AB57: RVOL: 1.86 | AC57: Trailing: 152.27 | AD57: 46150.455 | AE57: EMR,Preço: 158.84,Dist MM20: 10.81%,Momentum: 22.59,RSI: 69.60,ADX: 21.48,ATR: 4.69,RVOL: 1.86,Estado: Aguardar Recuo,Entrada: 156.96,Stop: 152.27,Take-Profit: 166.34,Break-Even: 161.65,Qtd: 10.66,Trailing: 152.27,Data: 05/08/2026 10:53:25
E58: ENVX | F58: Enovix | G58: =IFERROR(__xludf.DUMMYFUNCTION("GOOGLEFINANCE(E58, ""price"")"),2.98) -> 2.98 | H58: =IFERROR(__xludf.DUMMYFUNCTION("GOOGLEFINANCE(E58, ""low"")"),2.93) -> 2.93 | I58: =IFERROR(__xludf.DUMMYFUNCTION("GOOGLEFINANCE(E58, ""high"")"),3.05) -> 3.05 | O58: R2 Up | P58: 14.62 | Q58: 45852.922 | R58: TRUE | S58: ENVX,Preço: 3.06,Dist MM20: -4.88%,Momentum: -0.29,RSI: 38.20,ADX: 39.66,ATR: 0.15,RVOL: 0.92,Estado: Observar,Entrada: N/A,Stop: N/A,Take-Profit: N/A,Break-Even: N/A,Qtd: N/A,Trailing: 2.76,Data: 23/09/2026 06:55:43 | T58: 0 | U58: ENVX | V58: Preço: 4.18 | W58: Dist MM20: -11.68% | X58: Momentum: -1.02 | Y58: RSI: 38.66 | Z58: ADX: 34.51 | AA58: ATR: 0.33 | AB58: RVOL: 1.27 | AC58: Data: 31/07/2026 04:05:43 | AD58: 46030.371 | AE58: ENVX,Preço: 4.18,Dist MM20: -11.68%,Momentum: -1.02,RSI: 38.66,ADX: 34.51,ATR: 0.33,RVOL: 1.27,Estado: Forca Consolidada,Entrada: 4.11,Stop: 3.71,Take-Profit: 4.70,Break-Even: 4.41,Qtd: 126.26,Data: 31/07/2026 04:05:43
E59: EOG | F59: EOG Resources | G59: =IFERROR(__xludf.DUMMYFUNCTION("GOOGLEFINANCE(E59, ""price"")"),142.58) -> 142.58 | R59: TRUE | S59: EOG,Preço: 139.52,Dist MM20: -4.37%,Momentum: -8.83,RSI: 40.17,ADX: 11.61,ATR: 3.47,RVOL: 0.98,Estado: Observar,Entrada: N/A,Stop: N/A,Take-Profit: N/A,Break-Even: N/A,Qtd: N/A,Trailing: 132.58,Data: 23/09/2026 06:55:47 | T59: 0 | U59: EOG | V59: Preço: 144.93 | W59: Dist MM20: -1.82% | X59: Momentum: 0.09 | Y59: RSI: 48.07 | Z59: ADX: 10.57 | AA59: ATR: 3.55 | AB59: RVOL: 1.44 | AC59: Trailing: 137.83 | AD59: 17/09/2026 03:54:54 | AE59: EOG,Preço: 144.93,Dist MM20: -1.82%,Momentum: 0.09,RSI: 48.07,ADX: 10.57,ATR: 3.55,RVOL: 1.44,Estado: Observar,Entrada: N/A,Stop: N/A,Take-Profit: N/A,Break-Even: N/A,Qtd: N/A,Trailing: 137.83,Data: 17/09/2026 03:51:45
E60: FAST | F60: Fastenal | G60: =IFERROR(__xludf.DUMMYFUNCTION("GOOGLEFINANCE(E60, ""price"")"),50.76) -> 50.76 | R60: TRUE | S60: FAST,Preço: 50.08,Dist MM20: 1.22%,Momentum: 1.33,RSI: 55.11,ADX: 12.57,ATR: 1.01,RVOL: 1.07,Estado: Aguardar Recuo,Entrada: 49.68,Stop: 48.67,Take-Profit: 50.89,Break-Even: 50.28,Qtd: 24.75,Trailing: 48.67,Data: 23/09/2026 06:44:58 | T60: 0 | U60: FAST | V60: Preço: 46.66 | W60: Dist MM20: 0.11% | X60: Momentum: 0.17 | Y60: RSI: 50.92 | Z60: ADX: 15.73 | AA60: ATR: 1.46 | AB60: RVOL: 0.89 | AC60: Data: 31/07/2026 04:39:12 | AD60: 46030.371 | AE60: FAST,Preço: 46.66,Dist MM20: 0.11%,Momentum: 0.17,RSI: 50.92,ADX: 15.73,ATR: 1.46,RVOL: 0.89,Estado: Observar,Entrada: N/A,Stop: N/A,Take-Profit: N/A,Break-Even: N/A,Qtd: N/A,Data: 31/07/2026 04:39:12
B61: Time Now | C61: =now() -> 46288.715 | E61: FIG | F61: Figma | G61: =IFERROR(__xludf.DUMMYFUNCTION("GOOGLEFINANCE(E61, ""price"")"),21.94) -> 21.94 | H61: =IFERROR(__xludf.DUMMYFUNCTION("GOOGLEFINANCE(E61, ""low"")"),21.67) -> 21.67 | I61: =IFERROR(__xludf.DUMMYFUNCTION("GOOGLEFINANCE(E61, ""high"")"),22.48) -> 22.48 | K61: 8.57 | L61: 62.05 | M61: 30.49 | N61: 2.2 | O61: P Up | P61: 31.14 | Q61: 46079.314 | R61: TRUE | S61: FIG,Preço: 21.80,Dist MM20: -11.84%,Momentum: -5.39,RSI: 38.58,ADX: 14.12,ATR: 1.25,RVOL: 0.91,Estado: Observar,Entrada: N/A,Stop: N/A,Take-Profit: N/A,Break-Even: N/A,Qtd: N/A,Trailing: 19.30,Data: 23/09/2026 06:55:50 | T61: 0 | U61: FIG | V61: Preço: 23.76 | W61: Dist MM20: 5.04% | X61: Momentum: 2.64 | Y61: RSI: 56.54 | Z61: ADX: 15.82 | AA61: ATR: 1.72 | AB61: RVOL: 1.06 | AC61: Data: 31/07/2026 04:38:03 | AD61: 46030.371 | AE61: FIG,Preço: 23.76,Dist MM20: 5.04%,Momentum: 2.64,RSI: 56.54,ADX: 15.82,ATR: 1.72,RVOL: 1.06,Estado: Observar,Entrada: N/A,Stop: N/A,Take-Profit: N/A,Break-Even: N/A,Qtd: N/A,Data: 31/07/2026 04:38:03
E62: FITB | F62: Fifth Third Bancorp | G62: =IFERROR(__xludf.DUMMYFUNCTION("GOOGLEFINANCE(E62, ""price"")"),"#N/A") -> #N/A | H62: =IFERROR(__xludf.DUMMYFUNCTION("GOOGLEFINANCE(E62, ""low"")"),"#N/A") -> #N/A | I62: =IFERROR(__xludf.DUMMYFUNCTION("GOOGLEFINANCE(E62, ""high"")"),"#N/A") -> #N/A | K62: 0.69 | L62: 54.18 | M62: 22.72 | N62: 0.97 | O62: P Up | P62: 43.14 | Q62: 45972.325 | R62: TRUE | S62: FITB,Preço: 52.76,Dist MM20: -2.47%,Momentum: -0.25,RSI: 38.29,ADX: 21.84,ATR: 1.09,RVOL: 1.54,Estado: Observar,Entrada: N/A,Stop: N/A,Take-Profit: N/A,Break-Even: N/A,Qtd: N/A,Trailing: 50.58,Data: 23/09/2026 06:55:51 | T62: 0 | U62: FITB | V62: Preço: 56.59 | W62: Dist MM20: -1.34% | X62: Momentum: -0.48 | Y62: RSI: 50.98 | Z62: ADX: 19.13 | AA62: ATR: 1.32 | AB62: RVOL: 1.19 | AC62: Data: 31/07/2026 04:36:56 | AD62: 46030.371 | AE62: FITB,Preço: 56.59,Dist MM20: -1.34%,Momentum: -0.48,RSI: 50.98,ADX: 19.13,ATR: 1.32,RVOL: 1.19,Estado: Aguardar Recuo,Entrada: 56.06,Stop: 54.74,Take-Profit: 58.70,Break-Even: 57.38,Qtd: 37.88,Data: 31/07/2026 04:36:56
E63: FLEX | F63: Flex Ltd | G63: =IFERROR(__xludf.DUMMYFUNCTION("GOOGLEFINANCE(E63, ""price"")"),114.86) -> 114.86 | R63: TRUE | S63: FLEX,Preço: 114.45,Dist MM20: 3.81%,Momentum: 7.59,RSI: 52.18,ADX: 14.02,ATR: 4.61,RVOL: 0.84,Estado: Aguardar Recuo,Entrada: 112.61,Stop: 108.00,Take-Profit: 118.14,Break-Even: 115.38,Qtd: 5.42,Trailing: 108.00,Data: 23/09/2026 06:45:04 | T63: 0 | U63: FLEX | V63: Preço: 108.00 | W63: Dist MM20: -2.44% | X63: Momentum: -1.25 | Y63: RSI: 43.88 | Z63: ADX: 16.31 | AA63: ATR: 4.36 | AB63: RVOL: 0.69 | AC63: Trailing: 99.28 | AD63: 16/09/2026 03:09:53 | AE63: FLEX,Preço: 108.00,Dist MM20: -2.44%,Momentum: -1.25,RSI: 43.88,ADX: 16.31,ATR: 4.36,RVOL: 0.69,Estado: Observar,Entrada: N/A,Stop: N/A,Take-Profit: N/A,Break-Even: N/A,Qtd: N/A,Trailing: 99.28,Data: 16/09/2026 03:08:54
E64: FLR | F64: Fluor Company | G64: =IFERROR(__xludf.DUMMYFUNCTION("GOOGLEFINANCE(E64, ""price"")"),53.64) -> 53.64 | R64: TRUE | S64: FLR,Preço: 54.03,Dist MM20: -0.87%,Momentum: -2.22,RSI: 50.40,ADX: 14.64,ATR: 1.81,RVOL: 0.75,Estado: Observar,Entrada: N/A,Stop: N/A,Take-Profit: N/A,Break-Even: N/A,Qtd: N/A,Trailing: 50.41,Data: 23/09/2026 06:55:53 | T64: 0 | U64: FLR | V64: Preço: 53.51 | W64: Dist MM20: -1.13% | X64: Momentum: 2.23 | Y64: RSI: 49.33 | Z64: ADX: 19.90 | AA64: ATR: 1.90 | AB64: RVOL: 0.87 | AC64: Trailing: 49.71 | AD64: 15/09/2026 10:39:54 | AE64: FLR,Preço: 53.51,Dist MM20: -1.13%,Momentum: 2.23,RSI: 49.33,ADX: 19.90,ATR: 1.90,RVOL: 0.87,Estado: Observar,Entrada: N/A,Stop: N/A,Take-Profit: N/A,Break-Even: N/A,Qtd: N/A,Trailing: 49.71,Data: 15/09/2026 10:36:05
E65: GD | F65: General Dynamics | G65: =IFERROR(__xludf.DUMMYFUNCTION("GOOGLEFINANCE(E65, ""price"")"),344.86) -> 344.86 | R65: TRUE | S65: GD,Preço: 343.39,Dist MM20: -5.26%,Momentum: -26.02,RSI: 26.27,ADX: 44.23,ATR: 6.79,RVOL: 1.10,Estado: Observar,Entrada: N/A,Stop: N/A,Take-Profit: N/A,Break-Even: N/A,Qtd: N/A,Trailing: 329.81,Data: 23/09/2026 06:55:51 | T65: 0 | U65: GD | V65: Preço: 385.76 | W65: Dist MM20: 2.24% | X65: Momentum: 20.13 | Y65: RSI: 62.20 | Z65: ADX: 21.28 | AA65: ATR: 8.62 | AB65: RVOL: 0.69 | AC65: Trailing: 373.69 | AD65: 46150.444 | AE65: GD,Preço: 385.76,Dist MM20: 2.24%,Momentum: 20.13,RSI: 62.20,ADX: 21.28,ATR: 8.62,RVOL: 0.69,Estado: Aguardar Recuo,Entrada: 382.31,Stop: 373.69,Take-Profit: 399.55,Break-Even: 390.93,Qtd: 5.80,Trailing: 373.69,Data: 05/08/2026 10:31:42
E66: GOOGL | F66: Alphabet US Class A | G66: =IFERROR(__xludf.DUMMYFUNCTION("GOOGLEFINANCE(E66, ""price"")"),340.63) -> 340.63 | H66: =IFERROR(__xludf.DUMMYFUNCTION("GOOGLEFINANCE(E66, ""low"")"),340.14) -> 340.14 | I66: =IFERROR(__xludf.DUMMYFUNCTION("GOOGLEFINANCE(E66, ""high"")"),350.0) -> 350 | O66: S2 Up | P66: 213.56 | Q66: 45898.833 | R66: TRUE | S66: GOOGL,Preço: 351.16,Dist MM20: 2.54%,Momentum: 16.14,RSI: 55.26,ADX: 13.88,ATR: 7.29,RVOL: 1.13,Estado: Observar,Entrada: N/A,Stop: N/A,Take-Profit: N/A,Break-Even: N/A,Qtd: N/A,Trailing: 336.58,Data: 23/09/2026 02:34:24 | T66: 0 | U66: GOOGL | V66: Preço: 333.66 | W66: Dist MM20: -4.19% | X66: Momentum: -23.52 | Y66: RSI: 42.10 | Z66: ADX: 14.32 | AA66: ATR: 9.58 | AB66: RVOL: 1.03 | AC66: Data: 31/07/2026 02:05:25 | AD66: 46030.371 | AE66: GOOGL,Preço: 333.66,Dist MM20: -4.19%,Momentum: -23.52,RSI: 42.10,ADX: 14.32,ATR: 9.58,RVOL: 1.03,Estado: Observar,Entrada: N/A,Stop: N/A,Take-Profit: N/A,Break-Even: N/A,Qtd: N/A,Data: 31/07/2026 02:05:25
E67: GRMN | F67: Garmin | G67: =IFERROR(__xludf.DUMMYFUNCTION("GOOGLEFINANCE(E67, ""price"")"),285.19) -> 285.19 | H67: =IFERROR(__xludf.DUMMYFUNCTION("GOOGLEFINANCE(E67, ""low"")"),283.09) -> 283.09 | I67: =IFERROR(__xludf.DUMMYFUNCTION("GOOGLEFINANCE(E67, ""high"")"),286.25) -> 286.25 | K67: 18.32 | L67: 70.4 | M67: 21.06 | N67: 6.57 | O67: R2 Down | P67: 238.54 | Q67: 45708.61 | R67: TRUE | S67: GRMN,Preço: 284.67,Dist MM20: 1.75%,Momentum: 9.50,RSI: 54.53,ADX: 17.08,ATR: 6.47,RVOL: 1.37,Estado: Aguardar Recuo,Entrada: 282.08,Stop: 275.61,Take-Profit: 289.84,Break-Even: 285.96,Qtd: 3.86,Trailing: 275.61,Data: 23/09/2026 02:34:42 | T67: 0 | U67: GRMN | V67: Preço: 297.55 | W67: Dist MM20: 19.36% | X67: Momentum: 54.44 | Y67: RSI: 80.66 | Z67: ADX: 21.28 | AA67: ATR: 9.52 | AB67: RVOL: 1.07 | AC67: Data: 31/07/2026 02:09:02 | AD67: 46030.371 | AE67: GRMN,Preço: 297.55,Dist MM20: 19.36%,Momentum: 54.44,RSI: 80.66,ADX: 21.28,ATR: 9.52,RVOL: 1.07,Estado: Aguardar Recuo,Entrada: 293.74,Stop: 284.22,Take-Profit: 312.78,Break-Even: 303.26,Qtd: 5.25,Data: 31/07/2026 02:09:02
E68: HOOD | F68: Robinhood Markets | G68: =IFERROR(__xludf.DUMMYFUNCTION("GOOGLEFINANCE(E68, ""price"")"),125.32) -> 125.32 | H68: =IFERROR(__xludf.DUMMYFUNCTION("GOOGLEFINANCE(E68, ""low"")"),122.55) -> 122.55 | I68: =IFERROR(__xludf.DUMMYFUNCTION("GOOGLEFINANCE(E68, ""high"")"),126.74) -> 126.74 | K68: 24.88 | L68: 80.67 | M68: 45.07 | N68: 4.98 | O68: P Up | P68: 99.83 | Q68: 45840.761 | R68: TRUE | S68: HOOD,Preço: 124.25,Dist MM20: 9.87%,Momentum: 20.74,RSI: 62.94,ADX: 19.11,ATR: 6.42,RVOL: 0.69,Estado: Aguardar Recuo,Entrada: 121.68,Stop: 115.26,Take-Profit: 129.38,Break-Even: 125.53,Qtd: 3.89,Trailing: 115.26,Data: 23/09/2026 06:45:18 | T68: 0 | U68: HOOD | V68: Preço: 86.60 | W68: Dist MM20: -17.53% | X68: Momentum: -25.37 | Y68: RSI: 36.00 | Z68: ADX: 22.65 | AA68: ATR: 5.52 | AB68: RVOL: 1.31 | AC68: Data: 31/07/2026 04:21:56 | AD68: 46030.371 | AE68: HOOD,Preço: 86.60,Dist MM20: -17.53%,Momentum: -25.37,RSI: 36.00,ADX: 22.65,ATR: 5.52,RVOL: 1.31,Estado: Observar,Entrada: N/A,Stop: N/A,Take-Profit: N/A,Break-Even: N/A,Qtd: N/A,Data: 31/07/2026 04:21:56
E69: HPE | F69: HP | R69: TRUE | S69: HPE,Preço: 61.03,Dist MM20: 8.83%,Momentum: 10.16,RSI: 59.13,ADX: 15.01,ATR: 3.65,RVOL: 0.61,Estado: Observar,Entrada: N/A,Stop: N/A,Take-Profit: N/A,Break-Even: N/A,Qtd: N/A,Trailing: 53.73,Data: 23/09/2026 06:45:17 | T69: 0 | U69: HPE | V69: Preço: 51.83 | W69: Dist MM20: -4.69% | X69: Momentum: -7.99 | Y69: RSI: 48.46 | Z69: ADX: 13.58 | AA69: ATR: 2.32 | AB69: RVOL: 3.38 | AC69: Trailing: 48.58 | AD69: 46090.476 | AE69: HPE,Preço: 51.83,Dist MM20: -4.69%,Momentum: -7.99,RSI: 48.46,ADX: 13.58,ATR: 2.32,RVOL: 3.38,Estado: Aguardar Recuo,Entrada: 50.90,Stop: 48.58,Take-Profit: 55.54,Break-Even: 53.22,Qtd: 21.55,Trailing: 48.58,Data: 03/09/2026 11:10:10
E70: HUM | F70: Humana | G70: =IFERROR(__xludf.DUMMYFUNCTION("GOOGLEFINANCE(E70, ""price"")"),375.17) -> 375.17 | H70: =IFERROR(__xludf.DUMMYFUNCTION("GOOGLEFINANCE(E70, ""low"")"),369.13) -> 369.13 | I70: =IFERROR(__xludf.DUMMYFUNCTION("GOOGLEFINANCE(E70, ""high"")"),377.68) -> 377.68 | K70: 0.47 | L70: 28.9 | M70: 47.68 | N70: 7.69 | O70: S1 Up | P70: 175.87 | Q70: 46079.32 | R70: TRUE | S70: HUM,Preço: 372.00,Dist MM20: -5.46%,Momentum: -22.88,RSI: 37.91,ADX: 20.24,ATR: 12.93,RVOL: 0.92,Estado: Observar,Entrada: N/A,Stop: N/A,Take-Profit: N/A,Break-Even: N/A,Qtd: N/A,Trailing: 346.14,Data: 23/09/2026 02:35:00 | T70: 0 | U70: HUM | V70: Preço: 366.66 | W70: Dist MM20: -6.74% | X70: Momentum: -25.56 | Y70: RSI: 42.16 | Z70: ADX: 45.61 | AA70: ATR: 17.22 | AB70: RVOL: 1.11 | AC70: Data: 31/07/2026 02:36:41 | AD70: 46030.371 | AE70: HUM,Preço: 366.66,Dist MM20: -6.74%,Momentum: -25.56,RSI: 42.16,ADX: 45.61,ATR: 17.22,RVOL: 1.11,Estado: Forca Consolidada,Entrada: 363.22,Stop: 342.56,Take-Profit: 394.22,Break-Even: 378.72,Qtd: 2.42,Data: 31/07/2026 02:36:41
E71: IBM | F71: IBM | G71: =IFERROR(__xludf.DUMMYFUNCTION("GOOGLEFINANCE(E71, ""price"")"),236.23) -> 236.23 | H71: =IFERROR(__xludf.DUMMYFUNCTION("GOOGLEFINANCE(E71, ""low"")"),233.1) -> 233.1 | I71: =IFERROR(__xludf.DUMMYFUNCTION("GOOGLEFINANCE(E71, ""high"")"),237.86) -> 237.86 | R71: TRUE | S71: IBM,Preço: 231.38,Dist MM20: -1.96%,Momentum: -0.02,RSI: 45.65,ADX: 11.91,ATR: 6.79,RVOL: 0.86,Estado: Observar,Entrada: N/A,Stop: N/A,Take-Profit: N/A,Break-Even: N/A,Qtd: N/A,Trailing: 217.80,Data: 23/09/2026 02:35:18 | T71: 0 | U71: IBM | V71: Preço: 221.74 | W71: Dist MM20: -8.98% | X71: Momentum: -65.82 | Y71: RSI: 40.21 | Z71: ADX: 29.45 | AA71: ATR: 9.20 | AB71: RVOL: 0.41 | AC71: Data: 31/07/2026 02:37:53 | AD71: 46030.371 | AE71: IBM,Preço: 221.74,Dist MM20: -8.98%,Momentum: -65.82,RSI: 40.21,ADX: 29.45,ATR: 9.20,RVOL: 0.41,Estado: Observar,Entrada: N/A,Stop: N/A,Take-Profit: N/A,Break-Even: N/A,Qtd: N/A,Data: 31/07/2026 02:37:53
E72: IDR | F72: Indra Sistemas | G72: =IFERROR(__xludf.DUMMYFUNCTION("GOOGLEFINANCE(E72, ""price"")"),62.24) -> 62.24 | H72: =IFERROR(__xludf.DUMMYFUNCTION("GOOGLEFINANCE(E72, ""low"")"),61.32) -> 61.32 | I72: =IFERROR(__xludf.DUMMYFUNCTION("GOOGLEFINANCE(E72, ""high"")"),62.72) -> 62.72 | K72: -0.16 | L72: 60.8 | M72: 29.38 | N72: 1.12 | O72: P Down | P72: 36.12 | Q72: 45827.353 | R72: TRUE | S72: IDR,Preço: 31.04,Dist MM20: 0.45%,Momentum: 0.04,RSI: 51.56,ADX: 11.60,ATR: 1.28,RVOL: 0.81,Estado: Aguardar Recuo,Entrada: 30.53,Stop: 29.25,Take-Profit: 32.07,Break-Even: 31.30,Qtd: 19.53,Trailing: 29.25,Data: 23/09/2026 06:50:40 | T72: 0 | U72: IDR | V72: Preço: 29.20 | W72: Dist MM20: -1.94% | X72: Momentum: -1.56 | Y72: RSI: 43.96 | Z72: ADX: 14.04 | AA72: ATR: 1.56 | AB72: RVOL: 1.47 | AC72: Data: 31/07/2026 04:07:25 | AD72: 46030.371 | AE72: IDR,Preço: 29.20,Dist MM20: -1.94%,Momentum: -1.56,RSI: 43.96,ADX: 14.04,ATR: 1.56,RVOL: 1.47,Estado: Aguardar Recuo,Entrada: 28.58,Stop: 27.02,Take-Profit: 31.70,Break-Even: 30.14,Qtd: 32.05,Data: 31/07/2026 04:07:25
E73: INTC | F73: Intel US | G73: =IFERROR(__xludf.DUMMYFUNCTION("GOOGLEFINANCE(E73, ""price"")"),120.36) -> 120.36 | H73: =IFERROR(__xludf.DUMMYFUNCTION("GOOGLEFINANCE(E73, ""low"")"),119.44) -> 119.44 | I73: =IFERROR(__xludf.DUMMYFUNCTION("GOOGLEFINANCE(E73, ""high"")"),124.25) -> 124.25 | P73: 20.29 | Q73: 45812.25 | R73: TRUE | S73: INTC,Preço: 123.86,Dist MM20: 24.75%,Momentum: 34.89,RSI: 72.06,ADX: 19.59,ATR: 4.79,RVOL: 1.04,Estado: Aguardar Recuo,Entrada: 121.94,Stop: 117.15,Take-Profit: 127.69,Break-Even: 124.81,Qtd: 5.22,Trailing: 117.15,Data: 23/09/2026 02:35:37 | T73: 0 | U73: INTC | V73: Preço: 91.13 | W73: Dist MM20: -10.66% | X73: Momentum: -18.71 | Y73: RSI: 40.51 | Z73: ADX: 24.18 | AA73: ATR: 6.64 | AB73: RVOL: 1.14 | AC73: Data: 31/07/2026 02:09:19 | AD73: 46030.371 | AE73: INTC,Preço: 91.13,Dist MM20: -10.66%,Momentum: -18.71,RSI: 40.51,ADX: 24.18,ATR: 6.64,RVOL: 1.14,Estado: Aguardar Recuo,Entrada: 88.47,Stop: 81.83,Take-Profit: 101.75,Break-Even: 95.11,Qtd: 7.53,Data: 31/07/2026 02:09:19
B74: Time Now | C74: =now() -> 46288.715 | E74: IONQ | F74: IonQ | G74: =IFERROR(__xludf.DUMMYFUNCTION("GOOGLEFINANCE(E74, ""price"")"),42.86) -> 42.86 | H74: =IFERROR(__xludf.DUMMYFUNCTION("GOOGLEFINANCE(E74, ""low"")"),41.63) -> 41.63 | I74: =IFERROR(__xludf.DUMMYFUNCTION("GOOGLEFINANCE(E74, ""high"")"),46.05) -> 46.05 | K74: -2.1 | L74: 50.61 | M74: 29.81 | N74: 3.37 | O74: P Up | P74: 41.06 | Q74: 45868.359 | R74: TRUE | S74: IONQ,Preço: 40.74,Dist MM20: 4.29%,Momentum: 2.96,RSI: 52.78,ADX: 11.26,ATR: 2.09,RVOL: 0.81,Estado: Aguardar Recuo,Entrada: 39.90,Stop: 37.81,Take-Profit: 42.41,Break-Even: 41.16,Qtd: 11.96,Trailing: 37.81,Data: 23/09/2026 06:45:21 | T74: 0 | U74: IONQ | V74: Preço: 35.77 | W74: Dist MM20: -7.15% | X74: Momentum: -7.09 | Y74: RSI: 39.63 | Z74: ADX: 40.29 | AA74: ATR: 2.38 | AB74: RVOL: 0.95 | AC74: Data: 31/07/2026 04:08:22 | AD74: 46030.371 | AE74: IONQ,Preço: 35.77,Dist MM20: -7.15%,Momentum: -7.09,RSI: 39.63,ADX: 40.29,ATR: 2.38,RVOL: 0.95,Estado: Forca Consolidada,Entrada: 35.29,Stop: 32.43,Take-Profit: 39.57,Break-Even: 37.43,Qtd: 17.51,Data: 31/07/2026 04:08:22
E75: J | F75: Jacobs Solutions | G75: =IFERROR(__xludf.DUMMYFUNCTION("GOOGLEFINANCE(E75, ""price"")"),141.74) -> 141.74 | R75: TRUE | S75: J,Preço: 143.12,Dist MM20: -1.86%,Momentum: -3.21,RSI: 47.44,ADX: 24.62,ATR: 2.91,RVOL: 0.86,Estado: Observar,Entrada: N/A,Stop: N/A,Take-Profit: N/A,Break-Even: N/A,Qtd: N/A,Trailing: 137.30,Data: 23/09/2026 06:59:28 | T75: 0 | U75: J | V75: Preço: 144.07 | W75: Dist MM20: -1.90% | X75: Momentum: -7.54 | Y75: RSI: 49.78 | Z75: ADX: 31.65 | AA75: ATR: 2.99 | AB75: RVOL: 0.85 | AC75: Trailing: 138.09 | AD75: 15/09/2026 10:39:54 | AE75: J,Preço: 144.07,Dist MM20: -1.90%,Momentum: -7.54,RSI: 49.78,ADX: 31.65,ATR: 2.99,RVOL: 0.85,Estado: Observar,Entrada: N/A,Stop: N/A,Take-Profit: N/A,Break-Even: N/A,Qtd: N/A,Trailing: 138.09,Data: 15/09/2026 10:35:08
E76: KMB | F76: Kimberly-Clark | G76: =IFERROR(__xludf.DUMMYFUNCTION("GOOGLEFINANCE(E76, ""price"")"),97.88) -> 97.88 | R76: TRUE | S76: KMB,Preço: 98.91,Dist MM20: -4.20%,Momentum: -8.17,RSI: 34.93,ADX: 25.89,ATR: 1.92,RVOL: 0.86,Estado: Observar,Entrada: N/A,Stop: N/A,Take-Profit: N/A,Break-Even: N/A,Qtd: N/A,Trailing: 95.07,Data: 23/09/2026 06:59:28 | T76: 0 | U76: KMB | V76: Preço: 111.57 | W76: Dist MM20: 1.75% | X76: Momentum: 5.04 | Y76: RSI: 56.07 | Z76: ADX: 22.23 | AA76: ATR: 2.83 | AB76: RVOL: 2.18 | AC76: Trailing: 107.61 | AD76: 46150.444 | AE76: KMB,Preço: 111.57,Dist MM20: 1.75%,Momentum: 5.04,RSI: 56.07,ADX: 22.23,ATR: 2.83,RVOL: 2.18,Estado: Aguardar Recuo,Entrada: 110.44,Stop: 107.61,Take-Profit: 116.10,Break-Even: 113.27,Qtd: 17.67,Trailing: 107.61,Data: 05/08/2026 10:32:13
E77: KO | F77: Coca Cola | G77: =IFERROR(__xludf.DUMMYFUNCTION("GOOGLEFINANCE(E77, ""price"")"),88.15) -> 88.15 | R77: TRUE | S77: KO,Preço: 88.61,Dist MM20: -0.00%,Momentum: 0.61,RSI: 52.62,ADX: 14.24,ATR: 1.11,RVOL: 1.08,Estado: Aguardar Recuo,Entrada: 88.17,Stop: 87.06,Take-Profit: 89.50,Break-Even: 88.84,Qtd: 22.52,Trailing: 87.06,Data: 23/09/2026 06:59:29 | T77: 0 | U77: KO | V77: Preço: 88.49 | W77: Dist MM20: 5.56% | X77: Momentum: 5.00 | Y77: RSI: 65.94 | Z77: ADX: 18.34 | AA77: ATR: 1.77 | AB77: RVOL: 0.76 | AC77: Data: 31/07/2026 04:52:29 | AD77: 46030.371 | AE77: KO,Preço: 88.49,Dist MM20: 5.56%,Momentum: 5.00,RSI: 65.94,ADX: 18.34,ATR: 1.77,RVOL: 0.76,Estado: Observar,Entrada: N/A,Stop: N/A,Take-Profit: N/A,Break-Even: N/A,Qtd: N/A,Data: 31/07/2026 04:52:29
E78: LAES | F78: SEALSQ | G78: =IFERROR(__xludf.DUMMYFUNCTION("GOOGLEFINANCE(E78, ""price"")"),2.32) -> 2.32 | H78: =IFERROR(__xludf.DUMMYFUNCTION("GOOGLEFINANCE(E78, ""low"")"),2.29) -> 2.29 | I78: =IFERROR(__xludf.DUMMYFUNCTION("GOOGLEFINANCE(E78, ""high"")"),2.48) -> 2.48 | K78: -2.48 | L78: 46.72 | M78: 15.69 | N78: 2.76 | O78: R3 Up | P78: 3.72 | Q78: 45799.882 | R78: TRUE | S78: LAES,Preço: 2.35,Dist MM20: -1.76%,Momentum: -0.04,RSI: 45.63,ADX: 15.47,ATR: 0.09,RVOL: 0.64,Estado: Observar,Entrada: N/A,Stop: N/A,Take-Profit: N/A,Break-Even: N/A,Qtd: N/A,Trailing: 2.17,Data: 23/09/2026 06:45:25 | T78: 0 | U78: LAES | V78: Preço: 2.36 | W78: Dist MM20: -10.25% | X78: Momentum: -0.44 | Y78: RSI: 35.86 | Z78: ADX: 23.69 | AA78: ATR: 0.14 | AB78: RVOL: 1.00 | AC78: Data: 31/07/2026 04:23:06 | AD78: 46030.371 | AE78: LAES,Preço: 2.36,Dist MM20: -10.25%,Momentum: -0.44,RSI: 35.86,ADX: 23.69,ATR: 0.14,RVOL: 1.00,Estado: Aguardar Recuo,Entrada: 2.30,Stop: 2.16,Take-Profit: 2.58,Break-Even: 2.44,Qtd: 357.14,Data: 31/07/2026 04:23:06
E79: LLY | F79: Eli Lilly and Co US | G79: =IFERROR(__xludf.DUMMYFUNCTION("GOOGLEFINANCE(E79, ""price"")"),1154.84) -> 1154.84 | H79: =IFERROR(__xludf.DUMMYFUNCTION("GOOGLEFINANCE(E79, ""low"")"),1154.0) -> 1154 | I79: =IFERROR(__xludf.DUMMYFUNCTION("GOOGLEFINANCE(E79, ""high"")"),1188.88) -> 1188.88 | K79: 7.71 | L79: 64.6 | M79: 25.22 | N79: 20.69 | O79: R1 up | P79: 873.12 | Q79: 45709.538 | R79: TRUE | S79: LLY,Preço: 1170.14,Dist MM20: 1.32%,Momentum: 10.14,RSI: 52.49,ADX: 11.50,ATR: 24.59,RVOL: 1.01,Estado: Aguardar Recuo,Entrada: 1160.30,Stop: 1135.71,Take-Profit: 1189.81,Break-Even: 1175.05,Qtd: 1.02,Trailing: 1135.71,Data: 23/09/2026 02:35:55 | T79: 0 | U79: LLY | V79: Preço: 1154.97 | W79: Dist MM20: -2.78% | X79: Momentum: -33.61 | Y79: RSI: 46.87 | Z79: ADX: 19.05 | AA79: ATR: 31.63 | AB79: RVOL: 1.27 | AC79: Data: 31/07/2026 02:08:29 | AD79: 46030.371 | AE79: LLY,Preço: 1154.97,Dist MM20: -2.78%,Momentum: -33.61,RSI: 46.87,ADX: 19.05,ATR: 31.63,RVOL: 1.27,Estado: Observar,Entrada: N/A,Stop: N/A,Take-Profit: N/A,Break-Even: N/A,Qtd: N/A,Data: 31/07/2026 02:08:29
E80: LMT | F80: Lockheed Martin | G80: =IFERROR(__xludf.DUMMYFUNCTION("GOOGLEFINANCE(E80, ""price"")"),526.54) -> 526.54 | H80: =IFERROR(__xludf.DUMMYFUNCTION("GOOGLEFINANCE(E80, ""low"")"),523.57) -> 523.57 | I80: =IFERROR(__xludf.DUMMYFUNCTION("GOOGLEFINANCE(E80, ""high"")"),534.93) -> 534.93 | K80: -47 | L80: 27.16 | M80: 14.96 | N80: 11.23 | O80: S2 Up | P80: 415.91 | Q80: 45861.482 | R80: TRUE | S80: LMT,Preço: 522.34,Dist MM20: -3.20%,Momentum: -22.16,RSI: 37.85,ADX: 26.31,ATR: 12.58,RVOL: 1.22,Estado: Observar,Entrada: N/A,Stop: N/A,Take-Profit: N/A,Break-Even: N/A,Qtd: N/A,Trailing: 497.18,Data: 23/09/2026 02:36:13 | T80: 0 | U80: LMT | V80: Preço: 574.11 | W80: Dist MM20: 6.83% | X80: Momentum: 50.89 | Y80: RSI: 65.23 | Z80: ADX: 20.71 | AA80: ATR: 14.99 | AB80: RVOL: 1.07 | AC80: Data: 31/07/2026 02:09:35 | AD80: 46030.371 | AE80: LMT,Preço: 574.11,Dist MM20: 6.83%,Momentum: 50.89,RSI: 65.23,ADX: 20.71,ATR: 14.99,RVOL: 1.07,Estado: Aguardar Recuo,Entrada: 568.11,Stop: 553.12,Take-Profit: 598.09,Break-Even: 583.10,Qtd: 3.34,Data: 31/07/2026 02:09:35
E81: LNG | F81: Cheniere Energy | G81: =IFERROR(__xludf.DUMMYFUNCTION("GOOGLEFINANCE(E81, ""price"")"),278.52) -> 278.52 | R81: TRUE | S81: LNG,Preço: 272.96,Dist MM20: -2.48%,Momentum: -21.17,RSI: 48.13,ADX: 15.23,ATR: 7.27,RVOL: 1.09,Estado: Observar,Entrada: N/A,Stop: N/A,Take-Profit: N/A,Break-Even: N/A,Qtd: N/A,Trailing: 258.42,Data: 23/09/2026 06:59:33 | T81: 0 | U81: LNG | V81: Preço: 267.75 | W81: Dist MM20: -4.77% | X81: Momentum: -16.33 | Y81: RSI: 41.96 | Z81: ADX: 17.37 | AA81: ATR: 7.14 | AB81: RVOL: 0.84 | AC81: Trailing: 253.47 | AD81: 17/09/2026 03:54:54 | AE81: LNG,Preço: 267.75,Dist MM20: -4.77%,Momentum: -16.33,RSI: 41.96,ADX: 17.37,ATR: 7.14,RVOL: 0.84,Estado: Observar,Entrada: N/A,Stop: N/A,Take-Profit: N/A,Break-Even: N/A,Qtd: N/A,Trailing: 253.47,Data: 17/09/2026 03:51:58
E82: LOW | F82: Lowe's | G82: =IFERROR(__xludf.DUMMYFUNCTION("GOOGLEFINANCE(E82, ""price"")"),192.49) -> 192.49 | R82: TRUE | S82: LOW,Preço: 196.08,Dist MM20: -2.06%,Momentum: -3.97,RSI: 40.12,ADX: 19.55,ATR: 3.92,RVOL: 1.06,Estado: Observar,Entrada: N/A,Stop: N/A,Take-Profit: N/A,Break-Even: N/A,Qtd: N/A,Trailing: 188.24,Data: 23/09/2026 06:59:33 | T82: 0 | U82: LOW | V82: Preço: 218.08 | W82: Dist MM20: 3.77% | X82: Momentum: 8.42 | Y82: RSI: 55.27 | Z82: ADX: 13.59 | AA82: ATR: 5.77 | AB82: RVOL: 0.88 | AC82: Trailing: 210.00 | AD82: 46150.444 | AE82: LOW,Preço: 218.08,Dist MM20: 3.77%,Momentum: 8.42,RSI: 55.27,ADX: 13.59,ATR: 5.77,RVOL: 0.88,Estado: Aguardar Recuo,Entrada: 215.77,Stop: 210.00,Take-Profit: 227.31,Break-Even: 221.54,Qtd: 8.67,Trailing: 210.00,Data: 05/08/2026 10:35:09
E83: LTC | F83: LTC Properties | G83: =IFERROR(__xludf.DUMMYFUNCTION("GOOGLEFINANCE(E83, ""price"")"),42.53) -> 42.53 | J83: ACTIVA | R83: TRUE | S83: LTC,Preço: 42.42,Dist MM20: 1.14%,Momentum: 1.02,RSI: 55.51,ADX: 27.82,ATR: 0.94,RVOL: 1.07,Estado: Alerta Iminente,Entrada: 42.23,Stop: 41.10,Take-Profit: 43.58,Break-Even: 42.91,Qtd: 22.16,Trailing: 41.50,Data: 23/09/2026 06:41:48 | T83: 0 | U83: LTC | V83: Preço: 38.48 | W83: Dist MM20: -5.53% | X83: Momentum: -1.58 | Y83: RSI: 37.56 | Z83: ADX: 30.97 | AA83: ATR: 1.03 | AB83: RVOL: 0.66 | AC83: Trailing: 36.42 | AD83: 46150.444 | AE83: LTC,Preço: 38.48,Dist MM20: -5.53%,Momentum: -1.58,RSI: 37.56,ADX: 30.97,ATR: 1.03,RVOL: 0.66,Estado: Observar,Entrada: N/A,Stop: N/A,Take-Profit: N/A,Break-Even: N/A,Qtd: N/A,Trailing: 36.42,Data: 05/08/2026 10:33:51
E84: MA | F84: MasterCard US | G84: =IFERROR(__xludf.DUMMYFUNCTION("GOOGLEFINANCE(E84, ""price"")"),560.81) -> 560.81 | H84: =IFERROR(__xludf.DUMMYFUNCTION("GOOGLEFINANCE(E84, ""low"")"),554.0) -> 554 | I84: =IFERROR(__xludf.DUMMYFUNCTION("GOOGLEFINANCE(E84, ""high"")"),565.75) -> 565.75 | P84: 588.03 | Q84: 45912.101 | R84: TRUE | S84: MA,Preço: 555.89,Dist MM20: -3.75%,Momentum: -25.21,RSI: 38.45,ADX: 17.89,ATR: 8.19,RVOL: 1.41,Estado: Observar,Entrada: N/A,Stop: N/A,Take-Profit: N/A,Break-Even: N/A,Qtd: N/A,Trailing: 539.51,Data: 23/09/2026 02:36:31 | T84: 0 | U84: MA | V84: Preço: 577.35 | W84: Dist MM20: 6.69% | X84: Momentum: 50.61 | Y84: RSI: 72.28 | Z84: ADX: 31.59 | AA84: ATR: 10.69 | AB84: RVOL: 1.40 | AC84: Data: 31/07/2026 02:19:18 | AD84: 46030.371 | AE84: MA,Preço: 577.35,Dist MM20: 6.69%,Momentum: 50.61,RSI: 72.28,ADX: 31.59,ATR: 10.69,RVOL: 1.40,Estado: Forca Consolidada,Entrada: 575.21,Stop: 562.38,Take-Profit: 594.45,Break-Even: 584.83,Qtd: 3.90,Data: 31/07/2026 02:19:18
E85: MAIN | F85: Main Street Capital | G85: =IFERROR(__xludf.DUMMYFUNCTION("GOOGLEFINANCE(E85, ""price"")"),55.11) -> 55.11 | R85: TRUE | S85: MAIN,Preço: 56.00,Dist MM20: -2.12%,Momentum: -1.97,RSI: 42.80,ADX: 24.61,ATR: 0.84,RVOL: 0.88,Estado: Observar,Entrada: N/A,Stop: N/A,Take-Profit: N/A,Break-Even: N/A,Qtd: N/A,Trailing: 54.32,Data: 23/09/2026 06:59:35 | T85: 0 | U85: MAIN | V85: Preço: 57.15 | W85: Dist MM20: 5.86% | X85: Momentum: 3.74 | Y85: RSI: 69.09 | Z85: ADX: 19.30 | AA85: ATR: 1.27 | AB85: RVOL: 1.03 | AC85: Trailing: 55.37 | AD85: 46150.444 | AE85: MAIN,Preço: 57.15,Dist MM20: 5.86%,Momentum: 3.74,RSI: 69.09,ADX: 19.30,ATR: 1.27,RVOL: 1.03,Estado: Aguardar Recuo,Entrada: 56.64,Stop: 55.37,Take-Profit: 59.18,Break-Even: 57.91,Qtd: 39.37,Trailing: 55.37,Data: 05/08/2026 10:27:35
E86: MCHP | F86: Microchip Tec | G86: =IFERROR(__xludf.DUMMYFUNCTION("GOOGLEFINANCE(E86, ""price"")"),75.23) -> 75.23 | H86: =IFERROR(__xludf.DUMMYFUNCTION("GOOGLEFINANCE(E86, ""low"")"),73.77) -> 73.77 | I86: =IFERROR(__xludf.DUMMYFUNCTION("GOOGLEFINANCE(E86, ""high"")"),75.77) -> 75.77 | K86: 12.7 | L86: 66.73 | O86: R1 Down | P86: 63.5 | Q86: 45995.482 | R86: TRUE | S86: MCHP,Preço: 75.82,Dist MM20: 3.84%,Momentum: 4.41,RSI: 53.35,ADX: 17.76,ATR: 2.22,RVOL: 0.91,Estado: Aguardar Recuo,Entrada: 74.93,Stop: 72.71,Take-Profit: 77.59,Break-Even: 76.26,Qtd: 11.26,Trailing: 72.71,Data: 23/09/2026 02:36:48 | T86: 0 | U86: MCHP | V86: Preço: 75.01 | W86: Dist MM20: -8.97% | X86: Momentum: -13.58 | Y86: RSI: 37.87 | Z86: ADX: 26.32 | AA86: ATR: 3.45 | AB86: RVOL: 1.21 | AC86: Data: 31/07/2026 02:36:04 | AD86: 46030.371 | AE86: MCHP,Preço: 75.01,Dist MM20: -8.97%,Momentum: -13.58,RSI: 37.87,ADX: 26.32,ATR: 3.45,RVOL: 1.21,Estado: Forca Consolidada,Entrada: 74.32,Stop: 70.18,Take-Profit: 80.53,Break-Even: 77.42,Qtd: 12.08,Data: 31/07/2026 02:36:04
E87: MDB | F87: Mongo DB | G87: =IFERROR(__xludf.DUMMYFUNCTION("GOOGLEFINANCE(E87, ""price"")"),437.21) -> 437.21 | R87: TRUE | S87: MDB,Preço: 427.69,Dist MM20: 8.10%,Momentum: -6.52,RSI: 59.25,ADX: 17.62,ATR: 20.09,RVOL: 1.04,Estado: Observar,Entrada: N/A,Stop: N/A,Take-Profit: N/A,Break-Even: N/A,Qtd: N/A,Trailing: 387.51,Data: 23/09/2026 07:04:02 | T87: 0 | U87: MDB | V87: Preço: 434.21 | W87: Dist MM20: 1.87% | X87: Momentum: -3.62 | Y87: RSI: 57.78 | Z87: ADX: 24.58 | AA87: ATR: 20.07 | AB87: RVOL: 1.82 | AC87: Trailing: 394.07 | AD87: 46031.913 | AE87: MDB,Preço: 434.21,Dist MM20: 1.87%,Momentum: -3.62,RSI: 57.78,ADX: 24.58,ATR: 20.07,RVOL: 1.82,Estado: Observar,Entrada: N/A,Stop: N/A,Take-Profit: N/A,Break-Even: N/A,Qtd: N/A,Trailing: 394.07,Data: 01/09/2026 21:44:31
E88: MED | F88: Medifast | G88: =IFERROR(__xludf.DUMMYFUNCTION("GOOGLEFINANCE(E88, ""price"")"),12.09) -> 12.09 | J88: ACTIVA | R88: TRUE | S88: MED,Preço: 12.08,Dist MM20: -0.66%,Momentum: -0.01,RSI: 53.07,ADX: 26.09,ATR: 0.37,RVOL: 0.62,Estado: Observar,Entrada: N/A,Stop: N/A,Take-Profit: N/A,Break-Even: N/A,Qtd: N/A,Trailing: 11.75,Data: 23/09/2026 06:41:44 | T88: 0 | U88: MED | V88: Preço: 9.91 | W88: Dist MM20: -4.25% | X88: Momentum: -0.81 | Y88: RSI: 40.71 | Z88: ADX: 27.36 | AA88: ATR: 0.41 | AB88: RVOL: 0.64 | AC88: Data: 31/07/2026 04:49:42 | AD88: 46030.371 | AE88: MED,Preço: 9.91,Dist MM20: -4.25%,Momentum: -0.81,RSI: 40.71,ADX: 27.36,ATR: 0.41,RVOL: 0.64,Estado: Forca Consolidada,Entrada: 9.83,Stop: 9.34,Take-Profit: 10.57,Break-Even: 10.20,Qtd: 101.63,Data: 31/07/2026 04:49:42
B89: Time Now | C89: =now() -> 46288.715 | E89: MERC | F89: Mercer International | G89: =IFERROR(__xludf.DUMMYFUNCTION("GOOGLEFINANCE(E89, ""price"")"),0.32) -> 0.32 | R89: TRUE | S89: MERC,Preço: 0.32,Dist MM20: -15.18%,Momentum: -0.07,RSI: 26.32,ADX: 15.38,ATR: 0.03,RVOL: 0.06,Estado: Observar,Entrada: N/A,Stop: N/A,Take-Profit: N/A,Break-Even: N/A,Qtd: N/A,Trailing: 0.26,Data: 23/09/2026 07:04:04 | T89: 0 | U89: MERC | V89: Preço: 0.59 | W89: Dist MM20: -9.43% | X89: Momentum: -0.05 | Y89: RSI: 37.92 | Z89: ADX: 17.89 | AA89: ATR: 0.06 | AB89: RVOL: 0.31 | AC89: Data: 31/07/2026 04:50:40 | AD89: 46030.371 | AE89: MERC,Preço: 0.59,Dist MM20: -9.43%,Momentum: -0.05,RSI: 37.92,ADX: 17.89,ATR: 0.06,RVOL: 0.31,Estado: Observar,Entrada: N/A,Stop: N/A,Take-Profit: N/A,Break-Even: N/A,Qtd: N/A,Data: 31/07/2026 04:50:40
E90: META | F90: Meta Platforms | G90: =IFERROR(__xludf.DUMMYFUNCTION("GOOGLEFINANCE(E90, ""price"")"),754.12) -> 754.12 | H90: =IFERROR(__xludf.DUMMYFUNCTION("GOOGLEFINANCE(E90, ""low"")"),739.51) -> 739.51 | I90: =IFERROR(__xludf.DUMMYFUNCTION("GOOGLEFINANCE(E90, ""high"")"),763.9) -> 763.9 | K90: -7 | L90: 51.23 | M90: 27.21 | N90: 14.06 | O90: S1 Up | P90: 705.8 | Q90: 45855.341 | R90: TRUE | S90: META,Preço: 736.59,Dist MM20: 16.36%,Momentum: 158.05,RSI: 76.04,ADX: 32.25,ATR: 23.29,RVOL: 1.32,Estado: Observar,Entrada: N/A,Stop: N/A,Take-Profit: N/A,Break-Even: N/A,Qtd: N/A,Trailing: 690.01,Data: 23/09/2026 02:37:06 | T90: 0 | U90: META | V90: Preço: 539.03 | W90: Dist MM20: -13.35% | X90: Momentum: -130.18 | Y90: RSI: 32.11 | Z90: ADX: 18.64 | AA90: ATR: 19.31 | AB90: RVOL: 2.23 | AC90: Data: 31/07/2026 04:09:00 | AD90: 46030.371 | AE90: META,Preço: 539.03,Dist MM20: -13.35%,Momentum: -130.18,RSI: 32.11,ADX: 18.64,ATR: 19.31,RVOL: 2.23,Estado: Observar,Entrada: N/A,Stop: N/A,Take-Profit: N/A,Break-Even: N/A,Qtd: N/A,Data: 31/07/2026 04:09:00
E91: MNDY | F91: Monday.com | G91: =IFERROR(__xludf.DUMMYFUNCTION("GOOGLEFINANCE(E91, ""price"")"),87.51) -> 87.51 | H91: =IFERROR(__xludf.DUMMYFUNCTION("GOOGLEFINANCE(E91, ""low"")"),83.51) -> 83.51 | I91: =IFERROR(__xludf.DUMMYFUNCTION("GOOGLEFINANCE(E91, ""high"")"),90.76) -> 90.76 | P91: 316.01 | Q91: 45707.255 | R91: TRUE | S91: MNDY,Preço: 84.95,Dist MM20: -7.45%,Momentum: -11.56,RSI: 44.66,ADX: 12.24,ATR: 5.12,RVOL: 0.84,Estado: Observar,Entrada: N/A,Stop: N/A,Take-Profit: N/A,Break-Even: N/A,Qtd: N/A,Trailing: 74.71,Data: 23/09/2026 07:04:04 | T91: 0 | U91: MNDY | V91: Preço: 88.16 | W91: Dist MM20: 8.78% | X91: Momentum: 5.69 | Y91: RSI: 60.98 | Z91: ADX: 14.58 | AA91: ATR: 4.82 | AB91: RVOL: 1.36 | AC91: Data: 31/07/2026 04:09:17 | AD91: 46030.371 | AE91: MNDY,Preço: 88.16,Dist MM20: 8.78%,Momentum: 5.69,RSI: 60.98,ADX: 14.58,ATR: 4.82,RVOL: 1.36,Estado: Observar,Entrada: N/A,Stop: N/A,Take-Profit: N/A,Break-Even: N/A,Qtd: N/A,Data: 31/07/2026 04:09:17
E92: MPC | F92: Marathon Petroleum | G92: =IFERROR(__xludf.DUMMYFUNCTION("GOOGLEFINANCE(E92, ""price"")"),391.22) -> 391.22 | R92: TRUE | S92: S | T92: 0 | U92: MPC | V92: Preço: 413.92 | W92: Dist MM20: 8.66% | X92: Momentum: 51.65 | Y92: RSI: 80.27 | Z92: ADX: 48.12 | AA92: ATR: 12.21 | AB92: RVOL: 1.16 | AC92: Trailing: 389.50 | AD92: 17/09/2026 03:54:54 | AE92: MPC,Preço: 413.92,Dist MM20: 8.66%,Momentum: 51.65,RSI: 80.27,ADX: 48.12,ATR: 12.21,RVOL: 1.16,Estado: Observar,Entrada: N/A,Stop: N/A,Take-Profit: N/A,Break-Even: N/A,Qtd: N/A,Trailing: 389.50,Data: 17/09/2026 03:51:54
E93: MRNA | F93: Moderna | G93: =IFERROR(__xludf.DUMMYFUNCTION("GOOGLEFINANCE(E93, ""price"")"),184.69) -> 184.69 | H93: =IFERROR(__xludf.DUMMYFUNCTION("GOOGLEFINANCE(E93, ""low"")"),182.6) -> 182.6 | I93: =IFERROR(__xludf.DUMMYFUNCTION("GOOGLEFINANCE(E93, ""high"")"),192.31) -> 192.31 | K93: 5.14 | L93: 67.62 | M93: 23.09 | N93: 1.35 | O93: R1 Up | P93: 30.54 | Q93: 45841.419 | R93: TRUE | S93: MRNA,Preço: 182.56,Dist MM20: 22.14%,Momentum: 28.29,RSI: 72.17,ADX: 56.34,ATR: 10.67,RVOL: 1.30,Estado: Observar,Entrada: N/A,Stop: N/A,Take-Profit: N/A,Break-Even: N/A,Qtd: N/A,Trailing: 161.22,Data: 23/09/2026 02:37:25 | T93: 0 | U93: MRNA | V93: Preço: 57.92 | W93: Dist MM20: -10.88% | X93: Momentum: -10.35 | Y93: RSI: 45.07 | Z93: ADX: 23.22 | AA93: ATR: 2.82 | AB93: RVOL: 0.68 | AC93: Data: 31/07/2026 02:19:55 | AD93: 46030.371 | AE93: MRNA,Preço: 57.92,Dist MM20: -10.88%,Momentum: -10.35,RSI: 45.07,ADX: 23.22,ATR: 2.82,RVOL: 0.68,Estado: Aguardar Recuo,Entrada: 56.79,Stop: 53.97,Take-Profit: 62.43,Break-Even: 59.61,Qtd: 17.73,Data: 31/07/2026 02:19:55
E94: MRVL | F94: Marvell Tec Inv | G94: =IFERROR(__xludf.DUMMYFUNCTION("GOOGLEFINANCE(E94, ""price"")"),258.87) -> 258.87 | H94: =IFERROR(__xludf.DUMMYFUNCTION("GOOGLEFINANCE(E94, ""low"")"),254.0) -> 254 | I94: =IFERROR(__xludf.DUMMYFUNCTION("GOOGLEFINANCE(E94, ""high"")"),266.0) -> 266 | R94: TRUE | S94: MRVL,Preço: 262.36,Dist MM20: 14.00%,Momentum: 51.97,RSI: 63.95,ADX: 18.01,ATR: 10.52,RVOL: 0.89,Estado: Aguardar Recuo,Entrada: 258.15,Stop: 247.63,Take-Profit: 270.77,Break-Even: 264.46,Qtd: 2.38,Trailing: 247.63,Data: 23/09/2026 02:37:42 | T94: 0 | U94: MRVL | V94: Preço: 183.30 | W94: Dist MM20: -12.44% | X94: Momentum: -52.51 | Y94: RSI: 40.00 | Z94: ADX: 27.75 | AA94: ATR: 13.83 | AB94: RVOL: 1.15 | AC94: Data: 31/07/2026 02:10:09 | AD94: 46030.371 | AE94: MRVL,Preço: 183.30,Dist MM20: -12.44%,Momentum: -52.51,RSI: 40.00,ADX: 27.75,ATR: 13.83,RVOL: 1.15,Estado: Forca Consolidada,Entrada: 180.53,Stop: 163.93,Take-Profit: 205.42,Break-Even: 192.97,Qtd: 3.01,Data: 31/07/2026 02:10:09
E95: MSFT | F95: Microsoft | G95: =IFERROR(__xludf.DUMMYFUNCTION("GOOGLEFINANCE(E95, ""price"")"),498.95) -> 498.95 | H95: =IFERROR(__xludf.DUMMYFUNCTION("GOOGLEFINANCE(E95, ""low"")"),493.65) -> 493.65 | I95: =IFERROR(__xludf.DUMMYFUNCTION("GOOGLEFINANCE(E95, ""high"")"),509.44) -> 509.44 | R95: TRUE | S95: MSFT,Preço: 498.00,Dist MM20: -0.19%,Momentum: -3.02,RSI: 54.82,ADX: 31.57,ATR: 9.46,RVOL: 0.97,Estado: Observar,Entrada: N/A,Stop: N/A,Take-Profit: N/A,Break-Even: N/A,Qtd: N/A,Trailing: 479.08,Data: 23/09/2026 02:38:01 | T95: 0 | U95: MSFT | V95: Preço: 451.10 | W95: Dist MM20: 14.74% | X95: Momentum: 66.00 | Y95: RSI: 71.81 | Z95: ADX: 12.89 | AA95: ATR: 11.72 | AB95: RVOL: 3.10 | AC95: Data: 31/07/2026 02:19:37 | AD95: 46030.371 | AE95: MSFT,Preço: 451.10,Dist MM20: 14.74%,Momentum: 66.00,RSI: 71.81,ADX: 12.89,ATR: 11.72,RVOL: 3.10,Estado: Aguardar Recuo,Entrada: 446.41,Stop: 434.69,Take-Profit: 469.85,Break-Even: 458.13,Qtd: 4.27,Data: 31/07/2026 02:19:37
E96: MU | F96: Micron Tec | G96: =IFERROR(__xludf.DUMMYFUNCTION("GOOGLEFINANCE(E96, ""price"")"),1075.49) -> 1075.49 | R96: TRUE | S96: MU,Preço: 1096.16,Dist MM20: 12.69%,Momentum: 162.72,RSI: 66.06,ADX: 12.58,ATR: 36.89,RVOL: 1.15,Estado: Aguardar Recuo,Entrada: 1081.40,Stop: 1044.51,Take-Profit: 1125.67,Break-Even: 1103.54,Qtd: 0.68,Trailing: 1044.51,Data: 23/09/2026 06:45:28 | T96: 0 | U96: MU | V96: Preço: 892.67 | W96: Dist MM20: -0.99% | X96: Momentum: -11.61 | Y96: RSI: 48.76 | Z96: ADX: 20.55 | AA96: ATR: 69.49 | AB96: RVOL: 0.78 | AC96: Trailing: 795.38 | AD96: 46150.444 | AE96: MU,Preço: 892.67,Dist MM20: -0.99%,Momentum: -11.61,RSI: 48.76,ADX: 20.55,ATR: 69.49,RVOL: 0.78,Estado: Aguardar Recuo,Entrada: 864.87,Stop: 795.38,Take-Profit: 1003.85,Break-Even: 934.36,Qtd: 0.72,Trailing: 795.38,Data: 05/08/2026 10:25:58
E97: NET | F97: Cloudflare US | G97: =IFERROR(__xludf.DUMMYFUNCTION("GOOGLEFINANCE(E97, ""price"")"),358.42) -> 358.42 | H97: =IFERROR(__xludf.DUMMYFUNCTION("GOOGLEFINANCE(E97, ""low"")"),345.3) -> 345.3 | I97: =IFERROR(__xludf.DUMMYFUNCTION("GOOGLEFINANCE(E97, ""high"")"),364.23) -> 364.23 | K97: -11 | L97: 54.75 | M97: 29.18 | N97: 6.52 | O97: S1 Up | P97: 184.62 | Q97: 45853.692 | R97: TRUE | S97: NET,Preço: 353.00,Dist MM20: 14.65%,Momentum: 67.49,RSI: 65.72,ADX: 19.44,ATR: 17.10,RVOL: 1.02,Estado: Aguardar Recuo,Entrada: 346.16,Stop: 329.06,Take-Profit: 366.68,Break-Even: 356.42,Qtd: 1.46,Trailing: 329.06,Data: 23/09/2026 02:38:18 | T97: 0 | U97: NET | V97: Preço: 283.39 | W97: Dist MM20: 5.50% | X97: Momentum: 14.99 | Y97: RSI: 65.38 | Z97: ADX: 19.04 | AA97: ATR: 14.15 | AB97: RVOL: 0.92 | AC97: Data: 31/07/2026 02:07:55 | AD97: 46030.371 | AE97: NET,Preço: 283.39,Dist MM20: 5.50%,Momentum: 14.99,RSI: 65.38,ADX: 19.04,ATR: 14.15,RVOL: 0.92,Estado: Aguardar Recuo,Entrada: 277.73,Stop: 263.58,Take-Profit: 306.03,Break-Even: 291.88,Qtd: 3.53,Data: 31/07/2026 02:07:55
E98: NFLX | F98: Netflix US | G98: =IFERROR(__xludf.DUMMYFUNCTION("GOOGLEFINANCE(E98, ""price"")"),71.44) -> 71.44 | H98: =IFERROR(__xludf.DUMMYFUNCTION("GOOGLEFINANCE(E98, ""low"")"),71.07) -> 71.07 | I98: =IFERROR(__xludf.DUMMYFUNCTION("GOOGLEFINANCE(E98, ""high"")"),72.37) -> 72.37 | K98: 26.83 | L98: 68.29 | M98: 30.74 | N98: 24.79 | O98: R1 Up | P98: 1218.85 | Q98: 45812.248 | R98: TRUE | S98: NFLX,Preço: 72.16,Dist MM20: -7.74%,Momentum: -8.65,RSI: 38.55,ADX: 17.87,ATR: 2.06,RVOL: 1.06,Estado: Observar,Entrada: N/A,Stop: N/A,Take-Profit: N/A,Break-Even: N/A,Qtd: N/A,Trailing: 68.04,Data: 23/09/2026 02:38:36 | T98: 0 | U98: NFLX | V98: Preço: 73.17 | W98: Dist MM20: 0.79% | X98: Momentum: -0.20 | Y98: RSI: 48.85 | Z98: ADX: 29.33 | AA98: ATR: 2.21 | AB98: RVOL: 1.04 | AC98: Data: 31/07/2026 02:20:12 | AD98: 46030.371 | AE98: NFLX,Preço: 73.17,Dist MM20: 0.79%,Momentum: -0.20,RSI: 48.85,ADX: 29.33,ATR: 2.21,RVOL: 1.04,Estado: Observar,Entrada: N/A,Stop: N/A,Take-Profit: N/A,Break-Even: N/A,Qtd: N/A,Data: 31/07/2026 02:20:12
E99: NKE | F99: Nike US | G99: =IFERROR(__xludf.DUMMYFUNCTION("GOOGLEFINANCE(E99, ""price"")"),36.28) -> 36.28 | H99: =IFERROR(__xludf.DUMMYFUNCTION("GOOGLEFINANCE(E99, ""low"")"),35.78) -> 35.78 | I99: =IFERROR(__xludf.DUMMYFUNCTION("GOOGLEFINANCE(E99, ""high"")"),36.62) -> 36.62 | P99: 76.78 | Q99: 46219.377 | R99: TRUE | S99: NKE,Preço: 36.10,Dist MM20: -3.82%,Momentum: -2.02,RSI: 36.82,ADX: 28.31,ATR: 0.85,RVOL: 0.97,Estado: Observar,Entrada: N/A,Stop: N/A,Take-Profit: N/A,Break-Even: N/A,Qtd: N/A,Trailing: 34.40,Data: 23/09/2026 02:38:54 | T99: 0 | U99: NKE | V99: Preço: 42.29 | W99: Dist MM20: -1.70% | X99: Momentum: -2.08 | Y99: RSI: 46.47 | Z99: ADX: 11.38 | AA99: ATR: 1.27 | AB99: RVOL: 0.91 | AC99: Data: 31/07/2026 02:20:30 | AD99: 46030.371 | AE99: NKE,Preço: 42.29,Dist MM20: -1.70%,Momentum: -2.08,RSI: 46.47,ADX: 11.38,ATR: 1.27,RVOL: 0.91,Estado: Observar,Entrada: N/A,Stop: N/A,Take-Profit: N/A,Break-Even: N/A,Qtd: N/A,Data: 31/07/2026 02:20:30
E100: NOV | F100: Novo Nordisk EU | G100: =IFERROR(__xludf.DUMMYFUNCTION("GOOGLEFINANCE(E100, ""price"")"),33.78) -> 33.78 | H100: =IFERROR(__xludf.DUMMYFUNCTION("GOOGLEFINANCE(E100, ""low"")"),33.75) -> 33.75 | I100: =IFERROR(__xludf.DUMMYFUNCTION("GOOGLEFINANCE(E100, ""high"")"),34.82) -> 34.82 | K100: -1.26 | L100: 52.42 | M100: 17.96 | N100: 2.75 | O100: P up | P100: 82.41 | Q100: 45708.414 | R100: TRUE | S100: NOV,Preço: 20.18,Dist MM20: -3.32%,Momentum: -1.18,RSI: 43.36,ADX: 16.52,ATR: 0.61,RVOL: 0.86,Estado: Aguardar Recuo,Entrada: 19.94,Stop: 19.33,Take-Profit: 20.67,Break-Even: 20.30,Qtd: 40.98,Trailing: 19.33,Data: 23/09/2026 07:04:05 | T100: 0 | U100: NOV | V100: Preço: 19.30 | W100: Dist MM20: -0.15% | X100: Momentum: 0.41 | Y100: RSI: 47.31 | Z100: ADX: 15.83 | AA100: ATR: 0.67 | AB100: RVOL: 0.71 | AC100: Data: 31/07/2026 04:09:33 | AD100: 46030.371 | AE100: NOV,Preço: 19.30,Dist MM20: -0.15%,Momentum: 0.41,RSI: 47.31,ADX: 15.83,ATR: 0.67,RVOL: 0.71,Estado: Aguardar Recuo,Entrada: 19.03,Stop: 18.36,Take-Profit: 20.37,Break-Even: 19.70,Qtd: 74.63,Data: 31/07/2026 04:09:33
E101: NOW | F101: Service Noew | G101: =IFERROR(__xludf.DUMMYFUNCTION("GOOGLEFINANCE(E101, ""price"")"),140.29) -> 140.29 | H101: =IFERROR(__xludf.DUMMYFUNCTION("GOOGLEFINANCE(E101, ""low"")"),136.15) -> 136.15 | I101: =IFERROR(__xludf.DUMMYFUNCTION("GOOGLEFINANCE(E101, ""high"")"),141.54) -> 141.54 | P101: 1039.55 | Q101: 45793.512 | R101: TRUE | S101: NOW,Preço: 137.00,Dist MM20: -0.44%,Momentum: -5.90,RSI: 54.19,ADX: 23.93,ATR: 5.28,RVOL: 0.79,Estado: Observar,Entrada: N/A,Stop: N/A,Take-Profit: N/A,Break-Even: N/A,Qtd: N/A,Trailing: 126.44,Data: 23/09/2026 02:39:12 | T101: 0 | U101: NOW | V101: Preço: 110.07 | W101: Dist MM20: 4.22% | X101: Momentum: 2.36 | Y101: RSI: 55.47 | Z101: ADX: 13.88 | AA101: ATR: 5.98 | AB101: RVOL: 1.10 | AC101: Data: 31/07/2026 02:24:00 | AD101: 46030.371 | AE101: NOW,Preço: 110.07,Dist MM20: 4.22%,Momentum: 2.36,RSI: 55.47,ADX: 13.88,ATR: 5.98,RVOL: 1.10,Estado: Observar,Entrada: N/A,Stop: N/A,Take-Profit: N/A,Break-Even: N/A,Qtd: N/A,Data: 31/07/2026 02:24:00
...

Sheet Diário de Bordo
A1: Diario de Bordo | B1: Stock | C1: Description | D1: Market Price | E1: L | F1: H | G1: Result | H1: Momentum | I1: RSI | J1: ADX | K1: ATR | L1: Pivot | M1: Price | N1: Time | O1: true | P1: STOCK,#ERRO_LIMITE_CHAVES,Todas as chaves esgotaram,,,,,,,,,,,, | Q1: Máximo 15h30 | R1: Nova Entrada | S1: Novo Stop Loss | T1: Novo Take Profit | U1: Status Intraday | V1: Resumo Intraday | W1: STATUS | X1: PRECO ENTRADA | Y1: STOP INICIAL | Z1: PRECO SAIDA | AA1: QUANTIDADE | AB1: R MULTIPLO | AC1: LUCRO/PREJUIZO
Q2: Máximo 15h30 | R2: Nova Entrada | S2: Novo Stop Loss | T2: Novo Take Profit | U2: Status Intraday | V2: Resumo Intraday
A3: 23/09/2026 03:46:09 | B3: RGLD | C3: Royal Gold | P3: RGLD,Preço: 258.29,Dist MM20: 0.28%,Momentum: 4.20,RSI: 58.52,ADX: 23.00,ATR: 6.63,RVOL: 1.49,Estado: Alerta Iminente,Entrada: 256.96,Stop: 249.00,Take-Profit: 266.51,Break-Even: 261.74,Qtd: 3.14,Trailing: 249.00,Data: 23/09/2026 07:02:20 | W3: ATIVA | X3: 255.49 | Y3: 249 | AA3: 3.14 | AC3: =(Z3-X3) * AA3 -> -802.2386
A4: 22/09/2026 03:46:09 | B4: MED | C4: Medifast | D4: 12.26 | O4: TRUE | P4: MED,Preço: 12.26,Dist MM20: 0.86%,Momentum: 0.12,RSI: 57.22,ADX: 26.24,ATR: 0.37,RVOL: 1.33,Estado: Forca Consolidada,Entrada: 12.19,Stop: 11.75,Take-Profit: 12.72,Break-Even: 12.46,Qtd: 56.31,Trailing: 11.75,Data: 22/09/2026 03:46:08 | Q4: 12.47 | R4: 12.1 | S4: 11.73 | T4: 12.65 | U4: Forca Consolidada | V4: MED (INTRADAY),Máximo 15h30: 12.47,Estado: Forca Consolidada,Entrada: 12.10,Stop: 11.73,Take-Profit: 12.65,Data: 22/09/2026 15:31:06 | W4: LOSS | X4: 12.19 | Y4: 11.75 | Z4: 11.7 | AA4: 56.31 | AC4: =(Z4-X4) * AA4 -> -27.5919
A5: 22/09/2026 03:43:54 | B5: U | C5: Unity Software Inc | D5: 43.21 | E5: 41.26 | F5: 43.55 | H5: 6.81 | I5: 72.8 | J5: 14.06 | K5: 1,47 | L5: R1 Up | M5: 28 | N5: 45709.328 | O5: TRUE | P5: U,Preço: 43.21,Dist MM20: 0.93%,Momentum: 1.11,RSI: 55.92,ADX: 28.80,ATR: 1.69,RVOL: 1.14,Estado: Forca Consolidada,Entrada: 42.87,Stop: 40.84,Take-Profit: 45.30,Break-Even: 44.08,Qtd: 12.33,Trailing: 40.84,Data: 22/09/2026 03:43:53 | Q5: 43.87 | R5: 42.18 | S5: 40.49 | T5: 44.72 | U5: Forca Consolidada | V5: U (INTRADAY),Máximo 15h30: 43.87,Estado: Forca Consolidada,Entrada: 42.18,Stop: 40.49,Take-Profit: 44.72,Data: 22/09/2026 15:31:07 | AC5: =(Z5-X5) * AA5 -> 0
B6: LTC | C6: LTC Properties | D6: 42.88 | O6: TRUE | P6: LTC,Preço: 42.88,Dist MM20: 2.49%,Momentum: 2.56,RSI: 59.70,ADX: 28.43,ATR: 0.98,RVOL: 1.08,Estado: Forca Consolidada,Entrada: 42.68,Stop: 41.50,Take-Profit: 44.09,Break-Even: 43.39,Qtd: 21.26,Trailing: 41.50,Data: 22/09/2026 03:31:35 | Q6: 42.67 | R6: - | S6: - | T6: - | U6: Ignorado - S/ Quebra de Fecho | V6: LTC,Máximo 15h30: 42.67,Estado: Ignorado - S/ Quebra de Fecho,Data: 22/09/2026 15:31:07 | W6: ATIVA | X6: 42.48 | Y6: 41.5 | AA6: 21.26 | AC6: =(Z6-X6) * AA6 -> -903.1248
A7: 22/09/2026 02:20:47 | B7: CSCO | C7: Cisco Systems | D7: 111.46 | E7: 108.83 | F7: 111.5 | M7: 57.13 | N7: 45827.333 | O7: TRUE | P7: CSCO,Preço: 111.46,Dist MM20: 1.30%,Momentum: 0.97,RSI: 50.92,ADX: 25.23,ATR: 2.26,RVOL: 1.39,Estado: Forca Consolidada,Entrada: 111.01,Stop: 108.30,Take-Profit: 114.26,Break-Even: 112.64,Qtd: 9.22,Trailing: 108.30,Data: 22/09/2026 02:20:46 | Q7: 110.43 | R7: - | S7: - | T7: - | U7: Ignorado - S/ Quebra de Fecho | V7: CSCO,Máximo 15h30: 110.43,Estado: Ignorado - S/ Quebra de Fecho,Data: 22/09/2026 15:31:07 | AC7: =(Z7-X7) * AA7 -> 0
A8: 21/09/2026 08:05:47 | B8: EMR | C8: Emerson Electric | D8: 149.92 | O8: TRUE | P8: EMR,Preço: 149.92,Dist MM20: -1.19%,Momentum: -5.26,RSI: 47.65,ADX: 23.32,ATR: 3.33,RVOL: 1.75,Estado: Forca Consolidada,Entrada: 149.25,Stop: 145.25,Take-Profit: 155.24,Break-Even: 152.25,Qtd: 12.51,Trailing: 145.25,Data: 21/09/2026 08:05:47 | Q8: 151.47 | R8: 148.14 | S8: 144.81 | T8: 153.13 | U8: Forca Consolidada | V8: EMR (INTRADAY),Máximo 15h30: 151.47,Estado: Forca Consolidada,Entrada: 148.14,Stop: 144.81,Take-Profit: 153.13,Data: 21/09/2026 15:30:10 | AC8: =(Z8-X8) * AA8 -> 0
A9: 21/09/2026 04:06:09 | B9: PLTR | C9: Palantir US | D9: 177.64 | E9: 172 | F9: 177.75 | H9: 7.79 | I9: 66.59 | J9: 18.67 | K9: 5.75 | L9: S1 Up | M9: 123.26 | N9: 45814.379 | O9: TRUE | P9: PLTR,Preço: 177.64,Dist MM20: 0.99%,Momentum: -8.65,RSI: 57.04,ADX: 20.97,ATR: 6.71,RVOL: 1.36,Estado: Forca Consolidada,Entrada: 176.30,Stop: 168.25,Take-Profit: 188.38,Break-Even: 182.34,Qtd: 6.21,Trailing: 168.25,Data: 21/09/2026 04:06:08 | Q9: 182.2 | R9: 175.49 | S9: 168.78 | T9: 185.55 | U9: Forca Consolidada | V9: PLTR (INTRADAY),Máximo 15h30: 182.20,Estado: Forca Consolidada,Entrada: 175.49,Stop: 168.78,Take-Profit: 185.55,Data: 21/09/2026 15:30:10 | AC9: =(Z9-X9) * AA9 -> 0
A10: 21/09/2026 04:05:30 | B10: PFE | C10: Pfizer | D10: 27.66 | E10: 27.34 | F10: 27.66 | O10: TRUE | P10: PFE,Preço: 27.66,Dist MM20: -1.42%,Momentum: -0.30,RSI: 52.16,ADX: 32.71,ATR: 0.47,RVOL: 2.22,Estado: Forca Consolidada,Entrada: 27.57,Stop: 27.01,Take-Profit: 28.42,Break-Even: 28.00,Qtd: 88.65,Trailing: 27.01,Data: 21/09/2026 04:05:30 | Q10: 27.79 | R10: 27.32 | S10: 26.85 | T10: 28.02 | U10: Forca Consolidada | V10: PFE (INTRADAY),Máximo 15h30: 27.79,Estado: Forca Consolidada,Entrada: 27.32,Stop: 26.85,Take-Profit: 28.02,Data: 21/09/2026 15:30:11 | W10: BREAKEVEN | X10: 27.57 | Y10: 27.01 | Z10: 27.57 | AA10: 88.65 | AC10: =(Z10-X10) * AA10 -> 0
A11: 21/09/2026 02:20:55 | B11: BABA | C11: Alibaba US | D11: 113.24 | E11: 110.85 | F11: 113.77 | L11: R3 Down | M11: 117.11 | N11: 45856.305 | O11: TRUE | P11: BABA,Preço: 113.24,Dist MM20: 0.05%,Momentum: -5.66,RSI: 48.00,ADX: 22.29,ATR: 2.06,RVOL: 1.18,Estado: Forca Consolidada,Entrada: 112.83,Stop: 110.36,Take-Profit: 116.54,Break-Even: 114.69,Qtd: 20.23,Trailing: 110.36,Data: 21/09/2026 02:20:54 | Q11: 115.25 | R11: 113.19 | S11: 111.13 | T11: 116.28 | U11: Forca Consolidada | V11: BABA (INTRADAY),Máximo 15h30: 115.25,Estado: Forca Consolidada,Entrada: 113.19,Stop: 111.13,Take-Profit: 116.28,Data: 21/09/2026 15:30:12 | AC11: =(Z11-X11) * AA11 -> 0
A12: 21/09/2026 02:20:34 | B12: AVGO | C12: Broadcom | D12: 357.61 | E12: 351.33 | F12: 363.28 | H12: 26.17 | I12: 81.35 | J12: 35.38 | K12: 7.33 | L12: R1 Up | M12: 248.89 | N12: 45814.126 | O12: TRUE | P12: AVGO,Preço: 357.61,Dist MM20: -0.48%,Momentum: -11.18,RSI: 45.54,ADX: 25.90,ATR: 8.49,RVOL: 1.64,Estado: Forca Consolidada,Entrada: 355.91,Stop: 345.72,Take-Profit: 371.19,Break-Even: 363.55,Qtd: 4.91,Trailing: 345.72,Data: 21/09/2026 02:20:34 | Q12: 359.92 | R12: 351.43 | S12: 342.94 | T12: 364.17 | U12: Forca Consolidada | V12: AVGO (INTRADAY),Máximo 15h30: 359.92,Estado: Forca Consolidada,Entrada: 351.43,Stop: 342.94,Take-Profit: 364.17,Data: 21/09/2026 15:30:13 | AC12: =(Z12-X12) * AA12 -> 0
A13: 18/09/2026 03:04:55 | B13: OR | C13: Loreal | D13: 380.1 | E13: 380.1 | F13: 386.3 | M13: 335.95 | O13: TRUE | P13: OR,Preço: 36.99,Dist MM20: 0.50%,Momentum: -1.65,RSI: 57.99,ADX: 21.50,ATR: 1.16,RVOL: 0.94,Estado: Forca Consolidada,Entrada: 36.76,Stop: 35.37,Take-Profit: 38.85,Break-Even: 37.80,Qtd: 35.92,Trailing: 35.37,Data: 18/09/2026 03:04:53 | Q13: 36.95 | R13: - | S13: - | T13: - | U13: Ignorado - S/ Quebra de Fecho | V13: OR,Máximo 15h30: 36.95,Estado: Ignorado - S/ Quebra de Fecho,Data: 18/09/2026 15:30:48 | AC13: =(Z13-X13) * AA13 -> 0
A14: 18/09/2026 02:51:06 | B14: PFE | C14: Pfizer | D14: 27.64 | E14: 27.55 | F14: 27.81 | O14: TRUE | P14: PFE,Preço: 27.64,Dist MM20: -1.51%,Momentum: -0.38,RSI: 51.85,ADX: 34.67,ATR: 0.47,RVOL: 0.91,Estado: Forca Consolidada,Entrada: 27.55,Stop: 26.99,Take-Profit: 28.40,Break-Even: 27.98,Qtd: 88.65,Trailing: 26.99,Data: 18/09/2026 02:51:05 | Q14: 27.66 | R14: 27.19 | S14: 26.72 | T14: 27.89 | U14: Forca Consolidada | V14: PFE (INTRADAY),Máximo 15h30: 27.66,Estado: Forca Consolidada,Entrada: 27.19,Stop: 26.72,Take-Profit: 27.89,Data: 18/09/2026 15:30:48 | AC14: =(Z14-X14) * AA14 -> 0
A15: 18/09/2026 02:44:42 | B15: CVX | C15: Chevron | D15: 211.57 | O15: TRUE | P15: CVX,Preço: 211.57,Dist MM20: 1.52%,Momentum: 11.80,RSI: 58.53,ADX: 32.52,ATR: 3.88,RVOL: 0.94,Estado: Forca Consolidada,Entrada: 210.79,Stop: 206.13,Take-Profit: 217.77,Break-Even: 214.28,Qtd: 10.74,Trailing: 206.13,Data: 18/09/2026 02:44:39 | Q15: 211.9 | R15: 208.02 | S15: 204.14 | T15: 213.84 | U15: Forca Consolidada | V15: CVX (INTRADAY),Máximo 15h30: 211.90,Estado: Forca Consolidada,Entrada: 208.02,Stop: 204.14,Take-Profit: 213.84,Data: 18/09/2026 15:30:48 | AC15: =(Z15-X15) * AA15 -> 0
A16: 18/09/2026 02:43:39 | B16: COP | C16: ConocoPhillips | D16: 133.19 | O16: TRUE | P16: COP,Preço: 133.19,Dist MM20: -1.01%,Momentum: 3.67,RSI: 52.56,ADX: 25.26,ATR: 3.19,RVOL: 1.12,Estado: Forca Consolidada,Entrada: 132.55,Stop: 128.72,Take-Profit: 138.29,Break-Even: 135.42,Qtd: 13.06,Trailing: 128.72,Data: 18/09/2026 02:43:39 | Q16: 133.2 | R16: 130.01 | S16: 126.82 | T16: 134.79 | U16: Forca Consolidada | V16: COP (INTRADAY),Máximo 15h30: 133.20,Estado: Forca Consolidada,Entrada: 130.01,Stop: 126.82,Take-Profit: 134.79,Data: 18/09/2026 15:30:49 | W16: LOSS | X16: 132.51 | Y16: 128.72 | Z16: 128.76 | AA16: 13.06 | AC16: =(Z16-X16) * AA16 -> -48.975
A17: 18/09/2026 02:42:29 | B17: MSFT | C17: Microsoft | D17: 497.75 | E17: 493.17 | F17: 501.47 | O17: TRUE | P17: MSFT,Preço: 497.75,Dist MM20: 0.18%,Momentum: -7.31,RSI: 55.58,ADX: 32.72,ATR: 9.09,RVOL: 0.89,Estado: Forca Consolidada,Entrada: 495.93,Stop: 485.02,Take-Profit: 512.29,Break-Even: 504.11,Qtd: 4.58,Trailing: 485.02,Data: 18/09/2026 02:42:28 | Q17: 498.65 | R17: 489.56 | S17: 480.47 | T17: 503.19 | U17: Forca Consolidada | V17: MSFT (INTRADAY),Máximo 15h30: 498.65,Estado: Forca Consolidada,Entrada: 489.56,Stop: 480.47,Take-Profit: 503.19,Data: 18/09/2026 15:30:49 | AC17: =(Z17-X17) * AA17 -> 0
A18: 18/09/2026 02:42:22 | B18: MAIN | C18: Main Street Capital | D18: 57.03 | O18: TRUE | P18: MAIN,Preço: 57.03,Dist MM20: -0.94%,Momentum: -1.56,RSI: 50.29,ADX: 25.39,ATR: 0.88,RVOL: 0.90,Estado: Forca Consolidada,Entrada: 56.85,Stop: 55.79,Take-Profit: 58.43,Break-Even: 57.64,Qtd: 47.35,Trailing: 55.79,Data: 18/09/2026 02:42:21 | Q18: 57.1 | R18: 56.22 | S18: 55.34 | T18: 57.54 | U18: Forca Consolidada | V18: MAIN (INTRADAY),Máximo 15h30: 57.10,Estado: Forca Consolidada,Entrada: 56.22,Stop: 55.34,Take-Profit: 57.54,Data: 18/09/2026 15:30:49 | AC18: =(Z18-X18) * AA18 -> 0
A19: 18/09/2026 02:33:40 | B19: TSLA | C19: Tesla | O19: TRUE | P19: TSLA,Preço: 366.20,Dist MM20: 2.11%,Momentum: 11.39,RSI: 54.81,ADX: 21.03,ATR: 12.13,RVOL: 0.98,Estado: Forca Consolidada,Entrada: 363.77,Stop: 349.21,Take-Profit: 385.60,Break-Even: 374.69,Qtd: 3.44,Trailing: 349.21,Data: 18/09/2026 02:33:39 | Q19: 370.9 | R19: 358.77 | S19: 346.64 | T19: 376.96 | U19: Forca Consolidada | V19: TSLA (INTRADAY),Máximo 15h30: 370.90,Estado: Forca Consolidada,Entrada: 358.77,Stop: 346.64,Take-Profit: 376.96,Data: 18/09/2026 15:30:54 | AC19: =(Z19-X19) * AA19 -> 0
A20: 18/09/2026 02:25:35 | B20: CSCO | C20: Cisco Systems | D20: 110.24 | E20: 109.32 | F20: 111.44 | G20: ACTIVA | M20: 57.13 | N20: 45827.333 | O20: TRUE | P20: CSCO,Preço: 110.24,Dist MM20: 0.21%,Momentum: -1.91,RSI: 47.72,ADX: 25.01,ATR: 2.20,RVOL: 1.15,Estado: Forca Consolidada,Entrada: 109.80,Stop: 107.16,Take-Profit: 113.76,Break-Even: 111.78,Qtd: 18.94,Trailing: 109.27,Data: 18/09/2026 02:25:34 | Q20: 110.81 | R20: 108.61 | S20: 106.41 | T20: 111.91 | U20: Forca Consolidada | V20: CSCO (INTRADAY),Máximo 15h30: 110.81,Estado: Forca Consolidada,Entrada: 108.61,Stop: 106.41,Take-Profit: 111.91,Data: 18/09/2026 15:30:54 | AC20: =(Z20-X20) * AA20 -> 0
A21: 18/09/2026 02:25:04 | B21: BMNR | C21: BitMine Immersion | D21: 23.89 | G21: ACTIVA | O21: TRUE | P21: BMNR,Preço: 23.89,Dist MM20: -1.51%,Momentum: -1.74,RSI: 54.26,ADX: 41.62,ATR: 1.58,RVOL: 0.88,Estado: Forca Consolidada,Entrada: 23.57,Stop: 21.67,Take-Profit: 26.41,Break-Even: 24.99,Qtd: 26.37,Trailing: 21.37,Data: 18/09/2026 02:25:03 | Q21: 25.81 | R21: 24.23 | S21: 22.65 | T21: 26.6 | U21: Forca Consolidada | V21: BMNR (INTRADAY),Máximo 15h30: 25.81,Estado: Forca Consolidada,Entrada: 24.23,Stop: 22.65,Take-Profit: 26.60,Data: 18/09/2026 15:30:55 | AC21: =(Z21-X21) * AA21 -> 0
A22: 17/09/2026 05:36:16 | B22: SMCI | C22: Super Micro Computer | D22: 36.85 | E22: 35.36 | F22: 37.12 | M22: 44.04 | N22: 46219.397 | O22: TRUE | P22: SMCI,Preço: 36.85,Dist MM20: -1.89%,Momentum: -0.54,RSI: 51.10,ADX: 22.77,ATR: 2.01,RVOL: 0.85,Estado: Forca Consolidada,Entrada: 36.45,Stop: 34.04,Take-Profit: 40.07,Break-Even: 38.26,Qtd: 20.73,Trailing: 34.04,Data: 17/09/2026 05:36:15 | Q22: 39.77 | R22: 37.76 | S22: 35.75 | T22: 40.78 | U22: Forca Consolidada | V22: SMCI (INTRADAY),Máximo 15h30: 39.77,Estado: Forca Consolidada,Entrada: 37.76,Stop: 35.75,Take-Profit: 40.78,Data: 17/09/2026 15:31:00 | AC22: =(Z22-X22) * AA22 -> 0
A23: 16/09/2026 03:09:51 | B23: CSCO | C23: Cisco | P23: CSCO,Preço: 107.74,Dist MM20: -2.08%,Momentum: -4.62,RSI: 41.09,ADX: 25.12,ATR: 2.12,RVOL: 1.12,Estado: Observar,Entrada: N/A,Stop: N/A,Take-Profit: N/A,Break-Even: N/A,Qtd: N/A,Trailing: 103.50,Data: 17/09/2026 02:22:35 | Q23: 111.44 | R23: 109.27 | S23: 109.27 | T23: 112.5 | U23: Forca Consolidada | V23: CSCO (INTRADAY),Máximo 15h30: 111.44,Estado: Forca Consolidada,Entrada: 109.32,Stop: 107.20,Take-Profit: 112.50,Data: 17/09/2026 15:31:01 | W23: BREAKEVEN | X23: 109.27 | Y23: 109.27 | Z23: 109.24 | AA23: 25 | AC23: =(Z23-X23) * AA23 -> -0.75
A24: 16/09/2026 03:09:51 | B24: BMNR | C24: BitMine Immersion | P24: BMNR,Preço: 23.60,Dist MM20: -1.04%,Momentum: -1.22,RSI: 53.46,ADX: 44.08,ATR: 1.59,RVOL: 1.08,Estado: Alerta Iminente,Entrada: 23.28,Stop: 21.37,Take-Profit: 26.14,Break-Even: 24.71,Qtd: 26.21,Trailing: 21.37,Data: 16/09/2026 02:52:36 | Q24: 23.59 | R24: - | S24: - | T24: - | U24: Ignorado - S/ Quebra de Fecho | V24: BMNR,Máximo 15h30: 23.59,Estado: Ignorado - S/ Quebra de Fecho,Data: 16/09/2026 15:30:15 | W24: WIN | X24: 23.4 | Y24: 21.37 | Z24: 26.04 | AA24: 26 | AC24: =(Z24-X24) * AA24 -> 68.64
A25: 16/09/2026 03:09:51 | B25: ADP | C25: Automatic Data Processing | P25: ADP,Preço: 276.53,Dist MM20: -0.52%,Momentum: -6.25,RSI: 53.85,ADX: 26.79,ATR: 4.62,RVOL: 1.06,Estado: Alerta Iminente,Entrada: 275.61,Stop: 270.07,Take-Profit: 283.93,Break-Even: 279.77,Qtd: 9.02,Trailing: 270.07,Data: 16/09/2026 02:05:27 | Q25: 277.3 | R25: 272.68 | S25: 268.06 | T25: 279.61 | U25: Forca Consolidada | V25: ADP (INTRADAY),Máximo 15h30: 277.30,Estado: Forca Consolidada,Entrada: 272.68,Stop: 268.06,Take-Profit: 279.61,Data: 16/09/2026 15:30:15 | W25: LOSS | X25: 274.99 | Y25: 270.07 | Z25: 270 | AA25: 9 | AC25: =(Z25-X25) * AA25 -> -44.91
A26: 16/09/2026 03:09:51 | B26: QLYS | C26: Quakys | P26: QLYS,Preço: 185.37,Dist MM20: 4.84%,Momentum: 9.43,RSI: 57.97,ADX: 23.00,ATR: 9.96,RVOL: 1.77,Estado: Aguardar Recuo,Entrada: 181.39,Stop: 171.43,Take-Profit: 201.31,Break-Even: 191.35,Qtd: 5.02,Trailing: 171.43,Data: 16/09/2026 03:11:58 | Q26: 175.16 | R26: 165.94 | S26: 156.72 | T26: 179.77 | U26: Forca Consolidada | V26: QLYS (INTRADAY),Máximo 15h30: 175.16,Estado: Forca Consolidada,Entrada: 165.94,Stop: 156.72,Take-Profit: 179.77,Data: 15/09/2026 15:30:36 | W26: WIN | X26: 180.97 | Y26: 171.43 | Z26: 181.61 | AA26: 5 | AC26: =(Z26-X26) * AA26 -> 3.2
A27: 15/09/2026 03:09:52 | B27: ADSK | C27: Autodesk | P27: ADSK,Preço: 228.93,Dist MM20: -4.84%,Momentum: -25.49,RSI: 46.86,ADX: 24.86,ATR: 9.29,RVOL: 1.27,Estado: Aguardar Recuo,Entrada: 225.21,Stop: 215.92,Take-Profit: 243.79,Break-Even: 234.50,Qtd: 5.38,Trailing: 215.92,Data: 15/09/2026 06:04:38 | Q27: 229.3 | R27: 220.01 | S27: 210.72 | T27: 233.95 | U27: Forca Consolidada | V27: ADSK (INTRADAY),Máximo 15h30: 229.30,Estado: Forca Consolidada,Entrada: 220.01,Stop: 210.72,Take-Profit: 233.95,Data: 15/09/2026 15:30:37 | W27: LOSS | X27: 225.12 | Y27: 215.92 | Z27: 216.01 | AA27: 5.3 | AC27: =(Z27-X27) * AA27 -> -48.283
A28: 11/09/2026 03:09:53 | B28: UBER | C28: Uber | P28: UBER,Preço: 72.56,Dist MM20: -4.94%,Momentum: -5.99,RSI: 43.39,ADX: 15.29,ATR: 2.42,RVOL: 2.16,Estado: Aguardar Recuo,Entrada: 71.59,Stop: 69.17,Take-Profit: 76.43,Break-Even: 74.01,Qtd: 20.66,Trailing: 69.17,Data: 11/09/2026 02:38:40 | W28: LOSS | X28: 71.59 | Y28: 69.17 | Z28: 69.18 | AA28: 20.66 | AC28: =(Z28-X28) * AA28 -> -49.7906
A29: 04/09/2026 03:09:53 | B29: ADP | C29: Automatic Data Processing | D29: 283.53 | O29: TRUE | P29: ADP,Preço: 283.53,Dist MM20: 1.97%,Momentum: 10.57,RSI: 61.89,ADX: 38.04,ATR: 4.93,RVOL: 1.15,Estado: Forca Consolidada,Entrada: 282.54,Stop: 276.62,Take-Profit: 291.41,Break-Even: 286.98,Qtd: 8.45,Trailing: 276.62,Data: 04/09/2026 03:09:49 | Q29: 280.67 | R29: - | S29: - | T29: - | U29: Ignorado - S/ Quebra de Fecho | V29: ADP,Máximo 15h30: 280.67,Estado: Ignorado - S/ Quebra de Fecho,Data: 04/09/2026 15:31:08 | W29: LOSS | X29: 282.24 | Y29: 276.62 | Z29: 276.74 | AA29: 8.45 | AC29: =(Z29-X29) * AA29 -> -46.475
A30: 03/09/2026 02:54:09 | B30: ABT | C30: Abbot Laboratories | D30: 110.47 | E30: 109 | F30: 112.2 | H30: 7.93 | I30: 0 | J30: 21.44 | K30: 3.13 | O30: TRUE | P30: ABT,Preço: 110.47,Dist MM20: -1.21%,Momentum: -0.80,RSI: 53.05,ADX: 30.59,ATR: 2.32,RVOL: 1.10,Estado: Forca Consolidada,Entrada: 110.01,Stop: 107.23,Take-Profit: 114.19,Break-Even: 112.10,Qtd: 17.96,Trailing: 107.23,Data: 03/09/2026 02:54:08 | Q30: 111.99 | R30: 109.67 | S30: 107.35 | T30: 113.15 | U30: Forca Consolidada | V30: ABT (INTRADAY),Máximo 15h30: 111.99,Estado: Forca Consolidada,Entrada: 109.67,Stop: 107.35,Take-Profit: 113.15,Data: 03/09/2026 15:30:27 | AC30: =(Z30-X30) * AA30 -> 0
A31: 03/09/2026 02:52:23 | B31: PFE | C31: Pfizer | D31: 29.02 | E31: 28.71 | F31: 29.09 | O31: TRUE | P31: PFE,Preço: 29.02,Dist MM20: 5.22%,Momentum: 2.22,RSI: 71.44,ADX: 48.99,ATR: 0.54,RVOL: 1.06,Estado: Forca Consolidada,Entrada: 28.91,Stop: 28.26,Take-Profit: 29.88,Break-Even: 29.39,Qtd: 77.16,Trailing: 28.26,Data: 03/09/2026 02:52:22 | Q31: 29.21 | R31: 28.67 | S31: 28.13 | T31: 29.48 | U31: Forca Consolidada | V31: PFE (INTRADAY),Máximo 15h30: 29.21,Estado: Forca Consolidada,Entrada: 28.67,Stop: 28.13,Take-Profit: 29.48,Data: 03/09/2026 15:30:27 | AC31: =(Z31-X31) * AA31 -> 0
A32: 02/09/2026 06:16:47 | B32: PFE | C32: Pfizer | D32: 28.55 | E32: 28.47 | F32: 29.09 | O32: TRUE | P32: PFE,Preço: 28.55,Dist MM20: 4.12%,Momentum: 2.24,RSI: 68.11,ADX: 47.81,ATR: 0.55,RVOL: 1.09,Estado: Forca Consolidada,Entrada: 28.44,Stop: 27.78,Take-Profit: 29.43,Break-Even: 28.94,Qtd: 75.76,Trailing: 27.78,Data: 02/09/2026 06:16:46 | Q32: 29.09 | R32: 28.54 | S32: 27.99 | T32: 29.36 | U32: Forca Consolidada | V32: PFE (INTRADAY),Máximo 15h30: 29.09,Estado: Forca Consolidada,Entrada: 28.54,Stop: 27.99,Take-Profit: 29.36,Data: 02/09/2026 15:30:51 | W32: FUGIU | AC32: =(Z32-X32) * AA32 -> 0
A33: 02/09/2026 05:58:45 | B33: CVX | C33: Chevron | D33: 211.05 | O33: TRUE | P33: CVX,Preço: 211.05,Dist MM20: 5.65%,Momentum: 14.45,RSI: 70.80,ADX: 26.70,ATR: 3.38,RVOL: 1.08,Estado: Forca Consolidada,Entrada: 210.37,Stop: 206.31,Take-Profit: 216.45,Break-Even: 213.41,Qtd: 12.33,Trailing: 206.31,Data: 02/09/2026 05:58:44 | Q33: 212.72 | R33: 209.34 | S33: 205.96 | T33: 214.41 | U33: Forca Consolidada | V33: CVX (INTRADAY),Máximo 15h30: 212.72,Estado: Forca Consolidada,Entrada: 209.34,Stop: 205.96,Take-Profit: 214.41,Data: 02/09/2026 15:30:52 | W33: FUGIU | AC33: =(Z33-X33) * AA33 -> 0
A34: 01/09/2026 05:10:37 | B34: BMNR | C34: BitMine Immersion | D34: 25.32 | G34: ACTIVA | O34: TRUE | P34: BMNR,Preço: 25.32,Dist MM20: 22.21%,Momentum: 7.23,RSI: 71.03,ADX: 41.44,ATR: 1.39,RVOL: 1.03,Estado: Forca Consolidada,Entrada: 25.04,Stop: 23.37,Take-Profit: 27.54,Break-Even: 26.29,Qtd: 29.98,Trailing: 23.16,Data: 01/09/2026 05:10:36 | Q34: 24.58 | R34: - | S34: - | T34: - | U34: Ignorado - S/ Quebra de Fecho | V34: BMNR,Máximo 15h30: 24.58,Estado: Ignorado - S/ Quebra de Fecho,Data: 01/09/2026 15:30:27 | AC34: =(Z34-X34) * AA34 -> 0
A35: 01/09/2026 03:52:05 | B35: PFE | C35: Pfizer | D35: 28.46 | E35: 27.64 | F35: 28.7 | O35: TRUE | P35: PFE,Preço: 28.46,Dist MM20: 4.39%,Momentum: 1.84,RSI: 67.44,ADX: 46.55,ATR: 0.52,RVOL: 1.19,Estado: Forca Consolidada,Entrada: 28.36,Stop: 27.74,Take-Profit: 29.30,Break-Even: 28.83,Qtd: 80.13,Trailing: 27.74,Data: 01/09/2026 03:52:04 | Q35: 29.09 | R35: 28.57 | S35: 28.05 | T35: 29.35 | U35: Forca Consolidada | V35: PFE (INTRADAY),Máximo 15h30: 29.09,Estado: Forca Consolidada,Entrada: 28.57,Stop: 28.05,Take-Profit: 29.35,Data: 01/09/2026 15:30:27 | AC35: =(Z35-X35) * AA35 -> 0
A36: 01/09/2026 03:34:28 | B36: CRM | C36: Salesforce US | D36: 257.54 | E36: 254.39 | F36: 262.28 | G36: ACTIVA | O36: TRUE | P36: CRM,Preço: 257.54,Dist MM20: 24.32%,Momentum: 60.07,RSI: 81.12,ADX: 30.57,ATR: 9.09,RVOL: 1.34,Estado: Forca Consolidada,Entrada: 255.72,Stop: 244.81,Take-Profit: 272.08,Break-Even: 263.90,Qtd: 4.58,Trailing: 240.36,Data: 01/09/2026 03:34:28 | Q36: 260.89 | R36: 251.8 | S36: 242.71 | T36: 265.44 | U36: Forca Consolidada | V36: CRM (INTRADAY),Máximo 15h30: 260.89,Estado: Forca Consolidada,Entrada: 251.80,Stop: 242.71,Take-Profit: 265.44,Data: 01/09/2026 15:30:27 | AC36: =(Z36-X36) * AA36 -> 0
A37: 01/09/2026 02:19:17 | B37: ADBE | C37: Adobe Inc US | D37: 292.79 | E37: 286.26 | F37: 294.13 | O37: TRUE | P37: ADBE,Preço: 292.79,Dist MM20: 8.31%,Momentum: 29.08,RSI: 69.32,ADX: 25.96,ATR: 9.40,RVOL: 1.19,Estado: Forca Consolidada,Entrada: 290.91,Stop: 279.63,Take-Profit: 307.83,Break-Even: 299.37,Qtd: 4.43,Trailing: 279.63,Data: 01/09/2026 02:19:17 | Q37: 294.3 | R37: 284.9 | S37: 275.5 | T37: 299 | U37: Forca Consolidada | V37: ADBE (INTRADAY),Máximo 15h30: 294.30,Estado: Forca Consolidada,Entrada: 284.90,Stop: 275.50,Take-Profit: 299.00,Data: 01/09/2026 15:30:28 | W37: LOSS | X37: 290.88 | Y37: 279.63 | Z37: 279.6 | AA37: 4.43 | AC37: =(Z37-X37) * AA37 -> -49.9704
A38: 31/08/2026 02:38:20 | B38: TYL | C38: Tyler Tec | D38: 377.94 | E38: 369.43 | F38: 379.44 | H38: 13.08 | I38: 48.27 | J38: 44.69 | K38: 17.04 | L38: S1 Up | M38: 352.49 | N38: 46079.724 | O38: TRUE | P38: TYL,Preço: 377.94,Dist MM20: 13.40%,Momentum: 59.31,RSI: 72.72,ADX: 28.91,ATR: 12.37,RVOL: 1.46,Estado: Forca Consolidada,Entrada: 375.47,Stop: 360.63,Take-Profit: 397.74,Break-Even: 386.61,Qtd: 3.37,Trailing: 360.63,Data: 31/08/2026 02:38:19 | Q38: 380.12 | R38: 367.75 | S38: 355.38 | T38: 386.3 | U38: Forca Consolidada | V38: TYL (INTRADAY),Máximo 15h30: 380.12,Estado: Forca Consolidada,Entrada: 367.75,Stop: 355.38,Take-Profit: 386.30,Data: 31/08/2026 15:30:35 | AC38: =(Z38-X38) * AA38 -> 0
A39: 31/08/2026 02:24:40 | B39: CRM | C39: Salesforce US | D39: 256 | E39: 249 | F39: 263.53 | G39: ACTIVA | O39: TRUE | P39: CRM,Preço: 256.00,Dist MM20: 25.75%,Momentum: 58.49,RSI: 80.79,ADX: 28.23,ATR: 8.80,RVOL: 2.25,Estado: Forca Consolidada,Entrada: 254.24,Stop: 243.68,Take-Profit: 270.08,Break-Even: 262.16,Qtd: 4.73,Trailing: 240.36,Data: 31/08/2026 02:24:40 | Q39: 260.37 | R39: 251.57 | S39: 242.77 | T39: 264.77 | U39: Forca Consolidada | V39: CRM (INTRADAY),Máximo 15h30: 260.37,Estado: Forca Consolidada,Entrada: 251.57,Stop: 242.77,Take-Profit: 264.77,Data: 31/08/2026 15:30:35 | AC39: =(Z39-X39) * AA39 -> 0
A40: 31/08/2026 02:20:55 | B40: MSFT | C40: Microsoft | D40: 513.53 | E40: 504.87 | F40: 517.78 | O40: TRUE | P40: MSFT,Preço: 513.53,Dist MM20: 4.09%,Momentum: 7.47,RSI: 73.07,ADX: 36.73,ATR: 9.31,RVOL: 1.02,Estado: Forca Consolidada,Entrada: 511.67,Stop: 500.50,Take-Profit: 528.43,Break-Even: 520.05,Qtd: 4.48,Trailing: 500.50,Data: 31/08/2026 02:20:54 | Q40: 511.68 | R40: - | S40: - | T40: - | U40: Ignorado - S/ Quebra de Fecho | V40: MSFT,Máximo 15h30: 511.68,Estado: Ignorado - S/ Quebra de Fecho,Data: 31/08/2026 15:30:36 | W40: LOSS | X40: 509.79 | Y40: 500.5 | Z40: 498 | AA40: 4.48 | AB40: =IF(OR(W40="WIN", W40="LOSS"), (Z40-X40)/(X40-Y40), "") -> -1.2691066 | AC40: =(Z40-X40) * AA40 -> -52.8192
A41: 31/08/2026 02:04:25 | B41: ANF | C41: Abercrombie & Fitch | D41: 148.42 | E41: 145.04 | F41: 150.53 | M41: 90.18 | N41: 45805.765 | O41: TRUE | P41: ANF,Preço: 148.42,Dist MM20: 28.59%,Momentum: 29.89,RSI: 77.72,ADX: 32.37,ATR: 6.57,RVOL: 1.09,Estado: Forca Consolidada,Entrada: 147.11,Stop: 139.23,Take-Profit: 158.94,Break-Even: 153.03,Qtd: 6.34,Trailing: 139.23,Data: 31/08/2026 02:04:24 | Q41: 148.74 | R41: 142.17 | S41: 135.6 | T41: 152.02 | U41: Forca Consolidada | V41: ANF (INTRADAY),Máximo 15h30: 148.74,Estado: Forca Consolidada,Entrada: 142.17,Stop: 135.60,Take-Profit: 152.02,Data: 31/08/2026 15:30:36 | AB41: =IF(OR(W41="WIN", W41="LOSS"), (Z41-X41)/(X41-Y41), "") | AC41: =(Z41-X41) * AA41 -> 0
A42: 28/08/2026 02:45:35 | B42: BLK | C42: Alerta Iminente | D42: RVOL: 1.27 | E42: Entrada: 1163.84 | F42: Stop: 1141.44 | G42: Take-Profit: 1197.45 | H42: Qtd: 2.23 | I42: Dist MM20: 1.56% | P42: BLK,Preço: 1167.57,Dist MM20: 1.56%,Momentum: 31.18,RSI: 61.00,ADX: 31.27,ATR: 18.67,RVOL: 1.27,Estado: Alerta Iminente,Entrada: 1163.84,Stop: 1141.44,Take-Profit: 1197.45,Break-Even: 1180.64,Qtd: 2.23,Trailing: 1141.44,Data: 28/08/2026 02:45:35 | Q42: 1182.5 | R42: 1163.83 | S42: 1145.16 | T42: 1191.84 | U42: Forca Consolidada | V42: BLK (INTRADAY),Máximo 15h30: 1182.50,Estado: Forca Consolidada,Entrada: 1163.83,Stop: 1145.16,Take-Profit: 1191.84,Data: 28/08/2026 15:30:19 | AB42: =IF(OR(W42="WIN", W42="LOSS"), (Z42-X42)/(X42-Y42), "") | AC42: =(Z42-X42) * AA42 -> 0
A43: 28/08/2026 02:44:49 | B43: ADSK | C43: AutoDesk | D43: 270.58 | E43: #N/A | F43: #N/A | O43: TRUE | P43: ADSK,Preço: 270.58,Dist MM20: 8.67%,Momentum: 21.50,RSI: 69.89,ADX: 25.41,ATR: 8.87,RVOL: 2.12,Estado: Forca Consolidada,Entrada: 268.81,Stop: 258.17,Take-Profit: 284.78,Break-Even: 276.79,Qtd: 4.70,Trailing: 258.17,Data: 28/08/2026 02:44:49 | Q43: 267 | R43: - | S43: - | T43: - | U43: Ignorado - S/ Quebra de Fecho | V43: ADSK,Máximo 15h30: 267.00,Estado: Ignorado - S/ Quebra de Fecho,Data: 28/08/2026 15:30:23 | AB43: =IF(OR(W43="WIN", W43="LOSS"), (Z43-X43)/(X43-Y43), "") | AC43: =(Z43-X43) * AA43 -> 0
A44: 28/08/2026 02:38:55 | B44: TYL | C44: Tyler Tec | D44: 369.88 | E44: 356.83 | F44: 373.03 | H44: 13.08 | I44: 48.27 | J44: 44.69 | K44: 17.04 | L44: S1 Up | M44: 352.49 | N44: 46079.724 | O44: TRUE | P44: TYL,Preço: 369.88,Dist MM20: 12.13%,Momentum: 57.43,RSI: 70.40,ADX: 27.49,ATR: 12.59,RVOL: 1.67,Estado: Forca Consolidada,Entrada: 367.36,Stop: 352.25,Take-Profit: 390.02,Break-Even: 378.69,Qtd: 3.31,Trailing: 352.25,Data: 28/08/2026 02:38:55 | Q44: 375.68 | R44: 363.09 | S44: 350.5 | T44: 381.97 | U44: Forca Consolidada | V44: TYL (INTRADAY),Máximo 15h30: 375.68,Estado: Forca Consolidada,Entrada: 363.09,Stop: 350.50,Take-Profit: 381.97,Data: 28/08/2026 15:30:27 | AB44: =IF(OR(W44="WIN", W44="LOSS"), (Z44-X44)/(X44-Y44), "") | AC44: =(Z44-X44) * AA44 -> 0
A45: 28/08/2026 02:36:46 | B45: TEAM | C45: Atlassian | D45: 185.62 | E45: 168.73 | F45: 185.73 | M45: 315.51 | N45: 45707.373 | O45: TRUE | P45: TEAM,Preço: 185.62,Dist MM20: 23.29%,Momentum: 36.55,RSI: 77.75,ADX: 49.70,ATR: 8.71,RVOL: 1.12,Estado: Forca Consolidada,Entrada: 183.88,Stop: 173.43,Take-Profit: 199.56,Break-Even: 191.72,Qtd: 4.78,Trailing: 173.43,Data: 28/08/2026 02:36:45 | Q45: 193.4 | R45: 184.69 | S45: 175.98 | T45: 197.75 | U45: Forca Consolidada | V45: TEAM (INTRADAY),Máximo 15h30: 193.40,Estado: Forca Consolidada,Entrada: 184.69,Stop: 175.98,Take-Profit: 197.75,Data: 28/08/2026 15:30:28 | AB45: =IF(OR(W45="WIN", W45="LOSS"), (Z45-X45)/(X45-Y45), "") | AC45: =(Z45-X45) * AA45 -> 0
A46: 28/08/2026 02:34:18 | B46: SAP | C46: SAP | D46: 189.88 | E46: 181.14 | F46: 190.8 | H46: -5 | I46: 58.72 | J46: 39.72 | K46: 4.63 | M46: 238.78 | N46: 45770.367 | O46: TRUE | P46: SAP,Preço: 221.17,Dist MM20: 6.60%,Momentum: 15.01,RSI: 71.12,ADX: 41.88,ATR: 4.85,RVOL: 1.29,Estado: Forca Consolidada,Entrada: 220.20,Stop: 214.38,Take-Profit: 228.93,Break-Even: 224.56,Qtd: 8.59,Trailing: 214.38,Data: 28/08/2026 02:34:18 | Q46: 222.32 | R46: 217.47 | S46: 212.62 | T46: 224.75 | U46: Forca Consolidada | V46: SAP (INTRADAY),Máximo 15h30: 222.32,Estado: Forca Consolidada,Entrada: 217.47,Stop: 212.62,Take-Profit: 224.75,Data: 28/08/2026 15:30:28 | W46: LOSS | X46: 219.91 | Y46: 214.38 | Z46: 214.38 | AA46: 8.59 | AB46: =IF(OR(W46="WIN", W46="LOSS"), (Z46-X46)/(X46-Y46), "") -> -1 | AC46: =(Z46-X46) * AA46 -> -47.5027
A47: 28/08/2026 02:33:06 | B47: BMNR | C47: BitMine Immersion | D47: 25.63 | G47: ACTIVA | O47: TRUE | P47: BMNR,Preço: 25.63,Dist MM20: 28.17%,Momentum: 6.81,RSI: 79.80,ADX: 39.67,ATR: 1.24,RVOL: 1.47,Estado: Forca Consolidada,Entrada: 25.38,Stop: 23.89,Take-Profit: 27.61,Break-Even: 26.49,Qtd: 33.60,Trailing: 23.16,Data: 28/08/2026 02:33:06 | Q47: 25.68 | R47: 24.44 | S47: 23.2 | T47: 26.3 | U47: Forca Consolidada | V47: BMNR (INTRADAY),Máximo 15h30: 25.68,Estado: Forca Consolidada,Entrada: 24.44,Stop: 23.20,Take-Profit: 26.30,Data: 28/08/2026 15:30:29 | AB47: =IF(OR(W47="WIN", W47="LOSS"), (Z47-X47)/(X47-Y47), "") | AC47: =(Z47-X47) * AA47 -> 0
A48: 28/08/2026 02:32:55 | B48: CRM | C48: Salesforce US | D48: 252.05 | E48: 230.05 | F48: 254.48 | G48: ACTIVA | O48: TRUE | P48: CRM,Preço: 252.05,Dist MM20: 26.04%,Momentum: 59.31,RSI: 79.97,ADX: 25.72,ATR: 8.35,RVOL: 3.94,Estado: Forca Consolidada,Entrada: 250.38,Stop: 240.36,Take-Profit: 265.41,Break-Even: 257.89,Qtd: 4.99,Trailing: 240.36,Data: 28/08/2026 02:32:54 | Q48: 261.5 | R48: 253.15 | S48: 244.8 | T48: 265.68 | U48: Forca Consolidada | V48: CRM (INTRADAY),Máximo 15h30: 261.50,Estado: Forca Consolidada,Entrada: 253.15,Stop: 244.80,Take-Profit: 265.68,Data: 28/08/2026 15:30:29 | W48: LOSS | X48: 314.24 | Y48: 246.21 | Z48: 246.15 | AA48: 0.856 | AB48: =IF(OR(W48="WIN", W48="LOSS"), (Z48-X48)/(X48-Y48), "") -> -1.000882 | AC48: =(Z48-X48) * AA48 -> -58.28504
A49: 28/08/2026 02:25:01 | B49: QLYS | C49: Qualys US | D49: 188.59 | E49: 180 | F49: 190.99 | M49: 146.06 | N49: 45706.703 | O49: TRUE | P49: QLYS,Preço: 188.59,Dist MM20: 4.94%,Momentum: 5.11,RSI: 64.18,ADX: 36.32,ATR: 7.85,RVOL: 1.29,Estado: Forca Consolidada,Entrada: 187.02,Stop: 177.60,Take-Profit: 201.15,Break-Even: 194.09,Qtd: 5.31,Trailing: 177.60,Data: 28/08/2026 02:25:00 | Q49: 187.5 | R49: - | S49: - | T49: - | U49: Ignorado - S/ Quebra de Fecho | V49: QLYS,Máximo 15h30: 187.50,Estado: Ignorado - S/ Quebra de Fecho,Data: 28/08/2026 15:30:30 | W49: LOSS | X49: 186.99 | Y49: 177.6 | Z49: 177.63 | AA49: 5.31 | AB49: =IF(OR(W49="WIN", W49="LOSS"), (Z49-X49)/(X49-Y49), "") -> -0.99680511 | AC49: =(Z49-X49) * AA49 -> -49.7016
A50: 28/08/2026 02:10:03 | B50: EL | C50: Essilor | D50: 157.5 | E50: 156.15 | F50: 159.65 | H50: 23.4 | I50: 82.38 | J50: 60.69 | K50: 5.4 | L50: R2 Down | M50: 292 | N50: 45706.405 | O50: TRUE | P50: EL,Preço: 106.21,Dist MM20: 15.61%,Momentum: 17.86,RSI: 77.58,ADX: 29.37,ATR: 2.88,RVOL: 1.25,Estado: Forca Consolidada,Entrada: 105.63,Stop: 102.17,Take-Profit: 110.81,Break-Even: 108.22,Qtd: 14.47,Trailing: 102.17,Data: 28/08/2026 02:10:02 | Q50: 107.43 | R50: 104.55 | S50: 101.67 | T50: 108.87 | U50: Forca Consolidada | V50: EL (INTRADAY),Máximo 15h30: 107.43,Estado: Forca Consolidada,Entrada: 104.55,Stop: 101.67,Take-Profit: 108.87,Data: 28/08/2026 15:30:32 | AB50: =IF(OR(W50="WIN", W50="LOSS"), (Z50-X50)/(X50-Y50), "") | AC50: =(Z50-X50) * AA50 -> 0
A51: 27/08/2026 02:49:17 | B51: DASH | C51: DoorDash | D51: 236.93 | E51: 232 | F51: 238.52 | G51: ACTIVA | O51: TRUE | P51: DASH,Preço: 236.93,Dist MM20: 10.31%,Momentum: 23.67,RSI: 77.05,ADX: 37.58,ATR: 8.11,RVOL: 1.09,Estado: Forca Consolidada,Entrada: 235.31,Stop: 225.58,Take-Profit: 249.91,Break-Even: 242.61,Qtd: 5.14,Trailing: 225.58,Data: 27/08/2026 02:49:17 | Q51: 235.94 | R51: - | S51: - | T51: - | U51: Ignorado - S/ Quebra de Fecho | V51: DASH,Máximo 15h30: 235.94,Estado: Ignorado - S/ Quebra de Fecho,Data: 27/08/2026 15:30:26 | AB51: =IF(OR(W51="WIN", W51="LOSS"), (Z51-X51)/(X51-Y51), "") | AC51: =(Z51-X51) * AA51 -> 0
A52: 27/08/2026 02:04:18 | B52: ANF | C52: Abercrombie & Fitch | D52: 147.75 | E52: 130.24 | F52: 154.58 | M52: 90.18 | N52: 45805.765 | O52: TRUE | P52: ANF,Preço: 147.75,Dist MM20: 33.46%,Momentum: 37.27,RSI: 79.06,ADX: 27.73,ATR: 6.21,RVOL: 9.23,Estado: Forca Consolidada,Entrada: 146.51,Stop: 139.06,Take-Profit: 157.69,Break-Even: 152.10,Qtd: 6.71,Trailing: 139.06,Data: 27/08/2026 02:04:17 | Q52: 150.5 | R52: 144.29 | S52: 138.08 | T52: 153.6 | U52: Forca Consolidada | V52: ANF (INTRADAY),Máximo 15h30: 150.50,Estado: Forca Consolidada,Entrada: 144.29,Stop: 138.08,Take-Profit: 153.60,Data: 27/08/2026 15:30:27 | AB52: =IF(OR(W52="WIN", W52="LOSS"), (Z52-X52)/(X52-Y52), "") | AC52: =(Z52-X52) * AA52 -> 0
A53: 26/08/2026 02:04:27 | B53: ANF | C53: Alerta Iminente | D53: RVOL: 2.05 | E53: Entrada: 107.96 | F53: Stop: 102.30 | G53: Take-Profit: 116.46 | H53: Qtd: 8.83 | I53: Dist MM20: 0.42% | P53: ANF,Preço: 108.90,Dist MM20: 0.42%,Momentum: -0.55,RSI: 55.69,ADX: 25.14,ATR: 4.72,RVOL: 2.05,Estado: Alerta Iminente,Entrada: 107.96,Stop: 102.30,Take-Profit: 116.46,Break-Even: 112.21,Qtd: 8.83,Trailing: 102.30,Data: 26/08/2026 02:04:27 | W53: FUGIU | AB53: =IF(OR(W53="WIN", W53="LOSS"), (Z53-X53)/(X53-Y53), "") | AC53: =(Z53-X53) * AA53 -> 0
A54: 26/08/2026 06:23:08 | B54: ARES | C54: Ares Management | D54: 142.76 | E54: 137.12 | F54: 143.19 | O54: TRUE | P54: ARES,Preço: 142.76,Dist MM20: 2.75%,Momentum: 2.99,RSI: 59.11,ADX: 32.02,ATR: 4.67,RVOL: 1.19,Estado: Forca Consolidada,Entrada: 141.83,Stop: 136.23,Take-Profit: 150.24,Break-Even: 146.04,Qtd: 8.92,Trailing: 136.23,Data: 26/08/2026 06:23:07 | Q54: 1 | W54: FUGIU | AB54: =IF(OR(W54="WIN", W54="LOSS"), (Z54-X54)/(X54-Y54), "") | AC54: =(Z54-X54) * AA54 -> 0
A55: 26/08/2026 06:21:58 | B55: TEM | C55: Tempus AI US | D55: 68.73 | E55: 63.61 | F55: 70.79 | H55: 24.65 | I55: 73.45 | J55: 44.84 | K55: 7.18 | L55: R2 Up | M55: 72.55 | N55: 45973.4 | O55: TRUE | P55: TEM,Preço: 68.73,Dist MM20: 27.76%,Momentum: 22.03,RSI: 66.09,ADX: 30.66,ATR: 4.45,RVOL: 1.21,Estado: Forca Consolidada,Entrada: 67.84,Stop: 62.50,Take-Profit: 75.85,Break-Even: 71.84,Qtd: 9.36,Trailing: 62.50,Data: 26/08/2026 06:21:58 | Q55: 1 | W55: LOSS | X55: 67.5 | Y55: 62.5 | Z55: 62.44 | AA55: 9.36 | AB55: =IF(OR(W55="WIN", W55="LOSS"), (Z55-X55)/(X55-Y55), "") -> -1.012 | AC55: =(Z55-X55) * AA55 -> -47.3616
A56: 26/08/2026 06:12:07 | B56: BMNR | C56: BitMine Immersion | D56: 24.82 | G56: ACTIVA | O56: TRUE | P56: BMNR,Preço: 24.82,Dist MM20: 29.24%,Momentum: 6.39,RSI: 78.06,ADX: 34.42,ATR: 1.18,RVOL: 1.65,Estado: Forca Consolidada,Entrada: 24.58,Stop: 23.16,Take-Profit: 26.70,Break-Even: 25.64,Qtd: 35.31,Trailing: 23.16,Data: 26/08/2026 06:12:07 | Q56: 4 | AB56: =IF(OR(W56="WIN", W56="LOSS"), (Z56-X56)/(X56-Y56), "") | AC56: =(Z56-X56) * AA56 -> 0
A57: 26/08/2026 02:21:32 | B57: MRNA | C57: Moderna | D57: 158.83 | E57: 141.21 | F57: 161.37 | H57: 5.14 | I57: 67.62 | J57: 23.09 | K57: 1.35 | L57: R1 Up | M57: 30.54 | N57: 45841.419 | O57: TRUE | P57: MRNA,Preço: 158.83,Dist MM20: 93.97%,Momentum: 102.58,RSI: 72.50,ADX: 37.21,ATR: 13.03,RVOL: 1.78,Estado: Forca Consolidada,Entrada: 156.22,Stop: 140.58,Take-Profit: 179.67,Break-Even: 167.94,Qtd: 3.20,Trailing: 140.58,Data: 26/08/2026 02:21:31 | Q57: 1 | AB57: =IF(OR(W57="WIN", W57="LOSS"), (Z57-X57)/(X57-Y57), "") | AC57: =(Z57-X57) * AA57 -> 0
A58: 26/08/2026 02:20:04 | B58: OR | C58: Loreal | D58: 388.5 | E58: 386.6 | F58: 393 | M58: 335.95 | O58: TRUE | P58: OR,Preço: 38.92,Dist MM20: 17.19%,Momentum: 6.68,RSI: 77.42,ADX: 31.46,ATR: 1.08,RVOL: 1.08,Estado: Forca Consolidada,Entrada: 38.70,Stop: 37.40,Take-Profit: 40.64,Break-Even: 39.67,Qtd: 38.58,Trailing: 37.40,Data: 26/08/2026 02:20:04 | Q58: 5 | AB58: =IF(OR(W58="WIN", W58="LOSS"), (Z58-X58)/(X58-Y58), "") | AC58: =(Z58-X58) * AA58 -> 0
A59: 25/08/2026 04:53:29 | B59: BMNR | C59: BitMine Immersion | D59: 24.14 | O59: TRUE | P59: BMNR,Preço: 24.14,Dist MM20: 28.12%,Momentum: 6.04,RSI: 76.59,ADX: 31.68,ATR: 1.10,RVOL: 1.86,Estado: Forca Consolidada,Entrada: 23.92,Stop: 22.60,Take-Profit: 25.90,Break-Even: 24.91,Qtd: 113.64,Trailing: 22.60,Data: 25/08/2026 04:53:28 | Q59: 25.35 | R59: 24.25 | S59: 23.15 | T59: 25.9 | U59: Forca Consolidada | V59: BMNR (INTRADAY),Máximo 15h30: 25.35,Estado: Forca Consolidada,Entrada: 24.25,Stop: 23.15,Take-Profit: 25.90,Data: 25/08/2026 15:30:28 | W59: LOSS | X59: 41.01 | Y59: 23.16 | Z59: 23.16 | AA59: 18 | AB59: =IF(OR(W59="WIN", W59="LOSS"), (Z59-X59)/(X59-Y59), "") -> -1 | AC59: =(Z59-X59) * AA59 -> -321.3
A60: 25/08/2026 02:20:52 | B60: MA | C60: MasterCard US | D60: 599.86 | E60: 584.22 | F60: 599.99 | G60: W | M60: 588.03 | N60: 45912.101 | O60: TRUE | P60: MA,Preço: 599.86,Dist MM20: 5.12%,Momentum: 28.76,RSI: 73.33,ADX: 34.88,ATR: 9.94,RVOL: 1.00,Estado: Forca Consolidada,Entrada: 597.87,Stop: 585.94,Take-Profit: 615.76,Break-Even: 606.82,Qtd: 12.58,Trailing: 585.94,Data: 25/08/2026 02:20:51 | Q60: 601.18 | R60: 591.24 | S60: 581.3 | T60: 606.15 | U60: Forca Consolidada | V60: MA (INTRADAY),Máximo 15h30: 601.18,Estado: Forca Consolidada,Entrada: 591.24,Stop: 581.30,Take-Profit: 606.15,Data: 25/08/2026 15:30:29 | W60: LOSS | X60: 597.12 | Y60: 585.94 | Z60: 586.08 | AA60: 4 | AB60: =IF(OR(W60="WIN", W60="LOSS"), (Z60-X60)/(X60-Y60), "") -> -0.98747764 | AC60: =(Z60-X60) * AA60 -> -44.16
A61: 25/08/2026 02:20:14 | B61: OR | C61: Loreal | D61: 392.5 | E61: 387.2 | F61: 393.75 | M61: 335.95 | O61: TRUE | P61: OR,Preço: 37.49,Dist MM20: 14.52%,Momentum: 6.73,RSI: 74.05,ADX: 29.53,ATR: 0.99,RVOL: 2.25,Estado: Forca Consolidada,Entrada: 37.29,Stop: 36.10,Take-Profit: 39.07,Break-Even: 38.18,Qtd: 126.26,Trailing: 36.10,Data: 25/08/2026 02:20:13 | Q61: 38.34 | R61: 37.35 | S61: 36.36 | T61: 38.84 | U61: Forca Consolidada | V61: OR (INTRADAY),Máximo 15h30: 38.34,Estado: Forca Consolidada,Entrada: 37.35,Stop: 36.36,Take-Profit: 38.84,Data: 25/08/2026 15:30:29 | AB61: =IF(OR(W61="WIN", W61="LOSS"), (Z61-X61)/(X61-Y61), "") | AC61: =(Z61-X61) * AA61 -> 0
A62: 25/08/2026 02:04:29 | B62: ANF | C62: Abercrombie & Fitch | D62: 112.36 | E62: 109.83 | F62: 113.42 | M62: 90.18 | N62: 45805.765 | O62: TRUE | P62: ANF,Preço: 112.36,Dist MM20: 3.89%,Momentum: 2.16,RSI: 61.35,ADX: 26.07,ATR: 4.69,RVOL: 1.28,Estado: Forca Consolidada,Entrada: 111.42,Stop: 105.79,Take-Profit: 119.86,Break-Even: 115.64,Qtd: 26.65,Trailing: 105.79,Data: 25/08/2026 02:04:28 | Q62: 112.89 | R62: 108.2 | S62: 103.51 | T62: 115.23 | U62: Forca Consolidada | V62: ANF (INTRADAY),Máximo 15h30: 112.89,Estado: Forca Consolidada,Entrada: 108.20,Stop: 103.51,Take-Profit: 115.23,Data: 25/08/2026 15:30:30 | AB62: =IF(OR(W62="WIN", W62="LOSS"), (Z62-X62)/(X62-Y62), "") | AC62: =(Z62-X62) * AA62 -> 0
A63: 24/08/2026 02:49:19 | B63: ABT | C63: Abbot Laboratories | D63: 116.64 | E63: 113.45 | F63: 116.66 | H63: 7.93 | I63: 0 | J63: 21.44 | K63: 3.13 | O63: TRUE | P63: ABT,Preço: 116.64,Dist MM20: 6.76%,Momentum: 9.52,RSI: 77.80,ADX: 36.26,ATR: 2.17,RVOL: 1.16,Estado: Forca Consolidada,Entrada: 116.21,Stop: 113.61,Take-Profit: 120.12,Break-Even: 118.16,Qtd: 57.60,Trailing: 113.61,Data: 24/08/2026 02:49:18 | Q63: 117.34 | R63: 115.17 | S63: 113 | T63: 118.42 | U63: Forca Consolidada | V63: ABT (INTRADAY),Máximo 15h30: 117.34,Estado: Forca Consolidada,Entrada: 115.17,Stop: 113.00,Take-Profit: 118.42,Data: 24/08/2026 15:30:42 | W63: LOSS | X63: 116.1 | Y63: 113.61 | Z63: 112.67 | AA63: 28.8 | AB63: =IF(OR(W63="WIN", W63="LOSS"), (Z63-X63)/(X63-Y63), "") -> -1.37751 | AC63: =(Z63-X63) * AA63 -> -98.784
A64: 24/08/2026 02:46:52 | B64: ADP | C64: Abbot Laboratories | D64: 280.81 | O64: TRUE | P64: ADP,Preço: 280.81,Dist MM20: 3.73%,Momentum: 11.03,RSI: 65.52,ADX: 37.85,ATR: 5.90,RVOL: 1.05,Estado: Forca Consolidada,Entrada: 279.63,Stop: 272.55,Take-Profit: 290.25,Break-Even: 284.94,Qtd: 21.19,Trailing: 272.55,Data: 24/08/2026 02:46:51 | Q64: 285.59 | R64: 279.69 | S64: 273.79 | T64: 288.54 | U64: Forca Consolidada | V64: ADP (INTRADAY),Máximo 15h30: 285.59,Estado: Forca Consolidada,Entrada: 279.69,Stop: 273.79,Take-Profit: 288.54,Data: 24/08/2026 15:31:06 | AB64: =IF(OR(W64="WIN", W64="LOSS"), (Z64-X64)/(X64-Y64), "") | AC64: =(Z64-X64) * AA64 -> 0
A65: 24/08/2026 02:43:31 | B65: BMNR | C65: Abbot Laboratories | D65: 22.83 | O65: TRUE | P65: BMNR,Preço: 22.83,Dist MM20: 23.20%,Momentum: 5.41,RSI: 73.40,ADX: 28.94,ATR: 1.04,RVOL: 1.66,Estado: Forca Consolidada,Entrada: 22.62,Stop: 21.37,Take-Profit: 24.49,Break-Even: 23.55,Qtd: 120.19,Trailing: 21.37,Data: 24/08/2026 02:43:31 | Q65: 24.19 | R65: 23.15 | S65: 22.11 | T65: 24.71 | U65: Forca Consolidada | V65: BMNR (INTRADAY),Máximo 15h30: 24.19,Estado: Forca Consolidada,Entrada: 23.15,Stop: 22.11,Take-Profit: 24.71,Data: 24/08/2026 15:31:07 | AB65: =IF(OR(W65="WIN", W65="LOSS"), (Z65-X65)/(X65-Y65), "") | AC65: =(Z65-X65) * AA65 -> 0
A66: 24/08/2026 02:38:01 | B66: TEM | C66: Abbot Laboratories | D66: 72.69 | E66: 65.25 | F66: 72.96 | H66: 24.65 | I66: 73.45 | J66: 44.84 | K66: 7.18 | L66: R2 Up | M66: 72.55 | N66: 45973.4 | O66: TRUE | P66: TEM,Preço: 72.69,Dist MM20: 41.58%,Momentum: 26.64,RSI: 75.09,ADX: 27.36,ATR: 3.83,RVOL: 2.31,Estado: Forca Consolidada,Entrada: 71.92,Stop: 67.32,Take-Profit: 78.81,Break-Even: 75.37,Qtd: 32.64,Trailing: 67.32,Data: 24/08/2026 02:37:59 | Q66: 72.02 | R66: - | S66: - | T66: - | U66: Ignorado - S/ Quebra de Fecho | V66: TEM,Máximo 15h30: 72.02,Estado: Ignorado - S/ Quebra de Fecho,Data: 24/08/2026 15:31:08 | AB66: =IF(OR(W66="WIN", W66="LOSS"), (Z66-X66)/(X66-Y66), "") | AC66: =(Z66-X66) * AA66 -> 0
A67: 24/08/2026 02:21:52 | B67: MRNA | C67: Abbot Laboratories | D67: 145.13 | E67: 132.42 | F67: 159.47 | G67: SB | H67: 5.14 | I67: 67.62 | J67: 23.09 | K67: 1.35 | L67: R1 Up | M67: 30.54 | N67: 45841.419 | O67: TRUE | P67: MRNA,Preço: 145.13,Dist MM20: 99.99%,Momentum: 89.99,RSI: 71.60,ADX: 29.65,ATR: 10.94,RVOL: 3.63,Estado: Forca Consolidada,Entrada: 142.94,Stop: 129.81,Take-Profit: 162.63,Break-Even: 152.78,Qtd: 11.43,Trailing: 129.81,Data: 24/08/2026 02:21:49 | Q67: 145.49 | R67: 134.55 | S67: 123.61 | T67: 150.96 | U67: Forca Consolidada | V67: MRNA (INTRADAY),Máximo 15h30: 145.49,Estado: Forca Consolidada,Entrada: 134.55,Stop: 123.61,Take-Profit: 150.96,Data: 24/08/2026 15:31:08 | AB67: =IF(OR(W67="WIN", W67="LOSS"), (Z67-X67)/(X67-Y67), "") | AC67: =(Z67-X67) * AA67 -> 0
A68: 24/08/2026 02:19:49 | B68: OR | C68: Abbot Laboratories | D68: 386.6 | E68: 379.85 | F68: 387.4 | M68: 335.95 | O68: TRUE | P68: OR,Preço: 36.09,Dist MM20: 11.59%,Momentum: 5.66,RSI: 69.98,ADX: 27.84,ATR: 0.93,RVOL: 1.46,Estado: Forca Consolidada,Entrada: 35.90,Stop: 34.78,Take-Profit: 37.57,Break-Even: 36.73,Qtd: 134.41,Trailing: 34.78,Data: 24/08/2026 02:19:46 | Q68: 36.85 | R68: 35.92 | S68: 34.99 | T68: 37.32 | U68: Forca Consolidada | V68: OR (INTRADAY),Máximo 15h30: 36.85,Estado: Forca Consolidada,Entrada: 35.92,Stop: 34.99,Take-Profit: 37.32,Data: 24/08/2026 15:31:09 | AB68: =IF(OR(W68="WIN", W68="LOSS"), (Z68-X68)/(X68-Y68), "") | AC68: =(Z68-X68) * AA68 -> 0
A69: 24/08/2026 02:04:18 | B69: ANF | C69: Abbot Laboratories | D69: 109.01 | E69: 105.4 | F69: 109.53 | M69: 90.18 | N69: 45805.765 | O69: TRUE | P69: ANF,Preço: 109.01,Dist MM20: 1.40%,Momentum: 0.19,RSI: 57.46,ADX: 26.30,ATR: 4.72,RVOL: 1.00,Estado: Forca Consolidada,Entrada: 108.07,Stop: 102.41,Take-Profit: 116.57,Break-Even: 112.32,Qtd: 26.48,Trailing: 102.41,Data: 24/08/2026 02:04:17 | Q69: 113.42 | R69: 108.7 | S69: 103.98 | T69: 115.78 | U69: Forca Consolidada | V69: ANF (INTRADAY),Máximo 15h30: 113.42,Estado: Forca Consolidada,Entrada: 108.70,Stop: 103.98,Take-Profit: 115.78,Data: 24/08/2026 15:31:32 | AB69: =IF(OR(W69="WIN", W69="LOSS"), (Z69-X69)/(X69-Y69), "") | AC69: =(Z69-X69) * AA69 -> 0
A70: 21/08/2026 11:39:59 | B70: CVX | C70: Chevron | D70: 205.77 | O70: TRUE | P70: CVX,Preço: 205.77,Dist MM20: 5.39%,Momentum: 8.94,RSI: 69.81,ADX: 27.36,ATR: 3.71,RVOL: 1.01,Estado: Forca Consolidada,Entrada: 205.03,Stop: 200.58,Take-Profit: 211.71,Break-Even: 208.37,Qtd: 33.69,Trailing: 200.58,Data: 21/08/2026 11:39:59 | Q70: 207.82 | R70: 204.11 | S70: 200.4 | T70: 209.68 | U70: Forca Consolidada | V70: CVX (INTRADAY),Máximo 15h30: 207.82,Estado: Forca Consolidada,Entrada: 204.11,Stop: 200.40,Take-Profit: 209.68,Data: 21/08/2026 15:30:07 | AB70: =IF(OR(W70="WIN", W70="LOSS"), (Z70-X70)/(X70-Y70), "") | AC70: =(Z70-X70) * AA70 -> 0
A71: 21/08/2026 10:39:01 | B71: TEM | C71: Tempus AI US | D71: 66.65 | E71: 61.7 | F71: 68.96 | H71: 24.65 | I71: 73.45 | J71: 44.84 | K71: 7.18 | L71: R2 Up | M71: 72.55 | N71: 45973.4 | O71: TRUE | P71: TEM,Preço: 66.65,Dist MM20: 33.72%,Momentum: 22.78,RSI: 70.71,ADX: 25.09,ATR: 3.62,RVOL: 3.15,Estado: Forca Consolidada,Entrada: 65.93,Stop: 61.59,Take-Profit: 72.45,Break-Even: 69.19,Qtd: 34.53,Trailing: 61.59,Data: 21/08/2026 10:39:00 | Q71: 68.9 | R71: 65.28 | S71: 61.66 | T71: 70.71 | U71: Forca Consolidada | V71: TEM (INTRADAY),Máximo 15h30: 68.90,Estado: Forca Consolidada,Entrada: 65.28,Stop: 61.66,Take-Profit: 70.71,Data: 21/08/2026 15:30:07 | AB71: =IF(OR(W71="WIN", W71="LOSS"), (Z71-X71)/(X71-Y71), "") | AC71: =(Z71-X71) * AA71 -> 0
A72: 21/08/2026 05:55:02 | B72: BMNR | C72: BitMine Immersion | D72: 21.57 | O72: TRUE | P72: BMNR,Preço: 21.57,Dist MM20: 18.66%,Momentum: 4.29,RSI: 69.72,ADX: 26.49,ATR: 0.99,RVOL: 1.91,Estado: Forca Consolidada,Entrada: 21.37,Stop: 20.18,Take-Profit: 23.15,Break-Even: 22.26,Qtd: 126.26,Trailing: 20.18,Data: 21/08/2026 05:55:02 | Q72: 22.81 | R72: 21.82 | S72: 20.83 | T72: 23.3 | U72: Forca Consolidada | V72: BMNR (INTRADAY),Máximo 15h30: 22.81,Estado: Forca Consolidada,Entrada: 21.82,Stop: 20.83,Take-Profit: 23.30,Data: 21/08/2026 15:30:08 | AB72: =IF(OR(W72="WIN", W72="LOSS"), (Z72-X72)/(X72-Y72), "") | AC72: =(Z72-X72) * AA72 -> 0
A73: 21/08/2026 02:39:05 | B73: DASH | C73: DoorDash | D73: 222.36 | E73: 216.01 | F73: 224.04 | O73: TRUE | P73: DASH,Preço: 222.36,Dist MM20: 7.97%,Momentum: 26.20,RSI: 69.23,ADX: 31.71,ATR: 7.81,RVOL: 1.30,Estado: Forca Consolidada,Entrada: 220.80,Stop: 211.43,Take-Profit: 234.86,Break-Even: 227.83,Qtd: 16.01,Trailing: 211.43,Data: 21/08/2026 02:39:04 | Q73: 223.63 | R73: 215.81 | S73: 208 | T73: 227.53 | U73: Forca Consolidada | V73: DASH (INTRADAY),Máximo 15h30: 223.63,Estado: Forca Consolidada,Entrada: 215.81,Stop: 208.00,Take-Profit: 227.53,Data: 21/08/2026 15:30:08 | W73: WIN | X73: 220.8 | Y73: 232 | Z73: 232 | AA73: 16.01 | AB73: =IF(OR(W73="WIN", W73="LOSS"), (Z73-X73)/(X73-Y73), "") -> -1 | AC73: =(Z73-X73) * AA73 -> 179.312
A74: 21/08/2026 02:19:51 | B74: OR | C74: Loreal | D74: 385.8 | E74: 381.75 | F74: 386.15 | M74: 335.95 | O74: TRUE | P74: OR,Preço: 35.29,Dist MM20: 10.30%,Momentum: 5.53,RSI: 67.26,ADX: 26.63,ATR: 0.93,RVOL: 1.13,Estado: Forca Consolidada,Entrada: 35.10,Stop: 33.98,Take-Profit: 36.77,Break-Even: 35.94,Qtd: 134.41,Trailing: 33.98,Data: 21/08/2026 02:19:51 | Q74: 36.29 | R74: 35.36 | S74: 34.43 | T74: 36.76 | U74: Forca Consolidada | V74: OR (INTRADAY),Máximo 15h30: 36.29,Estado: Forca Consolidada,Entrada: 35.36,Stop: 34.43,Take-Profit: 36.76,Data: 21/08/2026 15:30:09 | AB74: =IF(OR(W74="WIN", W74="LOSS"), (Z74-X74)/(X74-Y74), "") | AC74: =(Z74-X74) * AA74 -> 0
A75: 21/08/2026 02:05:05 | B75: BABA | C75: Alibaba US | D75: 130.53 | E75: 121.88 | F75: 130.62 | G75: W | L75: R3 Down | M75: 117.11 | N75: 45856.305 | O75: TRUE | P75: BABA,Preço: 130.53,Dist MM20: 5.28%,Momentum: 8.28,RSI: 63.55,ADX: 27.79,ATR: 3.11,RVOL: 2.68,Estado: Forca Consolidada,Entrada: 129.91,Stop: 126.18,Take-Profit: 135.51,Break-Even: 132.71,Qtd: 40.19,Trailing: 126.18,Data: 21/08/2026 02:05:05 | Q75: 125.61 | R75: - | S75: - | T75: - | U75: Ignorado - S/ Quebra de Fecho | V75: BABA,Máximo 15h30: 125.61,Estado: Ignorado - S/ Quebra de Fecho,Data: 21/08/2026 15:30:13 | W75: LOSS | X75: 125.56 | Y75: 121.83 | Z75: 121.6 | AA75: 41.19 | AB75: =IF(OR(W75="WIN", W75="LOSS"), (Z75-X75)/(X75-Y75), "") -> -1.0616622 | AC75: =(Z75-X75) * AA75 -> -163.1124
A76: 20/08/2026 02:37:53 | B76: PFE | C76: Pfizer | D76: 28.24 | E76: 27.58 | F76: 28.44 | O76: TRUE | P76: PFE,Preço: 28.24,Dist MM20: 8.68%,Momentum: 3.33,RSI: 75.38,ADX: 33.92,ATR: 0.56,RVOL: 1.46,Estado: Forca Consolidada,Entrada: 28.13,Stop: 27.46,Take-Profit: 29.14,Break-Even: 28.63,Qtd: 148.81,Trailing: 27.46,Data: 20/08/2026 02:37:53 | Q76: 28.09 | R76: - | S76: - | T76: - | U76: Ignorado - S/ Quebra de Fecho | V76: PFE,Máximo 15h30: 28.09,Estado: Ignorado - S/ Quebra de Fecho,Data: 20/08/2026 15:30:36 | AB76: =IF(OR(W76="WIN", W76="LOSS"), (Z76-X76)/(X76-Y76), "") | AC76: =(Z76-X76) * AA76 -> 0
A77: 20/08/2026 02:19:50 | B77: OR | C77: Loreal | D77: 382.55 | E77: 373.65 | F77: 384.6 | M77: 335.95 | O77: TRUE | P77: OR,Preço: 34.90,Dist MM20: 10.15%,Momentum: 4.21,RSI: 65.85,ADX: 25.57,ATR: 0.90,RVOL: 1.56,Estado: Forca Consolidada,Entrada: 34.72,Stop: 33.64,Take-Profit: 36.34,Break-Even: 35.53,Qtd: 92.59,Trailing: 33.64,Data: 20/08/2026 02:19:49 | Q77: 35.48 | R77: 34.58 | S77: 33.68 | T77: 35.93 | U77: Forca Consolidada | V77: OR (INTRADAY),Máximo 15h30: 35.48,Estado: Forca Consolidada,Entrada: 34.58,Stop: 33.68,Take-Profit: 35.93,Data: 20/08/2026 15:30:36 | AB77: =IF(OR(W77="WIN", W77="LOSS"), (Z77-X77)/(X77-Y77), "") | AC77: =(Z77-X77) * AA77 -> 0
A78: 20/08/2026 02:05:01 | B78: BABA | C78: Alibaba US | D78: 128.9 | E78: 127.54 | F78: 129.5 | G78: W | L78: R3 Down | M78: 117.11 | N78: 45856.305 | O78: TRUE | P78: BABA,Preço: 128.90,Dist MM20: 4.66%,Momentum: 12.58,RSI: 61.58,ADX: 29.23,ATR: 2.73,RVOL: 1.22,Estado: Forca Consolidada,Entrada: 128.35,Stop: 125.07,Take-Profit: 133.26,Break-Even: 130.81,Qtd: 30.53,Trailing: 125.07,Data: 20/08/2026 02:05:00 | Q78: 126.92 | R78: - | S78: - | T78: - | U78: Ignorado - S/ Quebra de Fecho | V78: BABA,Máximo 15h30: 126.92,Estado: Ignorado - S/ Quebra de Fecho,Data: 20/08/2026 15:30:36 | AB78: =IF(OR(W78="WIN", W78="LOSS"), (Z78-X78)/(X78-Y78), "") | AC78: =(Z78-X78) * AA78 -> 0
A79: 19/08/2026 02:49:24 | B79: ADP | C79: Automatic Data Processing | D79: 269.31 | O79: TRUE | P79: ADP,Preço: 269.31,Dist MM20: 1.38%,Momentum: -4.06,RSI: 57.62,ADX: 37.39,ATR: 6.38,RVOL: 1.10,Estado: Forca Consolidada,Entrada: 268.03,Stop: 260.37,Take-Profit: 279.51,Break-Even: 273.77,Qtd: 13.06,Trailing: 260.37,Data: 19/08/2026 02:49:23 | Q79: 277.95 | R79: 271.57 | S79: 265.19 | T79: 281.14 | U79: Forca Consolidada | V79: ADP (INTRADAY),Máximo 15h30: 277.95,Estado: Forca Consolidada,Entrada: 271.57,Stop: 265.19,Take-Profit: 281.14,Data: 19/08/2026 15:30:08 | AB79: =IF(OR(W79="WIN", W79="LOSS"), (Z79-X79)/(X79-Y79), "") | AC79: =(Z79-X79) * AA79 -> 0
A80: 19/08/2026 02:39:47 | B80: DASH | C80: DoorDash | D80: 216.35 | E80: 212.66 | F80: 222.81 | O80: TRUE | P80: DASH,Preço: 216.35,Dist MM20: 7.53%,Momentum: 22.82,RSI: 65.45,ADX: 29.89,ATR: 7.79,RVOL: 1.29,Estado: Forca Consolidada,Entrada: 214.79,Stop: 205.44,Take-Profit: 228.81,Break-Even: 221.80,Qtd: 10.70,Trailing: 205.44,Data: 19/08/2026 02:39:47 | Q80: 220.7 | R80: 212.91 | S80: 205.12 | T80: 224.59 | U80: Forca Consolidada | V80: DASH (INTRADAY),Máximo 15h30: 220.70,Estado: Forca Consolidada,Entrada: 212.91,Stop: 205.12,Take-Profit: 224.59,Data: 19/08/2026 15:30:09 | AB80: =IF(OR(W80="WIN", W80="LOSS"), (Z80-X80)/(X80-Y80), "") | AC80: =(Z80-X80) * AA80 -> 0
A81: 19/08/2026 02:21:08 | B81: MA | C81: MasterCard US | D81: 574.31 | E81: 563.18 | F81: 578.5 | G81: W | M81: 588.03 | N81: 45912.101 | O81: TRUE | P81: MA,Preço: 574.31,Dist MM20: 2.20%,Momentum: 10.99,RSI: 62.70,ADX: 32.25,ATR: 10.21,RVOL: 1.29,Estado: Forca Consolidada,Entrada: 572.27,Stop: 560.02,Take-Profit: 590.65,Break-Even: 581.46,Qtd: 8.16,Trailing: 560.02,Data: 19/08/2026 02:21:07 | Q81: 582.86 | R81: 572.65 | S81: 562.44 | T81: 587.97 | U81: Forca Consolidada | V81: MA (INTRADAY),Máximo 15h30: 582.86,Estado: Forca Consolidada,Entrada: 572.65,Stop: 562.44,Take-Profit: 587.97,Data: 19/08/2026 15:30:09 | W81: LOSS | X81: 572.09 | Y81: 572.09 | Z81: 572.09 | AA81: 4.08 | AB81: =IF(OR(W81="WIN", W81="LOSS"), (Z81-X81)/(X81-Y81), "") -> #DIV/0! | AC81: =(Z81-X81) * AA81 -> 0
A82: 19/08/2026 02:05:16 | B82: BABA | C82: Alibaba US | D82: 128.15 | E82: 126.34 | F82: 128.79 | G82: W | L82: R3 Down | M82: 117.11 | N82: 45856.305 | O82: TRUE | P82: BABA,Preço: 128.15,Dist MM20: 4.58%,Momentum: 13.12,RSI: 60.66,ADX: 29.12,ATR: 2.83,RVOL: 1.25,Estado: Forca Consolidada,Entrada: 127.58,Stop: 124.18,Take-Profit: 132.67,Break-Even: 130.13,Qtd: 29.45,Trailing: 124.18,Data: 19/08/2026 02:05:14 | Q82: 128.76 | R82: 125.93 | S82: 123.1 | T82: 130.17 | U82: Forca Consolidada | V82: BABA (INTRADAY),Máximo 15h30: 128.76,Estado: Forca Consolidada,Entrada: 125.93,Stop: 123.10,Take-Profit: 130.17,Data: 19/08/2026 15:30:10 | W82: WIN | X82: 122.7 | Y82: 119.42 | Z82: 127.8 | AA82: 30.53 | AB82: =IF(OR(W82="WIN", W82="LOSS"), (Z82-X82)/(X82-Y82), "") -> 1.554878 | AC82: =(Z82-X82) * AA82 -> 155.703
A83: 14/08/2026 02:08:51 | B83: NET | C83: Cloudflare US | D83: 330.83 | E83: 313.02 | F83: 332.22 | H83: -11 | I83: 54.75 | J83: 29.18 | K83: 6.52 | L83: S1 Up | M83: 184.62 | N83: 45853.692 | O83: TRUE | P83: NET,Preço: 330.83,Dist MM20: 16.08%,Momentum: 68.68,RSI: 73.30,ADX: 30.83,ATR: 18.00,RVOL: 1.12,Estado: Forca Consolidada,Entrada: 327.23,Stop: 305.63,Take-Profit: 359.63,Break-Even: 343.43,Qtd: 4.63,Trailing: 305.63,Data: 14/08/2026 02:08:50 | Q83: 331.83 | R83: 313.83 | S83: 295.83 | T83: 340.83 | U83: Forca Consolidada | V83: NET (INTRADAY),Máximo 15h30: 331.83,Estado: Forca Consolidada,Entrada: 313.83,Stop: 295.83,Take-Profit: 340.83,Data: 14/08/2026 15:30:26 | AB83: =IF(OR(W83="WIN", W83="LOSS"), (Z83-X83)/(X83-Y83), "") | AC83: =(Z83-X83) * AA83 -> 0
A84: 13/08/2026 02:23:01 | B84: ORCL | C84: Oracle US | D84: 153.28 | E84: 147.89 | F84: 154.89 | H84: -16.41 | I84: 27.65 | J84: 36.4 | K84: 8.44 | M84: 181.52 | N84: 46219.377 | O84: TRUE | P84: ORCL,Preço: 153.28,Dist MM20: 15.80%,Momentum: 33.24,RSI: 59.56,ADX: 25.93,ATR: 6.98,RVOL: 1.26,Estado: Forca Consolidada,Entrada: 151.88,Stop: 143.50,Take-Profit: 164.44,Break-Even: 158.16,Qtd: 11.94,Trailing: 143.50,Data: 13/08/2026 02:23:00 | Q84: 159.25 | R84: 152.27 | S84: 145.29 | T84: 162.74 | U84: Forca Consolidada | V84: ORCL (INTRADAY),Máximo 15h30: 159.25,Estado: Forca Consolidada,Entrada: 152.27,Stop: 145.29,Take-Profit: 162.74,Data: 13/08/2026 15:30:50 | AB84: =IF(OR(W84="WIN", W84="LOSS"), (Z84-X84)/(X84-Y84), "") | AC84: =(Z84-X84) * AA84 -> 0
A85: 12/08/2026 08:53:27 | B85: MAIN | C85: Main Street Capital | D85: 59.03 | O85: TRUE | P85: MAIN,Preço: 59.03,Dist MM20: 6.56%,Momentum: 5.39,RSI: 69.98,ADX: 26.04,ATR: 1.30,RVOL: 1.29,Estado: Forca Consolidada,Entrada: 58.77,Stop: 57.21,Take-Profit: 61.11,Break-Even: 59.94,Qtd: 64.10,Trailing: 57.21,Data: 12/08/2026 08:53:22 | Q85: 59.35 | R85: 58.05 | S85: 56.75 | T85: 60 | U85: Forca Consolidada | V85: MAIN (INTRADAY),Máximo 15h30: 59.35,Estado: Forca Consolidada,Entrada: 58.05,Stop: 56.75,Take-Profit: 60.00,Data: 12/08/2026 15:30:14 | W85: LOSS | X85: 58.76 | Y85: 57.32 | Z85: 57.42 | AA85: 64.1 | AB85: =IF(OR(W85="WIN", W85="LOSS"), (Z85-X85)/(X85-Y85), "") -> -0.93055556 | AC85: =(Z85-X85) * AA85 -> -85.894
A86: 12/08/2026 08:53:11 | B86: ABNB | C86: Airbnb | D86: 184.98 | O86: TRUE | P86: ABNB,Preço: 184.98,Dist MM20: 20.94%,Momentum: 44.93,RSI: 81.64,ADX: 27.38,ATR: 5.40,RVOL: 1.64,Estado: Forca Consolidada,Entrada: 183.90,Stop: 177.42,Take-Profit: 193.62,Break-Even: 188.76,Qtd: 15.43,Trailing: 177.42,Data: 12/08/2026 08:53:10 | Q86: 184.11 | R86: - | S86: - | T86: - | U86: Ignorado - S/ Quebra de Fecho | V86: ABNB,Máximo 15h30: 184.11,Estado: Ignorado - S/ Quebra de Fecho,Data: 12/08/2026 15:30:14 | AB86: =IF(OR(W86="WIN", W86="LOSS"), (Z86-X86)/(X86-Y86), "") | AC86: =(Z86-X86) * AA86 -> 0
A87: 12/08/2026 07:36:04 | B87: AMPL | C87: Amplitude | D87: 12.69 | E87: 11.05 | F87: 12.87 | O87: TRUE | P87: AMPL,Preço: 12.69,Dist MM20: 31.29%,Momentum: 3.95,RSI: 80.68,ADX: 29.90,ATR: 0.65,RVOL: 1.11,Estado: Forca Consolidada,Entrada: 12.56,Stop: 11.78,Take-Profit: 13.73,Break-Even: 13.14,Qtd: 128.21,Trailing: 11.78,Data: 12/08/2026 07:36:03 | Q87: 12.68 | R87: - | S87: - | T87: - | U87: Ignorado - S/ Quebra de Fecho | V87: AMPL,Máximo 15h30: 12.68,Estado: Ignorado - S/ Quebra de Fecho,Data: 12/08/2026 15:30:15 | AB87: =IF(OR(W87="WIN", W87="LOSS"), (Z87-X87)/(X87-Y87), "") | AC87: =(Z87-X87) * AA87 -> 0
A88: 12/08/2026 02:39:41 | B88: DASH | C88: DoorDash | D88: 212 | E88: 206.25 | F88: 216.35 | O88: TRUE | P88: DASH,Preço: 212.00,Dist MM20: 9.09%,Momentum: 34.27,RSI: 65.36,ADX: 25.90,ATR: 8.03,RVOL: 1.02,Estado: Forca Consolidada,Entrada: 210.39,Stop: 200.75,Take-Profit: 224.84,Break-Even: 217.62,Qtd: 10.38,Trailing: 200.75,Data: 12/08/2026 02:39:39 | Q88: 215 | R88: 206.97 | S88: 198.94 | T88: 219.01 | U88: Forca Consolidada | V88: DASH (INTRADAY),Máximo 15h30: 215.00,Estado: Forca Consolidada,Entrada: 206.97,Stop: 198.94,Take-Profit: 219.01,Data: 12/08/2026 15:30:15 | W88: FUGIU | AB88: =IF(OR(W88="WIN", W88="LOSS"), (Z88-X88)/(X88-Y88), "") | AC88: =(Z88-X88) * AA88 -> 0
A89: 11/08/2026 07:42:02 | B89: U | C89: Unity Software Inc | D89: 43.1 | E89: 42.07 | F89: 43.55 | G89: SB | H89: 6.81 | I89: 72.8 | J89: 14.06 | K89: 1,47 | L89: R1 Up | M89: 28 | N89: 45709.328 | O89: TRUE | P89: U,Preço: 43.10,Dist MM20: 30.79%,Momentum: 13.23,RSI: 81.43,ADX: 30.28,ATR: 2.16,RVOL: 1.31,Estado: Forca Consolidada,Entrada: 42.67,Stop: 40.08,Take-Profit: 46.56,Break-Even: 44.62,Qtd: 38.58,Trailing: 40.08,Data: 11/08/2026 07:42:01 | Q89: 43.23 | R89: 41.08 | S89: 38.92 | T89: 44.32 | U89: Forca Consolidada | V89: U (INTRADAY),Máximo 15h30: 43.23,Estado: Forca Consolidada,Entrada: 41.08,Stop: 38.92,Take-Profit: 44.32,Data: 11/08/2026 15:30:33 | AB89: =IF(OR(W89="WIN", W89="LOSS"), (Z89-X89)/(X89-Y89), "") | AC89: =(Z89-X89) * AA89 -> 0
A90: 11/08/2026 07:38:54 | B90: QLYS | C90: Qualys US | D90: 185.8 | E90: 182.09 | F90: 192.73 | M90: 146.06 | N90: 45706.703 | O90: TRUE | P90: QLYS,Preço: 185.80,Dist MM20: 20.09%,Momentum: 42.02,RSI: 75.24,ADX: 34.61,ATR: 9.30,RVOL: 1.08,Estado: Forca Consolidada,Entrada: 183.94,Stop: 172.78,Take-Profit: 200.68,Break-Even: 192.31,Qtd: 8.96,Trailing: 172.78,Data: 11/08/2026 07:38:53 | Q90: 187.41 | R90: 178.11 | S90: 168.81 | T90: 192.06 | U90: Forca Consolidada | V90: QLYS (INTRADAY),Máximo 15h30: 187.41,Estado: Forca Consolidada,Entrada: 178.11,Stop: 168.81,Take-Profit: 192.06,Data: 11/08/2026 15:30:34 | W90: WIN | X90: 182.68 | Y90: 172.78 | Z90: 184.1 | AA90: 8.96 | AB90: =IF(OR(W90="WIN", W90="LOSS"), (Z90-X90)/(X90-Y90), "") -> 0.14343434 | AC90: =(Z90-X90) * AA90 -> 12.7232
A91: 11/08/2026 06:52:34 | B91: NET | C91: Cloudflare US | D91: 310.59 | E91: 290.49 | F91: 312.66 | H91: -11 | I91: 54.75 | J91: 29.18 | K91: 6.52 | L91: S1 Up | M91: 184.62 | N91: 45853.692 | O91: TRUE | P91: NET,Preço: 310.59,Dist MM20: 11.37%,Momentum: 38.28,RSI: 68.54,ADX: 26.99,ATR: 16.56,RVOL: 1.82,Estado: Forca Consolidada,Entrada: 307.28,Stop: 287.41,Take-Profit: 337.09,Break-Even: 322.18,Qtd: 5.03,Trailing: 287.41,Data: 11/08/2026 06:52:33 | Q91: 310.13 | R91: - | S91: - | T91: - | U91: Ignorado - S/ Quebra de Fecho | V91: NET,Máximo 15h30: 310.13,Estado: Ignorado - S/ Quebra de Fecho,Data: 11/08/2026 15:30:35 | W91: WIN | X91: 303.99 | Y91: 287.41 | Z91: 305.63 | AA91: 5.03 | AB91: =IF(OR(W91="WIN", W91="LOSS"), (Z91-X91)/(X91-Y91), "") -> 0.098914355 | AC91: =(Z91-X91) * AA91 -> 8.2492
